Workbook
Name SlicerCache_Table_1_Col_1: #N/A
Name SlicerCache_Table_3_Col_10: #N/A
Name SlicerCache_Table_4_Col_10: #N/A
Name SlicerCache_Table_5_Col_10: #N/A

Sheet Resumen
A1: CC | B1: Ppto | C1: Ppto ajustado | D1: ppto doc. | E1: Saldo | F1: % | H1: KELLUN | I1: CON TRASPASO | J1: DIFERENCIA | K1: 46149
A2: 409-1722 REMODELACIONES-OBRAS | B2: =SUMIF('Ppto 2026'!$D:$D,A2,'Ppto 2026'!$O:$O) -> 730355177 | C2: 822951860 | D2: =SUMIF('Ppto 2026'!$D:$D,A2,'Ppto 2026'!$P:$P) -> 576590671 | E2: =C2-D2 -> 246361189 | F2: =D2/B2 -> 0.78946612 | H2: 264211915 | I2: =H2+B37 -> 264211915 | J2: =I2-E2 -> 17850726 | K2: =(J2/E2) -> 0.072457541
A3: 409-5243 INSTITUTO TECNOLOGICO | B3: =SUMIF('Ppto 2026'!$D:$D,A3,'Ppto 2026'!$O:$O) -> 1641182758 | C3: ='Ppto 2026'!O11 -> 1641182758 | D3: =SUMIF('Ppto 2026'!$D:$D,A3,'Ppto 2026'!$P:$P) -> 1577697306 | E3: =C3-D3 -> 63485452 | F3: =D3/B3 -> 0.96131726 | H3: 60488457 | I3: =B45+H3 -> 60488457 | J3: =I3-E3 -> -2996995 | K3: =(J3/E3) -> -0.047207587
A4: 409-5503 PROYECTO TÚNEL SALIDA Y CALLE PROLONGACIÓN CJPII | B4: =SUMIF('Ppto 2026'!$D:$D,A4,'Ppto 2026'!$O:$O) -> 0 | D4: =SUMIF('Ppto 2026'!$D:$D,A4,'Ppto 2026'!$P:$P) -> 0 | E4: =C4-D4 -> 0 | F4: =D4/B4 -> #DIV/0! | J4: =H4-E4 -> 0 | K4: =(J4/E4) -> #DIV/0!
A5: 409-5506 - CASINO VRAE | B5: =SUMIF('Ppto 2026'!$D:$D,A5,'Ppto 2026'!$O:$O) -> 995200912 | C5: 995200912 | D5: =SUMIF('Ppto 2026'!$D:$D,A5,'Ppto 2026'!$P:$P) -> 957708957 | E5: =C5-D5 -> 37491955 | F5: =D5/B5 -> 0.96232725 | H5: 133118933 | I5: =B53+H5 -> 133118933 | J5: =H5-E5 -> 95626978 | K5: =(J5/E5) -> 2.5505999
A6: 409-6293 - CENTRO RECREACIONAL SAN NICOLAS | B6: 40000000 | C6: =B6 -> 40000000 | D6: =SUMIF('Ppto 2026'!$D:$D,A6,'Ppto 2026'!$P:$P) -> 2196742 | E6: =C6-D6 -> 37803258 | H6: $ 40.000.000
I8: =C5+C3+C2 -> 3459335530 | J8: =I8*0.05 -> 1.7296678e+08
A35: Regularización gastos
A37: 409-1722-REMODELACIONES-OBRAS
A38: Detalle | B38: Monto | D38: Obs. | E38: Estado
A39: SP:11753 - OC:10964 - FCAEL. 74427 - MELMAN SPA | B39: 47267344 | D39: Ppto. 2025 | E39: TRUE
A45: 409-5243 INSTITUTO TECNOLOGICO
A46: Detalle | B46: Monto | D46: Obs. | E46: Estado
A47: SP:9942 - OC:9031 - FCAEL. 499 - LUIS SAEZ ALLENDE | B47: 110752237 | D47: Ppto. 2025 | E47: TRUE
A53: 409-5506 - CASINO VRAE | B53: =B55+B56+B57 -> 0
A54: Detalle | B54: Monto | D54: Obs. | E54: Estado
E55: FALSE

Sheet Proyección
L1: =L2/'Ppto 2026'!$P$3 -> 0.00055517045 | M1: =M2/'Ppto 2026'!$P$3 -> 0.0016306529 | N1: =N2/'Ppto 2026'!$P$3 -> 0.012649957 | O1: =O2/'Ppto 2026'!$P$3 -> 0.015109029 | P1: =P2/'Ppto 2026'!$P$3 -> 0.00064107442 | Q1: =Q2/'Ppto 2026'!$P$3 -> 0 | R1: =R2/'Ppto 2026'!$P$3 -> 0 | S1: =S2/'Ppto 2026'!$P$3 -> 0.0012674041 | ... BM1: =BM2/'Ppto 2026'!$P$3 -> 0
L2: =SUM(L5:L79) -> 1905200 | M2: =SUM(M5:M79) -> 5595975 | N2: =SUM(N5:N79) -> 43411350 | O2: =SUM(O5:O79) -> 51850242 | P2: =SUM(P5:P79) -> 2200000 | Q2: =SUM(Q5:Q79) -> 0 | R2: =SUM(R5:R79) -> 0 | S2: =SUM(S5:S79) -> 4349400 | ... BM2: =SUM(BM5:BM79) -> 0
L3: Semana 1-Ene | M3: Semana 2-Enero | N3: Semana 3-Ene | O3: Semana 4-Ene | P3: Semana 1-Feb | Q3: Semana 2-Feb | R3: Semana 3-Febr | S3: Semana 4-Feb | T3: Semana 1-Mar | U3: Semana 2-Marz | V3: Semana 3-Marzo | W3: Semana 4-Mar | X3: Semana 1-Abri | Y3: Semana 2-Abri | Z3: Semana 3-Abril | AA3: Semana 4-Abril | AB3: Semana 5-Abri | AC3: Semana 1-May | AD3: Semana 2-Mayo | AE3: Semana 3-Mayo | AF3: Semana 4-Mayo | AG3: Semana 1-Jun | AH3: Semana 2-Jun | AI3: Semana 3-Junio | AJ3: Semana 4-Junio | AK3: Semana 1-Juli | AL3: Semana 2-Jul | AM3: Semana 3-Julio | AN3: Semana 4-Julio | AO3: Semana 5-Juli | AP3: Semana 1-Ago | AQ3: Semana 2-Agos | AR3: Semana 3-Agos | AS3: Semana 4-Agos | AT3: Semana 1-Sept | AU3: Semana 2-Septi | AV3: Semana 3-Septi | AW3: Semana 4-Septi | AX3: Semana 5-Septi | AY3: Semana 1-Octu | AZ3: Semana 2-Oct | BA3: Semana 3-Octu | BB3: Semana 4-Octu | BC3: Semana 5-Octu | BD3: Semana 1-Nov | BE3: Semana 2-Novi | BF3: Semana 3-Novi | BG3: Semana 4-Novi | BH3: Semana 1-Dic | BI3: Semana 2-Dic | BJ3: Semana 3-Dici | BK3: Semana 4-Dici | BL3: Semana 5-Dici | BM3: Semana 1-Ene
A4: CC | B4: Año | C4: OP | D4: OC | E4: Descripción | F4: Monto | G4: Pagado | H4: Saldo | I4: Columna 1 | J4: Columna 2 | K4: Δ | L4: 05 al 11 | M4: 12 al 18 | N4: 19 al 25 | O4: 26 al 01 | P4: 02 al 08 | Q4: 09 al 15 | R4: 16 al 22 | S4: 23 al 01 | T4: 02 al 08 2 | U4: 09 al 15 2 | V4: 16 al 22 2 | W4: 23 al 29 | X4: 30 al 05 | Y4: 06 al 12 | Z4: 13 al 19 | AA4: 20 al 26 | AB4: 27 al 03 | AC4: 04 al 10 | AD4: 11 al 17 | AE4: 18 al 24 | AF4: 25 al 31 | AG4: 01 al 07 | AH4: 08 al 14 | AI4: 15 al 21 | AJ4: 22 al 28 | AK4: 29 al 05 | AL4: 06 al 12 2 | AM4: 13 al 19 2 | AN4: 20 al 26 2 | AO4: 27 al 02 | AP4: 03 al 09 | AQ4: 10 al 16 | AR4: 17 al 23 | AS4: 24 al 30 | AT4: 31al 06 | AU4: 07 al 13 | AV4: 14 al 20 | AW4: 21 al 27 | AX4: 28 al 04 | AY4: 05 al 11 2 | AZ4: 12 al 18 2 | BA4: 19 al 25 2 | BB4: 26 al 01 2 | BC4: 02 al 08 3 | BD4: 09 al 15 3 | BE4: 16 al 22 3 | BF4: 23 al 29 2 | BG4: 24 al 30 2 | BH4: 30 al 06 | BI4: 07 al 13 2 | BJ4: 14 al 20 2 | BK4: 21 al 27 2 | BL4: 28 al 03 | BM4: 05 al 11 3
A5: 409-5243 INSTITUTO TECNOLOGICO | B5: 2024 | D5: 8022 | E5: Edificio Ingeniería (ex TEC) | F5: 4408299870 | G5: =200000000+214576722+451540786+242312734+224174189+155623352+252294712+201102519+155455601+218152853+324983774+366374243+153086824+152511772+102298014+203742698+184685827+170139342 -> 3973055962 | H5: =F5-G5 -> 435243908 | I5: LSA INGENIERIA Y CONSTRUCCIÓN E.I.R.L. | J5: J.Solis de Ovando | K5: =F5-G5-(SUM(L5:BM5)) -> 0 | T5: 185222684 | AC5: 250021224
A6: 409-5243 INSTITUTO TECNOLOGICO | B6: 2025 | D6: 9031 | E6: AO N°1 Edificio Ingeniería (ex TEC) | F6: 456637235 | G6: =81204459+170270732+89858090+110752237 -> 452085518 | H6: =F6-G6 -> 4551717 | I6: LSA INGENIERIA Y CONSTRUCCIÓN E.I.R.L. | J6: J.Solis de Ovando | K6: =F6-G6-(SUM(L6:BM6)) -> 0 | AD6: 4551717
A7: 409-5243 INSTITUTO TECNOLOGICO | B7: 2024 | D7: 4075 | E7: Arquitectura Edificio Ingeniería (ex TEC) | F7: 86080359 | G7: =24432144+7173363+12912054+7173363 -> 51690924 | H7: =F7-G7 -> 34389435 | I7: SOCIEDAD DE PROFESIONALES BAIXAS Y DEL RIO ARQUITECTOS LIMITADA | J7: J.Solis de Ovando | K7: =F7-G7-(SUM(L7:BM7)) -> 14304018 | AA7: 7173363 | AF7: 8608036.1 | AJ7: 4304018
A8: 409-5243 INSTITUTO TECNOLOGICO | B8: 2025 | D8: 13112 | E8: Armado muebles Edificio de Ingenieria UCT (exTEC) | F8: 13917050 | G8: 5566820 | H8: =F8-G8 -> 8350230 | I8: ESPACIO MUEBLES LIMITADA | J8: J.Solis de Ovando | K8: =F8-G8-(SUM(L8:BM8)) -> 0 | O8: 5566820 | AD8: 2783410
A9: 409-5243 INSTITUTO TECNOLOGICO | B9: 2025 | D9: 13810 | E9: ccess point y switch Edificio de Ingenieria UCT (exTEC) | F9: 85398978 | H9: =F9-G9 -> 85398978 | J9: M.Zurita | K9: =F9-G9-(SUM(L9:BM9)) -> 85398978
A10: 409-5243 INSTITUTO TECNOLOGICO | B10: 2026 | C10: 91 | D10: 66 | E10: AUMENTO DE OBRA OC. 9031 CONSTRUCCION EDIFICIO INGENIERIA CRC (EX TEC) JUAN IGNACIO SOLIS DE OVANDO | F10: 664691208 | G10: =186646382+118263881+132505939 -> 437416202 | H10: =F10-G10 -> 227275006 | I10: LSA INGENIERIA Y CONSTRUCCIÓN E.I.R.L. | J10: J.Solis de Ovando | K10: =F10-G10-(SUM(L10:BM10)) -> 18000001 | T10: 209275005
A11: 409-5243 INSTITUTO TECNOLOGICO | B11: 2026 | C11: 699 | D11: 703 | E11: INSTALACIÓN DE ACCESS POINT EN EDIFICIO EX TEC (MAURICIO ZURITA) | F11: 2416890 | H11: =F11-G11 -> 2416890 | I11: GYG SERVICIOS | J11: M.Zurita | K11: =F11-G11-(SUM(L11:BM11)) -> 0 | X11: 2416890
A12: 409-5243 INSTITUTO TECNOLOGICO | B12: 2026 | C12: 799 | D12: 864 | E12: SOPORTES PARA INSTALACION DE TELEVISORES SALAS DE REUNIONES, SALAS DE CLASES Y LABORARIOS NUEVO EDIFICIO INGENIERIA (ARTURO MEZA) | F12: 5537070 | H12: =F12-G12 -> 5537070 | I12: GYG SERVICIOS | J12: A. Meza | K12: =F12-G12-(SUM(L12:BM12)) -> 0 | Z12: 5537070
A13: 409-5243 INSTITUTO TECNOLOGICO | B13: 2026 | C13: 788 | D13: 731 | E13: HABILITACION MOBILIARIO OFICINAS 3ER NIVEL EDIFICIO INGENIERIA CRC10 (JUAN IGNACIO SOLIS) | F13: 25523715 | H13: =F13-G13 -> 25523715 | I13: ESPACIO MUEBLES LIMITADA | J13: J.Solis de Ovando | K13: =F13-G13-(SUM(L13:BM13)) -> 1.5 | O13: 7657114.5 | T13: 17866599
A14: 409-5243 INSTITUTO TECNOLOGICO | B14: 2026 | C14: 789 | D14: 732 | E14: MUEBLES HABILITACION LABORATORIO DE COMPUTACION EDIFICIO INGENIERIA CRC10 (JUAN IGNACIO SOLIS) | F14: 8425200 | H14: =F14-G14 -> 8425200 | I14: ESPACIO MUEBLES LIMITADA | J14: J.Solis de Ovando | K14: =F14-G14-(SUM(L14:BM14)) -> 0 | O14: 2527560 | U14: 5897640
A15: 409-5243 INSTITUTO TECNOLOGICO | B15: 2026 | C15: 1473 | D15: 1578 | E15: RACK PARA DATA CENTER NUEVO EDIFICIO FACULTAD DE INGENIERIA (ARTURO MEZA)PROVEEDOR ADJUDICADO CUMPLE CON TODAS LAS ESPECIFICACIONES TECNICAS. | F15: 3704470 | H15: =F15-G15 -> 3704470 | I15: GYG SERVICIOS | J15: A. Meza | K15: =F15-G15-(SUM(L15:BM15)) -> 0 | W15: 3704470
A16: 409-5243 INSTITUTO TECNOLOGICO | B16: 2026 | C16: 1770 | D16: 1786 | E16: TELEVISORES PARA SALAS DE CLASES, REUNIONES Y LABORATORIOS NUEVO EDIFICIO INGENIERIA (ARTURO MEZA) | F16: 17043200 | H16: =F16-G16 -> 17043200 | I16: GYG SERVICIOS | J16: A. Meza | K16: =F16-G16-(SUM(L16:BM16)) -> 0 | X16: 17043200
A17: 409-5243 INSTITUTO TECNOLOGICO | B17: 2026 | C17: 1803 | D17: 1788 | E17: MOBILITARIO INTERIOR CLOSET ESCALA CON CERRADURA PISOS 1,2,3 ED. INGENIERIA CRC10 (JUAN IGNACION SOLIS) | F17: 856800 | H17: =F17-G17 -> 856800 | I17: ESPACIO MUEBLES LIMITADA | J17: J.Solis de Ovando | K17: =F17-G17-(SUM(L17:BM17)) -> 0 | AA17: 856800
A18: 409-5243 INSTITUTO TECNOLOGICO | B18: 2026 | C18: 2055 | D18: 1991 | E18: PIZARRAS MOVIL, HABILITACION SALA DE ESTUDIOS EDIFICIO INGENIERIA CRC10 (JUAN IGNACION SOLIS) | F18: 1266755 | H18: =F18-G18 -> 1266755 | I18: MELMAN SPA | J18: J.Solis de Ovando | K18: =F18-G18-(SUM(L18:BM18)) -> 0 | AB18: 1266755
A19: 409-5243 INSTITUTO TECNOLOGICO | B19: 2026 | E19: Otros | F19: 17459520 | H19: =F19-G19 -> 17459520 | K19: =F19-G19-(SUM(L19:BM19)) -> 17459520
A20: 409-5243 INSTITUTO TECNOLOGICO | B20: 2026 | C20: 2071 | D20: 2025 | E20: EMPAVONADO DE OFICINAS Y CASINO EDIFICIO CRC10 (JUAN IGNACIOS SOLIS) | F20: 3599892 | H20: =F20-G20 -> 3599892 | J20: J.Solis de Ovando | K20: =F20-G20-(SUM(L20:BM20)) -> 0 | AA20: 3599892
A21: 409-5243 INSTITUTO TECNOLOGICO | B21: 2026 | C21: 2497 | D21: 2421 | E21: MODIFICACION DE ENCHUFES Y HDMI PARA INSTALACION DE TV EN SALAS DE CLASES EDIFICIO FAC. DE INGENIERIA (ARTURO MEZA) | F21: 799442 | H21: =F21-G21 -> 799442 | I21: GYG SERVICIOS | J21: A. Meza | K21: =F21-G21-(SUM(L21:BM21)) -> 0 | AA21: 799442
A22: 409-5243 INSTITUTO TECNOLOGICO | B22: 2026 | C22: 2714 | D22: 2483 | E22: GRUPO ELECTROGENO EDIFICIO CRC10 FACULTAD DE INGENIERIA (ARTURO MEZA) | F22: 15170428 | H22: =F22-G22 -> 15170428 | I22: ELECTROPOWER | J22: A. Meza | K22: =F22-G22-(SUM(L22:BM22)) -> 0 | AD22: 15170428
A23: 409-5243 INSTITUTO TECNOLOGICO | B23: 2026 | C23: 2809 | E23: HABILITACION MOBILIARIO LABORATORIO DE PRE Y POST GRADO FACULTAD DE INGENIERIA (JUAN IGNACION SOLIS) | F23: 28468370 | H23: =F23-G23 -> 28468370 | I23: ESPACIO MUEBLES LIMITADA | J23: J.Solis de Ovando | K23: =F23-G23-(SUM(L23:BM23)) -> 0 | AA23: 8540511 | AE23: 19927859
A24: 409-5243 INSTITUTO TECNOLOGICO | B24: 2026 | C24: 208 | D24: 1940 | E24: FCAEL. 4621 - ROXANA ELIANA RI | F24: 1796409 | H24: =F24-G24 -> 1796409 | K24: =F24-G24-(SUM(L24:BM24)) -> 0 | W24: 1796409
A25: 409-5243 INSTITUTO TECNOLOGICO | B25: 2026 | E25: PAGO PERMISO EDIFICACION | F25: 10000000 | H25: =F25-G25 -> 10000000 | K25: =F25-G25-(SUM(L25:BM25)) -> 0 | AC25: 10000000
A26: 409-5243 INSTITUTO TECNOLOGICO | B26: 2026 | E26: DEA Y EXTINTORES | F26: =2019430+1302683 -> 3322113 | H26: =F26-G26 -> 3322113 | K26: =F26-G26-(SUM(L26:BM26)) -> 0 | AD26: =2019430+1302683 -> 3322113
A27: 409-5243 INSTITUTO TECNOLOGICO | B27: 2026 | E27: AUMENTO DE OBRA N3 | F27: 110000000 | H27: =F27-G27 -> 110000000 | K27: =F27-G27-(SUM(L27:BM27)) -> 0 | AC27: 110000000
A28: 409-5243 INSTITUTO TECNOLOGICO | B28: 2026 | E28: TRABAJOS VIALES POR IMIV | F28: 30000000 | H28: =F28-G28 -> 30000000 | K28: =F28-G28-(SUM(L28:BM28)) -> 0 | AG28: 30000000
A29: 409-5243 INSTITUTO TECNOLOGICO | B29: 2026 | E29: BODEGA RESPEL Y SUSPEL | F29: 15000000 | H29: =F29-G29 -> 15000000 | K29: =F29-G29-(SUM(L29:BM29)) -> 0 | AG29: 15000000
A30: 409-5243 INSTITUTO TECNOLOGICO | B30: 2026 | E30: MUEBLES PENDIENTES SALAS, OFICINAS Y AUDITORIOS | F30: 7500000 | H30: =F30-G30 -> 7500000 | K30: =F30-G30-(SUM(L30:BM30)) -> 0 | AG30: 7500000
A31: 409-5243 INSTITUTO TECNOLOGICO | B31: 2026 | E31: SEÑALETICA CENTRO RECREACIONAL CURACAUTIN (DAVID SILVA) | F31: 12000000 | H31: =F31-G31 -> 12000000 | K31: =F31-G31-(SUM(L31:BM31)) -> 0 | AC31: 12000000
A32: 409-5243 INSTITUTO TECNOLOGICO | B32: 2026 | E32: REVISORA DE ARQUITECTURA POR MP PROYECTO | F32: 4000000 | H32: =F32-G32 -> 4000000 | K32: =F32-G32-(SUM(L32:BM32)) -> 0 | AP32: 4000000
A33: 409-1722 REMODELACIONES-OBRAS | B33: 2025 | D33: 3946 | E33: Cabañas Curacautín | F33: 316857372 | G33: =95057212+27725020+27725020+75253626+75253626 -> 301014504 | H33: =F33-G33 -> 15842868 | I33: CONSTRUCTORA RUKATAMI | J33: D.Silva | K33: =F33-G33-(SUM(L33:BM33)) -> -15842869 | AA33: 15842869 | BH33: 15842869
A34: 409-1722 REMODELACIONES-OBRAS | B34: 2025 | D34: 7844 | E34: Regularización PE cjp07/cjp10/cjp104 | F34: 10833477 | G34: 2540943 | H34: =F34-G34 -> 8292534 | J34: C.Correa | K34: =F34-G34-(SUM(L34:BM34)) -> 0 | AF34: 4146267 | AO34: 4146267
A35: 409-1722 REMODELACIONES-OBRAS | B35: 2025 | D35: 10964 | E35: Mobiliario Biblioteca CSF02 etapa 2 y 3 | F35: 67524777 | G35: 20257433 | H35: =F35-G35 -> 47267344 | J35: L. Rios | K35: =F35-G35-(SUM(L35:BM35)) -> 0.1 | Z35: 47267344
A36: 409-1722 REMODELACIONES-OBRAS | B36: 2025 | D36: 11875 | E36: Remodelación Dirección General Estudiantil CSF | F36: 24367129 | G36: =7310138+7421966 -> 14732104 | H36: =F36-G36 -> 9635025 | I36: CONSTRUCTORA INGETRAPP | J36: J.Solis de Ovando | K36: =F36-G36-(SUM(L36:BM36)) -> 0 | O36: 9635025
A37: 409-1722 REMODELACIONES-OBRAS | B37: 2025 | D37: 13310 | E37: Cortinas Cabañas Curacautín | F37: 4760000 | G37: =4760000*0.3 -> 1428000 | H37: =F37-G37 -> 3332000 | J37: F.Anselme | K37: =F37-G37-(SUM(L37:BM37)) -> 0 | O37: 3332000
A38: 409-1722 REMODELACIONES-OBRAS | B38: 2025 | D38: 10880 | E38: Calculo Casino CRC | F38: 2808400 | H38: =F38-G38 -> 2808400 | J38: J.Solis de Ovando | K38: =F38-G38-(SUM(L38:BM38)) -> 0 | U38: 2808400
A39: 409-1722 REMODELACIONES-OBRAS | B39: 2025 | D39: 10877 | E39: Proyecto sanitario, pavimentación y topografía casino | F39: 2380000 | H39: =F39-G39 -> 2380000 | J39: J.Solis de Ovando | K39: =F39-G39-(SUM(L39:BM39)) -> 0 | U39: 2380000
A40: 409-1722 REMODELACIONES-OBRAS | B40: 2025 | D40: 12560 | E40: Diseño proyecto sanitario edificio Pabellón Docente | F40: 1880200 | H40: =F40-G40 -> 1880200 | J40: C.Correa | K40: =F40-G40-(SUM(L40:BM40)) -> 0 | AB40: 1880200
A41: 409-1722 REMODELACIONES-OBRAS | B41: 2025 | D41: 5283 | E41: COMPRAS DE ACCESOS POINT, INSTALACION DISPOSITIVOS WIFI, OBRA MENORES SALA DOCTORADO HATCHERY CJP04, MENCHACA LIRA CML01 Y CONSTRUCCION POSTERIOR EDIFICIO A CSF16 | F41: 2519730 | H41: =F41-G41 -> 2519730 | J41: M.Zurita | K41: =F41-G41-(SUM(L41:BM41)) -> 2519730
A42: 409-5506 - CASINO VRAE | B42: 2026 | C42: 1434 | D42: 1426 | E42: Nuevo Edificio Casino CRC | F42: 855200912 | H42: =F42-G42 -> 855200912 | I42: LSA INGENIERIA Y CONSTRUCCIÓN E.I.R.L. | J42: J.Solis de Ovando | K42: =F42-G42-(SUM(L42:BM42)) -> -1 | X42: 144479558 | AB42: 69931126 | AG42: 167082324 | AK42: 155127189 | AO42: 178457507 | AT42: 97363163 | AX42: 42760046
A43: 409-5506 - CASINO VRAE | B43: 2026 | E43: Otros | F43: 14283000 | H43: =F43-G43 -> 14283000 | K43: =F43-G43-(SUM(L43:BM43)) -> 14283000
A44: 409-5506 - CASINO VRAE | B44: 2026 | E44: CASINO CRC11 (VRAE) HABILITACIÓN | F44: 100000000 | H44: =F44-G44 -> 100000000 | K44: =F44-G44-(SUM(L44:BM44)) -> 0 | AO44: 40000000 | AT44: 60000000
A45: 409-1722 REMODELACIONES-OBRAS | B45: 2026 | C45: 276 | D45: 331 | E45: AUMENTO DE OBRA OC 8157 ADICIONALES OBRAS POST CONTRUCCION SEGUN DETALLE (CRISTOBAL CORREA) | F45: 9440482 | H45: =F45-G45 -> 9440482 | I45: ROMO Y CADI LIMITADA | J45: C.Correa | K45: =F45-G45-(SUM(L45:BM45)) -> 0 | AC45: 9440482
A46: 409-1722 REMODELACIONES-OBRAS | B46: 2026 | C46: 277 | D46: 361 | E46: AUMENTO DE OBRA OC.13558 ADICIONAL MUEBLES HOSPITAL DE SIMULACION CLINICA (CRISTOBAL CORREA) | F46: 5595975 | H46: =F46-G46 -> 5595975 | I46: ESPACIO MUEBLES LIMITADA | J46: C.Correa | K46: =F46-G46-(SUM(L46:BM46)) -> 0 | M46: 5595975
A47: 409-1722 REMODELACIONES-OBRAS | B47: 2026 | C47: 278 | D47: 233 | E47: AUMENTO DE OBRA OC.3946-2025 CONSTRUCCIÓN CABAÑAS CENTRO RECREACIONAL CURACAUTIN. RESPONSABLE: DAVID SILVA. SEGUN COTIZACION N 522 | F47: 43411350 | H47: =F47-G47 -> 43411350 | I47: CONSTRUCTORA RUKATAMI | J47: D.Silva | K47: =F47-G47-(SUM(L47:BM47)) -> 0 | N47: 43411350
A48: 409-1722 REMODELACIONES-OBRAS | B48: 2026 | C48: 503 | D48: 449 | E48: AUMENTO DE OBRA OC.11875 REMODELACION OFICINAS Y ATENCION A PUBLICO CSF01 ED. CAEP (JUAN IGNACIO SOLIS) | F48: 1522909 | H48: =F48-G48 -> 1522909 | I48: CONSTRUCTORA INGETRAPP | J48: J.Solis de Ovando | K48: =F48-G48-(SUM(L48:BM48)) -> 0 | T48: 1522909
A49: 409-1722 REMODELACIONES-OBRAS | B49: 2026 | C49: 651 | D49: 633 | E49: INSTALACION EQUIPO DE AIRE ACONDICIONADO , MAS TRASLADO DE DOS EQUIPOS, CSF10_200 CREDITO Y RECAUDACION (LEONOR RIOS) | F49: 1997415 | H49: =F49-G49 -> 1997415 | I49: FLAVIA OYARZUN SOTO | J49: L. Rios | K49: =F49-G49-(SUM(L49:BM49)) -> 0 | T49: 1997415
A50: 409-1722 REMODELACIONES-OBRAS | B50: 2026 | C50: 666 | D50: 663 | E50: INSTALACION SERVICIOS DE INTERNET SATELITAL CENTRO RECREACIONAL CURACAUTIN (ARTURO MEZA) | F50: 4699310 | H50: =F50-G50 -> 4699310 | I50: GYG SERVICIOS | J50: M.Zurita | K50: =F50-G50-(SUM(L50:BM50)) -> 0 | AB50: 4699310
A51: 409-1722 REMODELACIONES-OBRAS | B51: 2026 | C51: 674 | D51: 705 | E51: SEÑALETICA CENTRO RECREACIONAL CURACAUTIN (DAVID SILVA) | F51: 4921911 | H51: =F51-G51 -> 4921911 | I51: DSIETE SPA | J51: D.Silva | K51: =F51-G51-(SUM(L51:BM51)) -> 0 | T51: 4921911
A52: 409-1722 REMODELACIONES-OBRAS | B52: 2026 | C52: 678 | D52: 738 | E52: MOBILIARIO HABILITACION LABORATORIO COMPUTACIÓN CRC16_210 (CRISTOBAL CORREA) | F52: 4405800 | H52: =F52-G52 -> 4405800 | I52: MULTIMUEBLES | J52: C.Correa | K52: =F52-G52-(SUM(L52:BM52)) -> 0 | T52: 4405800
A53: 409-1722 REMODELACIONES-OBRAS | B53: 2026 | C53: 800 | D53: 733 | E53: CONSTRUCCION DE PAÑOL Y REHABILITACION DE FRONTIS CRC18 (JUAN IGNACIO SOLIS) | F53: 23807821 | H53: =F53-G53 -> 23807821 | I53: CONSTRUCTORA ALPLAS SPA | J53: J.Solis de Ovando | K53: =F53-G53-(SUM(L53:BM53)) -> 0 | O53: 7142346.3 | T53: 10713519 | Z53: 5951955.7
A54: 409-1722 REMODELACIONES-OBRAS | B54: 2026 | C54: 803 | D54: 869 | E54: REMODELACION PROYECTO ELECTRICO ETAPA 2 Y 3 EDIFICIO BIBLIOTECA, LABORATORIO DE COMPUTACION CSF02-311/CSF02_321 (ARTURO MEZA) | F54: 30530278 | H54: =F54-G54 -> 30530278 | I54: ELEKTRICA | J54: M.Zurita | K54: =F54-G54-(SUM(L54:BM54)) -> 0 | T54: 24424223 | AC54: 6106055
A55: 409-1722 REMODELACIONES-OBRAS | B55: 2026 | E55: AUMENTO DE OBRA REMODELACION PROYECTO ELECTRICO ETAPA 2 Y 3 EDIFICIO BIBLIOTECA, LABORATORIO DE COMPUTACION CSF02-311/CSF02_321 | F55: 8315145 | H55: =F55-G55 -> 8315145 | I55: ELEKTRICA | J55: M.Zurita | K55: =F55-G55-(SUM(L55:BM55)) -> 0 | AA55: 8315145
A56: 409-1722 REMODELACIONES-OBRAS | B56: 2026 | C56: 796 | D56: 752 | E56: ADECUACION DE ESPACIOS PARA OFICINAS CPH02 ESPACIOS EX LABORATORIO DE SUELOS (PHILLIPPI B) (JUAN IGNACIO SOLIS) | F56: 53297921 | H56: =F56-G56 -> 53297921 | I56: CONSTRUCTORA INGETRAPP | J56: J.Solis de Ovando | K56: =F56-G56-(SUM(L56:BM56)) -> 0 | O56: 15989376 | T56: 21319172 | AA56: 15989373
A57: 409-1722 REMODELACIONES-OBRAS | B57: 2026 | C57: 794 | D57: 861 | E57: CONSTRUCCION BICICLETERO CAMPUS LUIS RIVAS DEL CANTO , COSTADO CASETA GUARDIA (ISABEL RIQUELME) | F57: 16082457 | H57: =F57-G57 -> 16082457 | I57: GATICAR SPA | J57: I. Riquelme | K57: =F57-G57-(SUM(L57:BM57)) -> 0 | T57: 16082457
A58: 409-1722 REMODELACIONES-OBRAS | B58: 2026 | C58: 791 | D58: 858 | E58: REPARACION Y MANTENCION DE ESTRUCTURAS DE MADELA LAMINADA EDIFICO CSF14, CSF15 Y CSF16 (DAVID SILVA) | F58: 94737758 | H58: =F58-G58 -> 94737758 | I58: AVANTI LTDA | J58: D.Silva | K58: =F58-G58-(SUM(L58:BM58)) -> 0 | U58: 68426229 | AB58: 26311529
A59: 409-1722 REMODELACIONES-OBRAS | B59: 2026 | E59: AUMENTO DE OBRA REVESTIMIENTO VIGAS LADO NORTE | F59: 8504097 | H59: =F59-G59 -> 8504097 | I59: AVANTI LTDA | J59: D.Silva | K59: =F59-G59-(SUM(L59:BM59)) -> 0 | AC59: 8504097
A60: 409-1722 REMODELACIONES-OBRAS | B60: 2026 | C60: 792 | D60: 859 | E60: MEJORAMIENTO TERMICO DE CUBIERTA SEGUNDO NIVEL EDIFICIO CRC05 (DAVID SILVA) | F60: 44864047 | H60: =F60-G60 -> 44864047 | I60: CONSTRUCTORA IGECE LIMITADA | J60: D.Silva | K60: =F60-G60-(SUM(L60:BM60)) -> 0 | U60: 40377642 | AB60: 4486405
A61: 409-1722 REMODELACIONES-OBRAS | B61: 2026 | C61: 793 | D61: 860 | E61: REMODELACION LABORATORIO COMPUTACION CRC16_210 (ARTURO MEZA) | F61: 10154673 | H61: =F61-G61 -> 10154673 | I61: INGERTEMUCO INGENIERIA SPA | J61: A. Meza | K61: =F61-G61-(SUM(L61:BM61)) -> 0 | X61: 10154673
A62: 409-1722 REMODELACIONES-OBRAS | B62: 2026 | C62: 1138 | D62: 1819 | E62: MEJORAMIENTO CAMARINES, DUCHAS GIMNASIO CAMPUS SAN FRANCISCO EDIFICIO 15 (DAVID SILVA) | F62: 19801637 | H62: =F62-G62 -> 19801637 | I62: ROMO Y CADI LIMITADA | J62: D.Silva | K62: =F62-G62-(SUM(L62:BM62)) -> 0 | X62: 19801637
A63: 409-1722 REMODELACIONES-OBRAS | B63: 2026 | C63: 1223 | D63: 1230 | E63: INSTALACIÓN DE CANAL DE AGUAS LLUVIAS Y POLICARBONATO EN PARED TRAS ENCHUFES BICICLETERO CAMPUS LUIS RIVAS DEL CANTO (FELIPE ANSELME) | F63: 511700 | H63: =F63-G63 -> 511700 | I63: GATICAR SPA | J63: I. Riquelme | K63: =F63-G63-(SUM(L63:BM63)) -> 0 | U63: 511700
A64: 409-1722 REMODELACIONES-OBRAS | B64: 2026 | C64: 1475 | D64: 1475 | E64: ASESORIAS CES, CERTIFICACION EDIFICIOS SUSTENTABLES PABELLON DOCENTE Y HOSPITAL DE SIMULACION (CRISTOBAL CORREA) | F64: 15015909 | H64: =F64-G64 -> 15015909 | I64: 88 ARQUITECTOS LIMITADA | J64: C.Correa | K64: =F64-G64-(SUM(L64:BM64)) -> 0 | V64: 12870779 | AH64: 2145130
A65: 409-1722 REMODELACIONES-OBRAS | B65: 2026 | C65: 1806 | D65: 1845 | E65: AUMENTO DE OBRA OC.733 REVESTIMIENTO PERIMETRAL CRC18 GALPON 2 GRANDE (JUAN IGNACIO SOLIS) | F65: 1536340 | H65: =F65-G65 -> 1536340 | I65: CONSTRUCTORA ALPLAS SPA | J65: J.Solis de Ovando | K65: =F65-G65-(SUM(L65:BM65)) -> 0 | Z65: 1536340
A66: 409-1722 REMODELACIONES-OBRAS | B66: 2026 | E66: Otros | F66: 14447916 | H66: =F66-G66 -> 14447916 | K66: =F66-G66-(SUM(L66:BM66)) -> 14447916
A67: 409-1722 REMODELACIONES-OBRAS | B67: 2026 | C67: 2637 | D67: 2500 | E67: REPISAS PARA PAÑOL CARRERA INGENIERÍA ELÉCTRICA CRC18_180 FELIPE ANSELME) | F67: 1328150 | H67: =F67-G67 -> 1328150 | I67: MULTIMUEBLES | J67: F.Anselme | K67: =F67-G67-(SUM(L67:BM67)) -> 0 | AA67: 1328150
A68: 409-1722 REMODELACIONES-OBRAS | B68: 2026 | C68: 2790 | D68: 2598 | E68: SEÑALÉTICA NOMBRE CRC10 Y NUMEROS EN CSL01 (LEONOR RIOS) | F68: 1074618 | H68: =F68-G68 -> 1074618 | I68: PUA DISEÑO | J68: L. Rios | K68: =F68-G68-(SUM(L68:BM68)) -> 0 | AA68: 1074618
A69: 409-1722 REMODELACIONES-OBRAS | B69: 2026 | C69: 2814 | E69: REMODELACION PROYECTO ETAPA 2 Y 3 BIBLIOTECA CAMPUS SAN FRANCISCO (LEONOR RIOS) | F69: 12630236 | H69: =F69-G69 -> 12630236 | I69: CONSTRUCTORA Y SERVICIOS S-TEC SPA | J69: L. Rios | K69: =F69-G69-(SUM(L69:BM69)) -> 0 | AA69: 12630236
A70: 409-1722 REMODELACIONES-OBRAS | B70: 2026 | E70: APS LEVANTAMIENTO PLAN DE MANTENCION | F70: 18714740 | H70: =F70-G70 -> 18714740 | K70: =F70-G70-(SUM(L70:BM70)) -> 0 | L70: 1905200 | P70: 2200000 | S70: 4349400 | X70: 4598000 | AB70: 3293280 | AG70: 2368860
A71: 409-1722 REMODELACIONES-OBRAS | B71: 2026 | E71: AUMENTO DE OBRA REMODELACION PROYECTO ETAPA 2 Y 3 BIBLIOTECA CAMPUS SAN FRANCISCO | F71: 4960920 | H71: =F71-G71 -> 4960920 | I71: CONSTRUCTORA Y SERVICIOS S-TEC SPA | J71: L. Rios | K71: =F71-G71-(SUM(L71:BM71)) -> 0 | AB71: 4960920
A72: 409-1722 REMODELACIONES-OBRAS | B72: 2026 | C72: 2863 | E72: INSTALACION GOMAS REFLECTANTES EN PILARES ESTACIONAMIENTO CSF21 (CRISTOBAL CORREA) | F72: 1427829 | H72: =F72-G72 -> 1427829 | I72: CONSTRUCTORA IGECE LIMITADA | J72: C.Correa | K72: =F72-G72-(SUM(L72:BM72)) -> 0 | AB72: 1427829
A73: 409-1722 REMODELACIONES-OBRAS | B73: 2026 | E73: PAGO DOTACION DE SERVICIO AGUAS ARAUCANIA (AFR) | F73: 10000000 | H73: =F73-G73 -> 10000000 | K73: =F73-G73-(SUM(L73:BM73)) -> 0 | AC73: 10000000
B74: 2024 | D74: 7981 | E74: SERVICIO EVALUACION CERTIFICACION EDIFICIO SUSTENTABLE, HOSPITAL SIMULACION Y PABELLON DOCENTE | F74: 4219946 | G74: 2260686 | H74: =F74-G74 -> 1959260 | I74: B-Green | J74: C.Correa | K74: =F74-G74-(SUM(L74:BM74)) -> 0 | AF74: 1959260
A75: 409-1722 REMODELACIONES-OBRAS | B75: 2026 | E75: OBRAS DE SEGURIDAD, PAISAJISMO CURACAUTIN | F75: 40000000 | H75: =F75-G75 -> 40000000 | K75: =F75-G75-(SUM(L75:BM75)) -> 24000000 | AB75: 6000000 | AK75: 10000000
A76: 409-1722 REMODELACIONES-OBRAS | B76: 2026 | E76: PAISAJISMO ESPACIO TRAS CRC18 (ÁREA VERDE) | F76: 15000000 | H76: =F76-G76 -> 15000000 | K76: =F76-G76-(SUM(L76:BM76)) -> 0 | AC76: 15000000
A77: 409-1722 REMODELACIONES-OBRAS | B77: 2026 | E77: MEJORAMIENTO DE ALMACENAMIENTO Y SUMINISTRO DE AGUA POTABLE CRC | F77: 25000000 | H77: =F77-G77 -> 25000000 | K77: =F77-G77-(SUM(L77:BM77)) -> 0 | AP77: =25000000*0.3 -> 7500000 | AT77: =25000000*0.7 -> 17500000
A78: 409-1722 REMODELACIONES-OBRAS | B78: 2026 | E78: ESTUDIO REPARACIÓN ESTRUCTURA DE CUBIERTA EDIFICIO CJP08 | F78: 12000000 | H78: =F78-G78 -> 12000000 | K78: =F78-G78-(SUM(L78:BM78)) -> 12000000
A79: 409-1722 REMODELACIONES-OBRAS | B79: 2026 | E79: REGULARIZACION CJP07, CJP10, CJP104 ESPECIALIDADES Y PAGOS | F79: 20000000 | H79: =F79-G79 -> 20000000 | K79: =F79-G79-(SUM(L79:BM79)) -> 20000000
A80: 409-1722 REMODELACIONES-OBRAS | B80: 2026 | E80: REGULARIZACION CJP07, CJP10, CJP104 OBRAS | F80: 35000000 | H80: =F80-G80 -> 35000000 | K80: =F80-G80-(SUM(L80:BM80)) -> 35000000
A81: 409-1722 REMODELACIONES-OBRAS | B81: 2026 | E81: CALEFACCIÓN SALA NUEVA OFICIOS CREATIVOS | F81: 22000000 | H81: =F81-G81 -> 22000000 | K81: =F81-G81-(SUM(L81:BM81)) -> 22000000
A82: 409-1722 REMODELACIONES-OBRAS | B82: 2026 | E82: RECAMBIO DE CÁMARA DE FRIO PARA CASINO CJP | F82: 9000000 | H82: =F82-G82 -> 9000000 | K82: =F82-G82-(SUM(L82:BM82)) -> 9000000
A83: 409-1722 REMODELACIONES-OBRAS | B83: 2026 | E83: BANCAS Y BASUREROS | F83: 6000000 | H83: =F83-G83 -> 6000000 | K83: =F83-G83-(SUM(L83:BM83)) -> 6000000
A84: 409-1722 REMODELACIONES-OBRAS | B84: 2026 | E84: ADECUACIONES POR TRASLADOS CSF16 y CSF12 (Descartado) | F84: 64987200 | H84: =F84-G84 -> 64987200 | K84: =F84-G84-(SUM(L84:BM84)) -> 64987200
A85: 409-1722 REMODELACIONES-OBRAS | B85: 2026 | E85: SEÑALETICA OFICINAS TERMINO EN CJP, CSF Y CRC | F85: 23890042 | H85: =F85-G85 -> 23890042 | K85: =F85-G85-(SUM(L85:BM85)) -> 23890042
A86: 409-1722 REMODELACIONES-OBRAS | B86: 2026 | E86: NORMALIZACIÓN SALA DE BASURA CSF Y CJP | F86: 25000000 | H86: =F86-G86 -> 25000000 | K86: =F86-G86-(SUM(L86:BM86)) -> 25000000
A87: 409-1722 REMODELACIONES-OBRAS | B87: 2026 | E87: REGULARIZACION EDIFICIOS | F87: 45000000 | H87: =F87-G87 -> 45000000 | K87: =F87-G87-(SUM(L87:BM87)) -> 45000000
A88: 409-1722 REMODELACIONES-OBRAS | B88: 2026 | E88: AUTOMATIZACION | F88: 15000000 | H88: =F88-G88 -> 15000000 | K88: =F88-G88-(SUM(L88:BM88)) -> 15000000
A89: 409-1722 REMODELACIONES-OBRAS | B89: 2026 | E89: IMPREVISTOS | F89: ='Ppto 2026'!Q83 -> -72396103 | H89: =F89-G89 -> -72396103 | K89: =F89-G89-(SUM(L89:BM89)) -> -72396103

Sheet Ppto 2026
C1: UNIVERSIDAD CATÓLICA DE TEMUCO | G1: Código: SGC PS-FOR-DGDC 0005 Versión: 02 Fecha de vigencia: 12/12/2024 Página: 1 de 1 | P1: =P3-P2 -> -27596683 | T1: =T2-T3 -> 296639056 | AE1: =AE2+AE3+AE4+AE5+AE6+AE7+AE8+AE9+AE11+AE13+AE14 -> 23
C2: PRESUPUESTO INFRAESTRUCTURA 2026 | O2: Resumen | P2: =Resumen!C5+Resumen!C3+Resumen!C2 -> 3459335530 | T2: 3728377903 | W2: Continuidad de obras 2026 | Y2: Obras 2026 | AA2: Remodelaciones 2026 | AD2: D.Silva | AE2: =COUNTIFS(B:B,AD2,J:J,$W$3) -> 4
O3: 1 | P3: =X3+Z3+AB3 -> 3431738847 | R3: =SUM(R10:R84) -> 67596683 | T3: =X3+Z3+AB3 -> 3431738847 | W3: 1 | X3: =SUMIFS(Continuidad_de_obras_2026[Ppto 2026],Continuidad_de_obras_2026[Prioridad],W3) -> 2636383670 | Y3: 1 | Z3: =SUMIFS(_Obras_2026[Ppto 2026],_Obras_2026[Prioridad],Y3) -> 80000000 | AA3: 1 | AB3: =SUMIFS(Remodelaciones_2026[Ppto 2026],Remodelaciones_2026[Prioridad],AA3) -> 715355177 | AD3: M.Zurita | AE3: =COUNTIFS(B:B,AD3,J:J,$W$3) -> 1
O4: 2 | P4: =X4+Z4+AB4 -> 3467510200 | T4: =X4+Z4+AB4 -> 3467510200 | W4: 2 | X4: =SUMIFS(Continuidad_de_obras_2026[Ppto 2026],Continuidad_de_obras_2026[Prioridad],W4) -> 360000000 | Y4: 2 | Z4: =SUMIFS(_Obras_2026[Ppto 2026],_Obras_2026[Prioridad],Y4) -> 751500000 | AA4: 2 | AB4: =SUMIFS(Remodelaciones_2026[Ppto 2026],Remodelaciones_2026[Prioridad],AA4) -> 2356010200 | AD4: F.Anselme | AE4: =COUNTIFS(B:B,AD4,J:J,$W$3) -> 5
O5: 3 | P5: =X5+Z5+AB5 -> 110000000 | T5: =X5+Z5+AB5 -> 110000000 | W5: 3 | X5: =SUMIFS(Continuidad_de_obras_2026[Ppto 2026],Continuidad_de_obras_2026[Prioridad],W5) -> 0 | Y5: 3 | Z5: =SUMIFS(_Obras_2026[Ppto 2026],_Obras_2026[Prioridad],Y5) -> 0 | AA5: 3 | AB5: =SUMIFS(Remodelaciones_2026[Ppto 2026],Remodelaciones_2026[Prioridad],AA5) -> 110000000 | AD5: C.Correa | AE5: =COUNTIFS(B:B,AD5,J:J,$W$3) -> 4
T6: =O8+O20+O34 -> 7009249047 | AD6: M.Matus | AE6: =COUNTIFS(B:B,AD6,J:J,$W$3) -> 0
O7: =O8+O20+O34 -> 7009249047 | AD7: J.Solis de Ovando | AE7: =COUNTIFS(B:B,AD7,J:J,$W$3) -> 4
O8: =SUM(Continuidad_de_obras_2026[Ppto 2026]) -> 2996383670 | AD8: L. Rios | AE8: =COUNTIFS(B:B,AD8,J:J,$W$3) -> 3
A9: Ítem | B9: Responsable | C9: Colaborador | D9: CC | E9: C | F9: Proyecto | G9: Trabajos Receso 2026 | H9: Inicio | I9: Termino | J9: Prioridad | K9: Ppto 2022 | L9: Ppto 2023 | M9: Ppto 2024 | N9: Ppto 2025 | O9: Ppto 2026 | P9: Ppto doc. 2026 | Q9: Saldo | R9: Ajuste | S9: % | T9: Superficie | U9: Comentario | AD9: C. Huenchual | AE9: =COUNTIFS(B:B,AD9,J:J,$W$3) -> 0
B10: C.Correa | E10: CSF | F10: PABELLON DE DOCENCIA + HABILITACIÓN | J10: 2 | O10: =25000000+5000000 -> 30000000 | U10: Esquineros | AD10: F.Anselme | AE10: =COUNTIFS(B:B,AD10,J:J,$W$3) -> 5
B11: J.Solis de Ovando | C11: I. Riquelme | D11: 409-5243 INSTITUTO TECNOLOGICO | E11: CRC | F11: EDIFICIO INGENIERÍA (EX TEC) + HABILITACIÓN | G11: Si | I11: 46054 | J11: 1 | O11: =1568182758+73000000 -> 1641182758 | P11: =SUMIFS('Base datos 2026'!J:J,'Base datos 2026'!A:A,D11,'Base datos 2026'!B:B,F11)+'Ingeniería'!N23+'Ingeniería'!N24+'Ingeniería'!N25 -> 1577697306 | Q11: =O11-P11 -> 63485452 | S11: =P11/O11 -> 0.96131726 | U11: Obras , adicional ingeniaria + Grupo electrógeno | AD11: I. Cisternas | AE11: =COUNTIFS(B:B,AD11,J:J,$W$3) -> 1
B12: D.Silva | E12: CJP | F12: TÚNEL, SALIDA Y CALLE PROLONGACIÓN CJPII | J12: 3 | AD12: A. Meza | AE12: =COUNTIFS(B:B,AD12,J:J,$W$3) -> 0
B13: J.Solis de Ovando | C13: I. Riquelme | D13: 409-5506 - CASINO VRAE | E13: CRC | F13: PERMISO + CONSTRUCCION CASINO CRC11 (VRAE) | G13: Si | H13: 46023 | I13: 46266 | J13: 1 | O13: =855200912+40000000 -> 895200912 | P13: =SUMIFS('Base datos 2026'!J:J,'Base datos 2026'!A:A,D13,'Base datos 2026'!B:B,F13) -> 859639867 | Q13: =O13-P13 -> 35561045 | S13: =P13/O13 -> 0.96027591 | T13: 470 | U13: Permiso + Obras + estacionamientos lado contenedores | W13: =(855200912)/T13/X13 -> 45.778789 | X13: 39747.15 | Y13: UF | AD13: I. Riquelme | AE13: =COUNTIFS(B:B,AD13,J:J,$W$3) -> 1
B14: J.Solis de Ovando | D14: 409-5506 - CASINO VRAE | E14: CRC | F14: CASINO CRC11 (VRAE) HABILITACIÓN | H14: 46235 | I14: 46296 | J14: 1 | O14: 100000000 | P14: =SUMIFS('Base datos 2026'!J:J,'Base datos 2026'!A:A,D14,'Base datos 2026'!B:B,F14) -> 98069090 | Q14: =O14-P14 -> 1930910 | S14: =P14/O14 -> 0.9806909 | U14: Habilitación | AD14: A. Meza | AE14: =COUNTIFS(B:B,AD14,J:J,$W$3) -> 0
B15: C.Correa | E15: CHS | F15: HOSPITAL DE SIMULACION CLINICA + HABILITACIÓN | J15: 2 | O15: =20000000+40000000 -> 60000000 | S15: =P15/O15 -> 0 | U15: Habilitar laboratorio clínico +Torniquete de acceso
B16: D.Silva | E16: CCC | F16: CONSTRUCCIÓN SALON DE CONVENCIONES Y EVENTOS, CURACAUTÍN (ETAPA 2) | J16: 2 | O16: 270000000 | S16: =P16/O16 -> 0 | U16: Cubierta, revestimientos, aislación y terminaciones. instalaciones eléctricas y sanitarias. habilitación básica (calefacción, cocina, mobiliario básico)
O20: =SUM(_Obras_2026[Ppto 2026]) -> 831500000
A21: Ítem | B21: Responsable | C21: Colaborador | D21: CC | E21: C | F21: Proyecto | G21: Trabajos Receso 2026 | H21: Inicio | I21: Termino | J21: Prioridad | K21: Ppto 2022 | L21: Ppto 2023 | M21: Ppto 2024 | N21: Ppto 2025 | O21: Ppto 2026 | P21: Ppto doc. 2026 | Q21: Saldo | R21: Ajuste | S21: % | T21: Superficie | U21: Comentario
B22: D.Silva | C22: D.Silva | D22: 409-6293 - CENTRO RECREACIONAL SAN NICOLAS | E22: CCC | F22: OBRAS DE SEGURIDAD, PAISAJISMO CURACAUTIN | G22: Si | H22: 46023 | I22: 46143 | J22: 1 | O22: 40000000 | P22: =SUMIFS('Base datos 2026'!J:J,'Base datos 2026'!A:A,D22,'Base datos 2026'!B:B,F22) -> 2196742 | Q22: =O22-P22 -> 37803258 | S22: =P22/O22 -> 0.05491855 | U22: Barandas de seguridad, cierre perimetral piscina, portones, senderos, paisajismo
B23: J.Solis de Ovando | E23: CRC | F23: ETAPA 2 GRECA CRC (EXTERIOR CASINO + PAISAJISMO) | J23: 2 | O23: 120000000 | T23: 450 | U23: La etapa 2 del proyecto GRECA CRC incluye trabajos en el exterior del nuevo casino. Esto implica la ejecución de obras al aire libre que complementan la infraestructura del edificio, como el condicionamiento de áreas exteriores, acceso, y la implementación de diseño paisajístico para mejorar la estética y funcionalidad de los espacios exteriores del casino y edificio de ingeniería. La intervención busca integrar el entorno construido con áreas verdes y elementos de paisaje.
B24: C.Correa | D24: 409-1722 REMODELACIONES-OBRAS | E24: CRC | F24: PAISAJISMO ESPACIO TRAS CRC18 (ÁREA VERDE) | H24: 46023 | I24: 46174 | J24: 1 | O24: =5000000+10000000 -> 15000000 | P24: =SUMIFS('Base datos 2026'!J:J,'Base datos 2026'!A:A,D24,'Base datos 2026'!B:B,F24) -> 14669999 | Q24: =O24-P24 -> 330001 | S24: =P24/O24 -> 0.97799993 | U24: Trazado zonificaciones, urbanizacion, agua y electricidad
B25: F.Anselme | D25: 409-6293 - CENTRO RECREACIONAL SAN NICOLAS | E25: CRC | F25: MEJORAMIENTO DE ALMACENAMIENTO Y SUMINISTRO DE AGUA POTABLE CRC | H25: 46023 | I25: 46143 | J25: 1 | O25: 25000000 | P25: =SUMIFS('Base datos 2026'!J:J,'Base datos 2026'!A:A,D25,'Base datos 2026'!B:B,F25) -> 0 | Q25: =O25-P25 -> 25000000 | S25: =P25/O25 -> 0 | U25: Sistema autónomo desde la red externa considerando sala de bombas y estanque soterrado
B26: J.Solis de Ovando | E26: CSF | F26: INSTALACIÓN ASCENSOR CSF03 (ACCESIBILIDAD UNIVERSAL) | J26: 2 | O26: 250000000 | S26: =P26/O26 -> 0 | U26: proyecto que aumenta en 1.200 m2 de superficie con acceso universal, dejando al campus con mas del 90% de sus recintos accesibles
B27: C.Correa | E27: CSF | F27: MANTENCIÓN PISO 5 CSF12 (CLIMATIZACIÓN, ELECTRICIDAD Y CUBIERTA) | J27: 2 | O27: =(850*290000)+30000000 -> 276500000 | S27: =P27/O27 -> 0
B28: F.Anselme | E28: CJP | F28: URBANIZACIÓN CAMINO LATERAL CANCHAS | J28: 2 | O28: 45000000 | S28: =P28/O28 -> 0 | U28: Mejorar estacionamientos y veredas para acceso a edificaciones
B29: L. Rios | E29: CSF | F29: OFICINAS MODULARES CSF + URBANIZACION | J29: 2 | O29: 30000000 | S29: =P29/O29 -> 0 | T29: =40*2 -> 80 | U29: Contrucción de modulos de oficinas en CSF, posterior CSF14 - CSF16
E30: CSF | F30: ANTEPROYECTO TEC CSF | J30: 2 | O30: 30000000 | S30: =P30/O30 -> 0
O34: =SUM(Remodelaciones_2026[Ppto 2026]) -> 3181365377
A35: Ítem | B35: Responsable | C35: Colaborador | D35: CC | E35: C | F35: Proyecto | G35: Trabajos Receso 2026 | H35: Inicio | I35: Termino | J35: Prioridad | K35: Ppto 2022 | L35: Ppto 2023 | M35: Ppto 2024 | N35: Ppto 2025 | O35: Ppto 2026 | P35: Ppto doc. 2026 | Q35: Saldo | R35: Ajuste | S35: % | T35: Superficie | U35: Comentario
B36: L. Rios | E36: CBQ | F36: REMODELACIÓN LABORATORIO CLÍNICO UCT (OFICINAS) CBQ03 | J36: 2 | O36: =T36*40000*10 -> 64000000 | S36: =P36/O36 -> 0 | T36: 160 | U36: Remodelación asociada al traslado de TEC al edificio, requiee ampliación habilitación de multiples oficinas
B37: M.Zurita | E37: CDS | F37: NORMALIZACIÓN Y AUMENTO DE POTENCIA ELÉCTRICA 18 DE SEPTIEMBRE | J37: 2 | O37: 25000000 | S37: =P37/O37 -> 0
B38: J.Solis de Ovando | E38: CJP | F38: CAMBIO DE VENTANAS TERMOPANEL Y ENVOLVENTE TERMICA CJP08 ETAPA 2 | J38: 2 | O38: 250000000 | S38: =P38/O38 -> 0 | T38: 919 | U38: El trabajo de "Cambio de Ventanas Termopanel y Envolvente Térmica CJP08 Etapa 2" consiste en mejorar la eficiencia térmica del edificio CJP08 , continuando con los trabnajos del año 2025 , mediante la instalación de ventanas tipo termopanel, que permiten reducir la transferencia de calor entre el interior y exterior, mejorando el confort térmico y disminuyendo la demanda energética. Además, se realiza el mejoramiento de la envolvente térmica, es decir, la capa que aísla térmicamente el edificio.
B39: D.Silva | D39: 409-1722 REMODELACIONES-OBRAS | E39: CJP | F39: ESTUDIO REPARACIÓN ESTRUCTURA DE CUBIERTA EDIFICIO CJP08 | H39: 46082 | I39: 46174 | J39: 1 | O39: 12000000 | P39: =SUMIFS('Base datos 2026'!J:J,'Base datos 2026'!A:A,D39,'Base datos 2026'!B:B,F39) -> 0 | Q39: =O39-P39 -> 12000000 | S39: =P39/O39 -> 0
B40: J.Solis de Ovando | E40: CJP | F40: CAMBIO DE VENTANAS TERMOPANEL Y ENVOLVENTE TERMICA CJP10 | J40: 2 | O40: 150000000 | S40: =P40/O40 -> 0 | T40: 600 | U40: instalación de ventanas tipo termopanel, que permiten reducir la transferencia de calor entre el interior y exterior, mejorando el confort térmico y disminuyendo la demanda energética. Además, se realiza el mejoramiento de la envolvente térmica, es decir, la capa que aísla térmicamente el edificio.
B41: C.Correa | D41: 409-1722 REMODELACIONES-OBRAS | E41: CJP | F41: REGULARIZACION CJP07, CJP10, CJP104 ESPECIALIDADES Y PAGOS | H41: 46023 | I41: 46327 | J41: 1 | O41: 20000000 | P41: =SUMIFS('Base datos 2026'!J:J,'Base datos 2026'!A:A,D41,'Base datos 2026'!B:B,F41) -> 0 | Q41: =O41-P41 -> 20000000 | S41: =P41/O41 -> 0
B42: C.Correa | D42: 409-1722 REMODELACIONES-OBRAS | E42: CJP | F42: REGULARIZACION CJP07, CJP10, CJP104 OBRAS | H42: 46023 | I42: 46327 | J42: 1 | O42: 35000000 | P42: =SUMIFS('Base datos 2026'!J:J,'Base datos 2026'!A:A,D42,'Base datos 2026'!B:B,F42) -> 0 | Q42: =O42-P42 -> 35000000 | S42: =P42/O42 -> 0 | U42: intervenciones en: Tabiques, baños, puertas, franjas podotactil, señaleticas, muebles, otros.
B43: J.Solis de Ovando | E43: CJP | F43: CAMBIO BUTACAS AUDITORIO CJP08 | J43: 2 | O43: 75000000 | S43: =P43/O43 -> 0 | T43: 144 butacas | U43: Cambio de la totalidad de la butacas del auditorio CJP08_260
B44: F.Anselme | D44: 409-1722 REMODELACIONES-OBRAS | E44: CJP | F44: CALEFACCIÓN SALA NUEVA OFICIOS CREATIVOS | H44: 46023 | I44: 46054 | J44: 1 | O44: 22000000 | P44: =SUMIFS('Base datos 2026'!J:J,'Base datos 2026'!A:A,D44,'Base datos 2026'!B:B,F44) -> 0 | Q44: =O44-P44 -> 22000000 | S44: =P44/O44 -> 0
B45: F.Anselme | D45: 409-1722 REMODELACIONES-OBRAS | E45: CJP | F45: RECAMBIO DE CÁMARA DE FRIO PARA CASINO CJP | H45: 46023 | I45: 46082 | J45: 1 | O45: 9000000 | P45: =SUMIFS('Base datos 2026'!J:J,'Base datos 2026'!A:A,D45,'Base datos 2026'!B:B,F45) -> 0 | Q45: =O45-P45 -> 9000000 | S45: =P45/O45 -> 0
B46: F.Anselme | E46: CJP | F46: CAMBIO VENTANAS DVH EN MAL ESTADO CJP05 ETAPA 1 | J46: 2 | O46: =T46*190000 -> 58140000 | S46: =P46/O46 -> 0 | T46: =100+206 -> 306 | U46: Cambio de vidrios en mal estado
B47: J.Solis de Ovando | E47: CML | F47: REMODELACION PLAZA ACCESO CML | J47: 2 | O47: 100000000 | S47: =P47/O47 -> 0 | T47: 243.33 | U47: Estudio Topografico de Plaza Acceso campus ML , a solicitud de Rectoria , continuacion de baldosas exteriores , mejoramioento de drenes de agua lluvia y evitar pozones de agua exterior.
B48: J.Solis de Ovando | E48: CML | F48: TRATAMIENTO PINTURA TEXTURADA (GRANO) CML01 | J48: 2 | O48: 50000000 | S48: =P48/O48 -> 0 | T48: 500 | U48: Trabajos esteticos de fachada
B49: J.Solis de Ovando | E49: CML | F49: CAMBIO VENTANAS DE MADERA CON TP CML01 | J49: 2 | O49: 80000000 | S49: =P49/O49 -> 0
B50: J.Solis de Ovando | D50: 409-1722 REMODELACIONES-OBRAS | E50: CPH | F50: REMODELACION LAB. SUELOS , CONSTRUCCION DE OFICINAS CPH02 (PHILLIPPI) | G50: Si | H50: 46023 | I50: 46143 | J50: 1 | O50: 34000000 | P50: =SUMIFS('Base datos 2026'!J:J,'Base datos 2026'!A:A,D50,'Base datos 2026'!B:B,F50) -> 53297921 | Q50: =O50-P50 -> -19297921 | S50: =P50/O50 -> 1.5675859 | T50: 100 | U50: Postuesto para Vicerrectoria para Marzo 2026 (54MM)
B51: C.Correa | E51: CRC | F51: PINTURA Y CAMBIO DE ELEMENTOS DAÑADO EDIFICIO CRC17 Y CRC18 | J51: 2 | O51: 50000000 | S51: =P51/O51 -> 0 | T51: =(52*4.6)+(38*6) -> 467.2
B52: I. Riquelme | C52: I. Riquelme | D52: 409-1722 REMODELACIONES-OBRAS | E52: CRC | F52: BIBICLETERO CRC (VRAE) | G52: Si | H52: 46054 | I52: 46113 | J52: 1 | O52: =20000000-R52 -> 17300000 | P52: =SUMIFS('Base datos 2026'!J:J,'Base datos 2026'!A:A,D52,'Base datos 2026'!B:B,F52) -> 16594157 | Q52: =O52-P52 -> 705843 | R52: 2700000 | S52: =P52/O52 -> 0.95919983 | T52: 50
B53: J.Solis de Ovando | E53: CRC | F53: TRATAMIENTO PINTURA TEXTURADA (GRANO) CRC09 | J53: 2 | O53: 50000000 | S53: =P53/O53 -> 0 | T53: 1200
B54: D.Silva | E54: CRC | F54: PINTURA EDIFICIO CRC03 (MAC) | J54: 2 | O54: 25000000 | S54: =P54/O54 -> 0 | T54: 800
B55: J.Solis de Ovando | E55: CRC | F55: MANTENCIÓN ESTRUCTURA LETRERO CAMINERO CRC | J55: 2 | O55: 5000000 | S55: =P55/O55 -> 0 | U55: Demoler
B56: D.Silva | C56: I. Riquelme | D56: 409-1722 REMODELACIONES-OBRAS | E56: CRC | F56: CRC05 MEJORAS HABITABILIDAD INTERIOR | G56: Si | H56: 46054 | I56: 46082 | J56: 1 | O56: =50000000-R56 -> 44864047 | P56: =SUMIFS('Base datos 2026'!J:J,'Base datos 2026'!A:A,D56,'Base datos 2026'!B:B,F56) -> 44864047 | Q56: =O56-P56 -> 0 | R56: 5135953 | S56: =P56/O56 -> 1 | T56: 521.64 | U56: Mejorar espacios internos con mayor confort termino y habitabilidad.
B57: F.Anselme | E57: CRC | F57: CERCO PERIMETRAL PRINCIPAL Y LATERAL LADO NORTE CRC | J57: 2 | O57: =T57*120000 -> 48120000 | S57: =P57/O57 -> 0 | T57: =180+221 -> 401 | U57: ml
B58: I. Cisternas | D58: 409-1722 REMODELACIONES-OBRAS | E58: CRC | F58: BANCAS Y BASUREROS | H58: 46082 | I58: 46327 | J58: 1 | O58: 6000000 | P58: =SUMIFS('Base datos 2026'!J:J,'Base datos 2026'!A:A,D58,'Base datos 2026'!B:B,F58) -> 0 | Q58: =O58-P58 -> 6000000 | S58: =P58/O58 -> 0 | U58: Compra de basurerros y bancas asociados a campus CJP y CRC
B59: D.Silva | C59: I. Riquelme | D59: 409-1722 REMODELACIONES-OBRAS | E59: CSF | F59: MANTENCIÓN ESTRUCTURA MADERA LAMINADA PILARES Y VIGAS CSF14 - CSF16 | G59: Si | H59: 46054 | I59: 46113 | J59: 1 | O59: =150000000-R59 -> 103241855 | P59: =SUMIFS('Base datos 2026'!J:J,'Base datos 2026'!A:A,D59,'Base datos 2026'!B:B,F59) -> 103241855 | Q59: =O59-P59 -> 0 | R59: 46758145 | S59: =P59/O59 -> 1 | U59: lijado completo de las piezas expuestas al exterior, pintura protectora (cutek o similar), cambio de piezas en mal estado, arriostramientos metalicos de marcos,rejilla guia de enreraderas
B60: L. Rios | D60: 409-1722 REMODELACIONES-OBRAS | E60: CSF | F60: ADECUACIONES POR TRASLADOS CSF16 y CSF12 | H60: 46054 | I60: 46235 | J60: 1 | O60: =T60*40000*3 -> 64987200 | P60: =SUMIFS('Base datos 2026'!J:J,'Base datos 2026'!A:A,D60,'Base datos 2026'!B:B,F60) -> 0 | Q60: =O60-P60 -> 64987200 | S60: =P60/O60 -> 0 | T60: =328.27+213.29 -> 541.56 | U60: Traslado de Antropologia y Psicologia, requiere habilitación en CSF16
B61: F.Anselme | E61: CSF | F61: CAMBIO VENTANAS ETAPA 1 A DVH CSF03 | J61: 2 | O61: 65000000 | S61: =P61/O61 -> 0 | T61: 187.2 | U61: Cambio de ventanas fierro monolítico a PVC doble vidrio hermético lado calle el bosque
B62: F.Anselme | E62: CSF | F62: CAMBIO VENTANAS A DVH CSF12 | J62: 2 | O62: =T62*199000 -> 53391700 | S62: =P62/O62 -> 0 | T62: =(26.7*4)+(33.7*4)+26.7 -> 268.3 | U62: Cambio de ventanas fierro monolítico a PVC doble vidrio hermético lado Bautista
B63: M.Zurita | C63: A. Meza | D63: 409-1722 REMODELACIONES-OBRAS | E63: CSF | F63: BIBLIOTECA CSF02 ETAPA 2 Y 3, ELECTRICO | G63: Si | H63: 46023 | I63: 46082 | J63: 1 | O63: =30000000+15000000 -> 45000000 | P63: =SUMIFS('Base datos 2026'!J:J,'Base datos 2026'!A:A,D63,'Base datos 2026'!B:B,F63) -> 57436579 | Q63: =O63-P63 -> -12436579 | S63: =P63/O63 -> 1.2763684 | U63: Trabajos electricos asociados a biblitoeca etpa 2 y 3, traslado de laboratorio de computación + obras
B64: L. Rios | E64: CSF | F64: BIBLIOTECA CSF02 ETAPA 4 Y 6, REMODELACIÓN Y MOBILIARIO | J64: 2 | O64: =((103329+20612)*1000)*1.3 -> 161123300 | S64: =P64/O64 -> 0 | U64: Compra de mobiliario y remodelación tercer piso
B65: L. Rios | E65: CSF | F65: TRASLADO LAB CSF12_255 A CSF12_256 ARQUEOLOGIA | J65: 2 | O65: =T65*14*40000 -> 56235200 | S65: =P65/O65 -> 0 | T65: =55.69+44.73 -> 100.42 | U65: Intercambio de espacios, habilitación de laboratorio
B66: F.Anselme | E66: CSF | F66: SISTEMA DE VENTILACIÓN Y RENOVACIÓN DE AIRE CSF02 (AULA MAGNA) | J66: 2 | O66: 50000000 | S66: =P66/O66 -> 0
B67: M.Zurita | E67: CSF | F67: NORMALIZACIÓN ELÉCTRICA EDIFICIO CSF14 | J67: 2 | O67: =155000000 -> 155000000 | S67: =P67/O67 -> 0
B68: M.Zurita | E68: CSF | F68: NORMALIZACIÓN ELÉCTRICA EDIFICIO CSF16 | J68: 2 | O68: =165000000 -> 165000000 | S68: =P68/O68 -> 0
B69: M.Zurita | E69: CSF | F69: NORMALIZACIÓN ELÉCTRICA EDIFICIO CSF12 | J69: 2 | O69: =210000000 -> 210000000 | S69: =P69/O69 -> 0
B70: L. Rios | D70: 409-1722 REMODELACIONES-OBRAS | E70: TODOS | F70: SEÑALETICA OFICINAS TERMINO EN CJP, CSF Y CRC | H70: 46082 | I70: 46327 | J70: 1 | O70: =178319*140 -> 24964660 | P70: =SUMIFS('Base datos 2026'!J:J,'Base datos 2026'!A:A,D70,'Base datos 2026'!B:B,F70) -> 10274694 | Q70: =O70-P70 -> 14689966 | S70: =P70/O70 -> 0.41156955 | U70: Compra de 140 unidades, tipo oficinas, para termino en CSF, CJP Y CRC
B71: M.Zurita | E71: TODOS | F71: MANTENCIÓN Y CAMBIO DE CALDERAS, EFICIENCIA ENERGÉTICA, 2 DE 20 | J71: 2 | O71: 70000000 | S71: =P71/O71 -> 0
B72: M.Zurita | E72: TODOS | F72: MONITOREO DE CALDERAS, ETAPA 2 | J72: 3 | O72: 25000000 | S72: =P72/O72 -> 0
B73: M.Zurita | E73: TODOS | F73: MONITOREO DE EFICIENCIA ENERGÉTICA, ETAPA 2 | J73: 3 | O73: 25000000 | S73: =P73/O73 -> 0
B74: M.Zurita | E74: TODOS | F74: NORMALIZACIÓN ELÉCTRICA DE TABLERO GENERALES CRÍTICOS 10/100 | J74: 3 | O74: 30000000 | S74: =P74/O74 -> 0
B75: M.Zurita | E75: TODOS | F75: INSTALACIÓN DE EQUIPOS DE MEDIDA AGUA Y GAS 10/64 | J75: 3 | O75: 30000000 | S75: =P75/O75 -> 0
B76: M.Zurita | E76: TODOS | F76: TRASLADO GRUPO ELECTRÓGENO DE EDIFICIO DE CBQ A SCN | J76: 2 | O76: 20000000 | S76: =P76/O76 -> 0
B77: M.Zurita | E77: TODOS | F77: PLANTA FOTOVOLTAICA DE 250KWP | J77: 2 | O77: 300000000 | S77: =P77/O77 -> 0
B78: M.Zurita | E78: TODOS | F78: INSTALACIÓN DE EQUIPOS DE MEDIDA ELECTRICOS 20/35 | J78: 2 | O78: 20000000 | S78: =P78/O78 -> 0
B79: F.Anselme | D79: 409-1722 REMODELACIONES-OBRAS | E79: TODOS | F79: NORMALIZACIÓN SALA DE BASURA CSF Y CJP | H79: 46023 | I79: 46082 | J79: 1 | O79: =25000000-R79 -> 15000000 | P79: =SUMIFS('Base datos 2026'!J:J,'Base datos 2026'!A:A,D79,'Base datos 2026'!B:B,F79) -> 1333871 | Q79: =O79-P79 -> 13666129 | R79: 10000000 | S79: =P79/O79 -> 0.088924733 | U79: Trabajos para obtener resolución sanitaria
B80: C.Correa | D80: 409-1722 REMODELACIONES-OBRAS | E80: TODOS | F80: REGULARIZACION EDIFICIOS | H80: 46082 | I80: 46327 | J80: 1 | O80: 45000000 | P80: =SUMIFS('Base datos 2026'!J:J,'Base datos 2026'!A:A,D80,'Base datos 2026'!B:B,F80) -> 484030 | Q80: =O80-P80 -> 44515970 | S80: =P80/O80 -> 0.010756222 | U80: Recepcion Definitiva edificios CJP11 y CJP17 (Fid y Cedelem)
B81: F.Anselme | D81: 409-1722 REMODELACIONES-OBRAS | E81: TODOS | F81: AUTOMATIZACION | H81: 46082 | I81: 46327 | J81: 1 | O81: 15000000 | P81: =SUMIFS('Base datos 2026'!J:J,'Base datos 2026'!A:A,D81,'Base datos 2026'!B:B,F81) -> 0 | Q81: =O81-P81 -> 15000000 | S81: =P81/O81 -> 0 | U81: Mejorar automatización de registro actividades
B82: L. Rios | C82: L. Rios | D82: 409-1722 REMODELACIONES-OBRAS | E82: CSF | F82: MEJORAS ESPACIOS INTERNAS CSF10 (CREDITO) | G82: Si | H82: 46054 | I82: 46082 | J82: 1 | O82: =5000000-R82 -> 1997415 | P82: =SUMIFS('Base datos 2026'!J:J,'Base datos 2026'!A:A,D82,'Base datos 2026'!B:B,F82) -> 1997415 | Q82: =O82-P82 -> 0 | R82: 3002585 | S82: =P82/O82 -> 1
D83: 409-1722 REMODELACIONES-OBRAS | E83: TODOS | F83: IMPREVISTOS | H83: 46023 | I83: 46327 | J83: 1 | O83: 200000000 | P83: =SUMIFS('Base datos 2026'!J:J,'Base datos 2026'!A:A,D83,'Base datos 2026'!B:B,F83) -> 272396103 | Q83: =O83-P83 -> -72396103 | S83: =P83/O83 -> 1.3619805

Sheet Base datos 2026
T1: =SUM(T4:T496) -> 1905200 | U1: =SUM(U4:U496) -> 5595975 | V1: =SUM(V4:V496) -> 43411350 | W1: =SUM(W4:W496) -> 39197456 | X1: =SUM(X4:X496) -> 2200000 | Y1: =SUM(Y4:Y496) -> 0 | Z1: =SUM(Z4:Z496) -> 0 | AA1: =SUM(AA4:AA496) -> 4349400 | ... BU1: =SUM(BU4:BU496) -> 0
T2: Semana 1-Ene | U2: Semana 2-Enero | V2: Semana 3-Ene | W2: Semana 4-Ene | X2: Semana 1-Feb | Y2: Semana 2-Feb | Z2: Semana 3-Febr | AA2: Semana 4-Feb | AB2: Semana 1-Mar | AC2: Semana 2-Marz | AD2: Semana 3-Marzo | AE2: Semana 4-Mar | AF2: Semana 1-Abri | AG2: Semana 2-Abri | AH2: Semana 3-Abril | AI2: Semana 4-Abril | AJ2: Semana 5-Abri | AK2: Semana 1-May | AL2: Semana 2-Mayo | AM2: Semana 3-Mayo | AN2: Semana 4-Mayo | AO2: Semana 1-Jun | AP2: Semana 2-Jun | AQ2: Semana 3-Junio | AR2: Semana 4-Junio | AS2: Semana 1-Juli | AT2: Semana 2-Jul | AU2: Semana 3-Julio | AV2: Semana 4-Julio | AW2: Semana 5-Juli | AX2: Semana 1-Ago | AY2: Semana 2-Agos | AZ2: Semana 3-Agos | BA2: Semana 4-Agos | BB2: Semana 1-Sept | BC2: Semana 2-Septi | BD2: Semana 3-Septi | BE2: Semana 4-Septi | BF2: Semana 5-Septi | BG2: Semana 1-Octu | BH2: Semana 2-Oct | BI2: Semana 3-Octu | BJ2: Semana 4-Octu | BK2: Semana 5-Octu | BL2: Semana 1-Nov | BM2: Semana 2-Novi | BN2: Semana 3-Novi | BO2: Semana 4-Novi | BP2: Semana 1-Dic | BQ2: Semana 2-Dic | BR2: Semana 3-Dici | BS2: Semana 4-Dici | BT2: Semana 5-Dici | BU2: Semana 1-Ene
A3: CC | B3: Proyecto | C3: OP | D3: OC | E3: Tipo Obra | F3: Campus | G3: Edificio | H3: Uso | I3: Descripción | J3: Monto | K3: Pagado | L3: Saldo | M3: % | N3: Contratista | O3: Responsable | P3: RC | Q3: Fecha RC | R3: Column 74 | S3: Δ | T3: 05 al 11 | U3: 12 al 18 | V3: 19 al 25 | W3: 26 al 01 | X3: 02 al 08 | Y3: 09 al 15 | Z3: 16 al 22 | AA3: 23 al 01 | AB3: 02 al 08 | AC3: 09 al 15 | AD3: 16 al 22 | AE3: 23 al 29 | AF3: 30 al 05 | AG3: 06 al 12 | AH3: 13 al 19 | AI3: 20 al 26 | AJ3: 27 al 03 | AK3: 04 al 10 | AL3: 11 al 17 | AM3: 18 al 24 | AN3: 25 al 31 | AO3: 01 al 07 | AP3: 08 al 14 | AQ3: 15 al 21 | AR3: 22 al 28 | AS3: 29 al 05 | AT3: 06 al 12 | AU3: 13 al 19 | AV3: 20 al 26 | AW3: 27 al 02 | AX3: 03 al 09 | AY3: 10 al 16 | AZ3: 17 al 23 | BA3: 24 al 30 | BB3: 31al 06 | BC3: 07 al 13 | BD3: 14 al 20 | BE3: 21 al 27 | BF3: 28 al 04 | BG3: 05 al 11 | BH3: 12 al 18 | BI3: 19 al 25 | BJ3: 26 al 01 | BK3: 02 al 08 | BL3: 09 al 15 | BM3: 16 al 22 | BN3: 23 al 29 | BO3: 24 al 30 | BP3: 30 al 06 | BQ3: 07 al 13 | BR3: 14 al 20 | BS3: 21 al 27 | BT3: 28 al 03 | BU3: 05 al 11
A4: 409-5243 INSTITUTO TECNOLOGICO | B4: EDIFICIO INGENIERÍA (EX TEC) + HABILITACIÓN | C4: 799 | D4: 864 | I4: SOPORTES PARA INSTALACION DE TELEVISORES SALAS DE REUNIONES, SALAS DE CLASES Y LABORARIOS NUEVO EDIFICIO INGENIERIA (ARTURO MEZA) | J4: 5537070 | L4: =J4-K4 -> 5537070 | N4: GYG SERVICIOS | O4: A. Meza | P4: RC-070_26 | Q4: 46121 | R4: 0.73361111 | S4: =J4-K4-(SUM(T4:BU4)) -> 0 | AH4: 5537070
A5: 409-1722 REMODELACIONES-OBRAS | B5: IMPREVISTOS | C5: 793 | D5: 860 | E5: INSTALACIONES | F5: CRC Campus Doctor Luis Rivas Del Canto (vrae) | G5: CRC16 | H5: DOCENCIA | I5: REMODELACION LABORATORIO COMPUTACION CRC16_210 (ARTURO MEZA) | J5: 10154673 | L5: =J5-K5 -> 10154673 | N5: INGERTEMUCO INGENIERIA SPA | O5: A. Meza | P5: RC-008_26 | Q5: 46091 | R5: 0.61634259 | S5: =J5-K5-(SUM(T5:BU5)) -> 0 | AF5: 10154673
A6: 409-5243 INSTITUTO TECNOLOGICO | B6: EDIFICIO INGENIERÍA (EX TEC) + HABILITACIÓN | C6: 1473 | D6: 1578 | E6: INSTALACIONES | F6: CRC Campus Doctor Luis Rivas Del Canto (vrae) | G6: CRC10 | I6: RACK PARA DATA CENTER NUEVO EDIFICIO FACULTAD DE INGENIERIA (ARTURO MEZA)PROVEEDOR ADJUDICADO CUMPLE CON TODAS LAS ESPECIFICACIONES TECNICAS. | J6: 3704470 | L6: =J6-K6 -> 3704470 | N6: GYG SERVICIOS | O6: A. Meza | P6: RC-036_26 | Q6: 46101 | R6: 0.45989583 | S6: =J6-K6-(SUM(T6:BU6)) -> 0 | AE6: 3704470
A7: 409-5243 INSTITUTO TECNOLOGICO | B7: EDIFICIO INGENIERÍA (EX TEC) + HABILITACIÓN | C7: 1770 | D7: 1786 | E7: ALHAJAMIENTO | F7: CRC Campus Doctor Luis Rivas Del Canto (vrae) | G7: CRC10 | I7: TELEVISORES PARA SALAS DE CLASES, REUNIONES Y LABORATORIOS NUEVO EDIFICIO INGENIERIA (ARTURO MEZA) | J7: 17043200 | L7: =J7-K7 -> 17043200 | N7: GYG SERVICIOS | O7: A. Meza | P7: RC-048_26 | Q7: 46107 | R7: 0.58019676 | S7: =J7-K7-(SUM(T7:BU7)) -> 0 | AF7: 17043200
A8: 409-5243 INSTITUTO TECNOLOGICO | B8: EDIFICIO INGENIERÍA (EX TEC) + HABILITACIÓN | C8: 2497 | D8: 2421 | E8: INSTALACIONES | F8: CRC Campus Doctor Luis Rivas Del Canto (vrae) | G8: CRC10 | I8: MODIFICACION DE ENCHUFES Y HDMI PARA INSTALACION DE TV EN SALAS DE CLASES EDIFICIO FAC. DE INGENIERIA (ARTURO MEZA) | J8: 799442 | L8: =J8-K8 -> 799442 | N8: GYG SERVICIOS | O8: A. Meza | P8: RC-199_26 | Q8: 46162 | R8: 0.57662037 | S8: =J8-K8-(SUM(T8:BU8)) -> 0 | AI8: 799442
A9: 409-5243 INSTITUTO TECNOLOGICO | B9: EDIFICIO INGENIERÍA (EX TEC) + HABILITACIÓN | C9: 2714 | D9: 2483 | E9: INSTALACIONES | F9: CRC Campus Doctor Luis Rivas Del Canto (vrae) | G9: CRC10 | I9: GRUPO ELECTROGENO EDIFICIO CRC10 FACULTAD DE INGENIERIA (ARTURO MEZA) | J9: 15170428 | L9: =J9-K9 -> 15170428 | N9: ELECTROPOWER | O9: A. Meza | P9: RC-189_26 | Q9: 46160 | R9: 0.61135417 | S9: =J9-K9-(SUM(T9:BU9)) -> 0 | AL9: 15170428
A10: 409-1722 REMODELACIONES-OBRAS | B10: IMPREVISTOS | C10: 276 | D10: 331 | E10: AUMENTO DE OBRA | F10: CLE Nuestra Señora de Lourdes | G10: CHS01 | H10: DOCENCIA | I10: AUMENTO DE OBRA OC 8157 ADICIONALES OBRAS POST CONTRUCCION SEGUN DETALLE (CRISTOBAL CORREA) | J10: 9440482 | L10: =J10-K10 -> 9440482 | N10: ROMO Y CADI LIMITADA | O10: C.Correa | Q10: #N/A | S10: =J10-K10-(SUM(T10:BU10)) -> 0 | AK10: 9440482
A11: 409-1722 REMODELACIONES-OBRAS | B11: IMPREVISTOS | C11: 277 | D11: 361 | E11: AUMENTO DE OBRA | F11: CLE Nuestra Señora de Lourdes | G11: CHS01 | H11: DOCENCIA | I11: AUMENTO DE OBRA OC.13558 ADICIONAL MUEBLES HOSPITAL DE SIMULACION CLINICA (CRISTOBAL CORREA) | J11: 5595975 | L11: =J11-K11 -> 5595975 | N11: ESPACIO MUEBLES LIMITADA | O11: C.Correa | Q11: #N/A | S11: =J11-K11-(SUM(T11:BU11)) -> 0 | U11: 5595975
A12: 409-1722 REMODELACIONES-OBRAS | B12: IMPREVISTOS | C12: 678 | D12: 738 | E12: COMPRA ELEMENTOS | F12: CRC Campus Doctor Luis Rivas Del Canto (vrae) | G12: CRC16 | H12: DOCENCIA | I12: MOBILIARIO HABILITACION LABORATORIO COMPUTACIÓN CRC16_210 (CRISTOBAL CORREA) | J12: 4405800 | L12: =J12-K12 -> 4405800 | N12: MULTIMUEBLES | O12: C.Correa | Q12: #N/A | S12: =J12-K12-(SUM(T12:BU12)) -> 0 | AB12: 4405800
A13: 409-1722 REMODELACIONES-OBRAS | B13: IMPREVISTOS | C13: 1475 | D13: 1475 | E13: REGULARIZACION | I13: ASESORIAS CES, CERTIFICACION EDIFICIOS SUSTENTABLES PABELLON DOCENTE Y HOSPITAL DE SIMULACION (CRISTOBAL CORREA) | J13: 15015909 | L13: =J13-K13 -> 15015909 | N13: 88 ARQUITECTOS LIMITADA | O13: C.Correa | P13: RC-031_26; RC-033_26 | Q13: #N/A | S13: =J13-K13-(SUM(T13:BU13)) -> 0 | AD13: 15015909
A14: 409-1722 REMODELACIONES-OBRAS | B14: IMPREVISTOS | C14: 2863 | D14: 2771 | E14: OTROS | F14: CSF Campus San Francisco | G14: CSF21 | I14: INSTALACION GOMAS REFLECTANTES EN PILARES ESTACIONAMIENTO CSF21 (CRISTOBAL CORREA) | J14: 1427829 | L14: =J14-K14 -> 1427829 | N14: CONSTRUCTORA IGECE LIMITADA | O14: C.Correa | P14: RC-167_26 | Q14: 46155 | R14: 0.50836806 | S14: =J14-K14-(SUM(T14:BU14)) -> 0 | AJ14: 1427829
A15: 409-1722 REMODELACIONES-OBRAS | B15: IMPREVISTOS | C15: 278 | D15: 233 | E15: AUMENTO DE OBRA | F15: CCC Campus Curacautin | H15: OTROS | I15: AUMENTO DE OBRA OC.3946-2025 CONSTRUCCIÓN CABAÑAS CENTRO RECREACIONAL CURACAUTIN. RESPONSABLE: DAVID SILVA. SEGUN COTIZACION N 522 | J15: 43411350 | L15: =J15-K15 -> 43411350 | N15: CONSTRUCTORA RUKATAMI | O15: D.Silva | Q15: #N/A | S15: =J15-K15-(SUM(T15:BU15)) -> 0 | V15: 43411350
A16: 409-1722 REMODELACIONES-OBRAS | B16: OBRAS DE SEGURIDAD, PAISAJISMO CURACAUTIN | C16: 674 | D16: 705 | E16: COMPRA ELEMENTOS | F16: CCC Campus Curacautin | G16: CCC | H16: ESPACIOS COMUNES | I16: SEÑALETICA CENTRO RECREACIONAL CURACAUTIN (DAVID SILVA) | J16: 4921911 | L16: =J16-K16 -> 4921911 | N16: DSIETE SPA | O16: D.Silva | P16: RC-282 | Q16: 46083 | R16: 0.71075231 | S16: =J16-K16-(SUM(T16:BU16)) -> 0 | AB16: 4921911
A17: 409-1722 REMODELACIONES-OBRAS | B17: MANTENCIÓN ESTRUCTURA MADERA LAMINADA PILARES Y VIGAS CSF14 - CSF16 | C17: 791 | D17: 858 | E17: OTROS | F17: CSF Campus San Francisco | H17: ESPACIOS COMUNES | I17: REPARACION Y MANTENCION DE ESTRUCTURAS DE MADELA LAMINADA EDIFICO CSF14, CSF15 Y CSF16 (DAVID SILVA) | J17: 94737758 | L17: =J17-K17 -> 94737758 | N17: AVANTI LTDA | O17: D.Silva | P17: RC-002_26; RC-118_26 | Q17: #N/A | S17: =J17-K17-(SUM(T17:BU17)) -> 0 | AC17: 68426229 | AJ17: 26311529
A18: 409-1722 REMODELACIONES-OBRAS | B18: CRC05 MEJORAS HABITABILIDAD INTERIOR | C18: 792 | D18: 859 | E18: REMODELACION | F18: CRC Campus Doctor Luis Rivas Del Canto (vet) | G18: CRC05 | H18: DOCENCIA | I18: MEJORAMIENTO TERMICO DE CUBIERTA SEGUNDO NIVEL EDIFICIO CRC05 (DAVID SILVA) | J18: 44864047 | L18: =J18-K18 -> 44864047 | N18: CONSTRUCTORA IGECE LIMITADA | O18: D.Silva | P18: RC-010_26; RC-119_26 | Q18: #N/A | S18: =J18-K18-(SUM(T18:BU18)) -> 0 | AC18: 40377642 | AJ18: 4486405
A19: 409-1722 REMODELACIONES-OBRAS | B19: IMPREVISTOS | C19: 1138 | D19: 1819 | E19: OTROS | F19: CSF Campus San Francisco | G19: CJP15 | H19: ESPACIOS COMUNES | I19: MEJORAMIENTO CAMARINES, DUCHAS GIMNASIO CAMPUS SAN FRANCISCO EDIFICIO 15 (DAVID SILVA) | J19: 19801637 | L19: =J19-K19 -> 19801637 | N19: ROMO Y CADI LIMITADA | O19: D.Silva | P19: RC-066_26 | Q19: 46118 | R19: 0.64304398 | S19: =J19-K19-(SUM(T19:BU19)) -> 0 | AF19: 19801637
A20: 409-1722 REMODELACIONES-OBRAS | B20: IMPREVISTOS | C20: 2637 | D20: 2500 | E20: ALHAJAMIENTO | F20: CRC Campus Doctor Luis Rivas Del Canto (vrae) | G20: CRC18 | I20: REPISAS PARA PAÑOL CARRERA INGENIERÍA ELÉCTRICA CRC18_180 FELIPE ANSELME) | J20: 1328150 | L20: =J20-K20 -> 1328150 | N20: MULTIMUEBLES | O20: F.Anselme | P20: RC-131_26 | Q20: 46140 | R20: 0.61581019 | S20: =J20-K20-(SUM(T20:BU20)) -> 0 | AI20: 1328150
A21: 409-1722 REMODELACIONES-OBRAS | B21: BIBICLETERO CRC (VRAE) | C21: 794 | D21: 861 | I21: CONSTRUCCION BICICLETERO CAMPUS LUIS RIVAS DEL CANTO , COSTADO CASETA GUARDIA (ISABEL RIQUELME) | J21: 16082457 | L21: =J21-K21 -> 16082457 | N21: GATICAR SPA | O21: I. Riquelme | P21: RC-283 | Q21: 46084 | R21: 0.4259838 | S21: =J21-K21-(SUM(T21:BU21)) -> 0 | AB21: 16082457
A22: 409-1722 REMODELACIONES-OBRAS | B22: BIBICLETERO CRC (VRAE) | C22: 1223 | D22: 1230 | E22: AUMENTO DE OBRA | F22: CRC Campus Doctor Luis Rivas Del Canto (vrae) | H22: ESPACIOS COMUNES | I22: INSTALACIÓN DE CANAL DE AGUAS LLUVIAS Y POLICARBONATO EN PARED TRAS ENCHUFES BICICLETERO CAMPUS LUIS RIVAS DEL CANTO (FELIPE ANSELME) | J22: 511700 | L22: =J22-K22 -> 511700 | N22: GATICAR SPA | O22: I. Riquelme | P22: RC-021_26 | Q22: 46092 | R22: 0.82554398 | S22: =J22-K22-(SUM(T22:BU22)) -> 0 | AC22: 511700
A23: 409-5243 INSTITUTO TECNOLOGICO | B23: EDIFICIO INGENIERÍA (EX TEC) + HABILITACIÓN | C23: 91 | D23: 66 | E23: AUMENTO DE OBRA | F23: CRC Campus Doctor Luis Rivas Del Canto (vet) | G23: CRC10 | H23: DOCENCIA | I23: AUMENTO DE OBRA OC. 9031 CONSTRUCCION EDIFICIO INGENIERIA CRC (EX TEC) JUAN IGNACIO SOLIS DE OVANDO | J23: 664691208 | K23: =186646382+118263881+132505939 -> 437416202 | L23: =J23-K23 -> 227275006 | N23: LSA INGENIERIA Y CONSTRUCCIÓN E.I.R.L. | O23: J.Solis de Ovando | P23: RC-286 | Q23: 46085 | R23: 0.61953704 | S23: =J23-K23-(SUM(T23:BU23)) -> 18000001 | AB23: 209275005
A24: 409-5506 - CASINO VRAE | B24: PERMISO + CONSTRUCCION CASINO CRC11 (VRAE) | C24: 1434 | D24: 1426 | E24: OBRA NUEVA | F24: CRC Campus Doctor Luis Rivas Del Canto (vrae) | G24: CRC11 | H24: OTROS | I24: Nuevo Edificio Casino CRC | J24: 855200912 | L24: =J24-K24 -> 855200912 | N24: LSA INGENIERIA Y CONSTRUCCIÓN E.I.R.L. | O24: J.Solis de Ovando | P24: RC-053_26; RC-054_26; RC-140_26; RC-209_26; RC-275_26 | Q24: #N/A | S24: =J24-K24-(SUM(T24:BU24)) -> -1 | AF24: 144479558 | AJ24: 69931126 | AO24: 167082324 | AS24: 155127189 | AW24: 178457507 | BB24: 97363163 | BF24: 42760046
A25: 409-1722 REMODELACIONES-OBRAS | B25: IMPREVISTOS | C25: 503 | D25: 449 | E25: AUMENTO DE OBRA | F25: CSF Campus San Francisco | G25: CSF01 | H25: ADMINISTRACION | I25: AUMENTO DE OBRA OC.11875 REMODELACION OFICINAS Y ATENCION A PUBLICO CSF01 ED. CAEP (JUAN IGNACIO SOLIS) | J25: 1522909 | L25: =J25-K25 -> 1522909 | N25: CONSTRUCTORA INGETRAPP | O25: J.Solis de Ovando | P25: RC-281 | Q25: 46083 | R25: 0.56324074 | S25: =J25-K25-(SUM(T25:BU25)) -> 0 | AB25: 1522909
A26: 409-1722 REMODELACIONES-OBRAS | B26: IMPREVISTOS | C26: 800 | D26: 733 | E26: REMODELACION | F26: CRC Campus Doctor Luis Rivas Del Canto (vrae) | G26: CRC18 | H26: ESPACIOS COMUNES | I26: CONSTRUCCION DE PAÑOL Y REHABILITACION DE FRONTIS CRC18 (JUAN IGNACIO SOLIS) | J26: 23807821 | L26: =J26-K26 -> 23807821 | N26: CONSTRUCTORA ALPLAS SPA | O26: J.Solis de Ovando | P26: RC-279; RC-086_26 | Q26: #N/A | S26: =J26-K26-(SUM(T26:BU26)) -> -5881058.7 | W26: =$L$15*0.3 -> 13023405 | AB26: 10713519 | AH26: 5951955.7
A27: 409-1722 REMODELACIONES-OBRAS | B27: REMODELACION LAB. SUELOS , CONSTRUCCION DE OFICINAS CPH02 (PHILLIPPI) | C27: 796 | D27: 752 | I27: ADECUACION DE ESPACIOS PARA OFICINAS CPH02 ESPACIOS EX LABORATORIO DE SUELOS (PHILLIPPI B) (JUAN IGNACIO SOLIS) | J27: 53297921 | L27: =J27-K27 -> 53297921 | N27: CONSTRUCTORA INGETRAPP | O27: J.Solis de Ovando | P27: RC-249_26; RC-250_26 | Q27: #N/A | S27: =J27-K27-(SUM(T27:BU27)) -> 0 | W27: 15989376 | AB27: 21319172 | AI27: 15989373
A28: 409-5243 INSTITUTO TECNOLOGICO | B28: EDIFICIO INGENIERÍA (EX TEC) + HABILITACIÓN | C28: 788 | D28: 731 | E28: ALHAJAMIENTO | F28: CRC Campus Doctor Luis Rivas Del Canto (vrae) | G28: CRC10 | H28: ADMINISTRACION | I28: HABILITACION MOBILIARIO OFICINAS 3ER NIVEL EDIFICIO INGENIERIA CRC10 (JUAN IGNACIO SOLIS) | J28: 25523715 | L28: =J28-K28 -> 25523715 | N28: ESPACIO MUEBLES LIMITADA | O28: J.Solis de Ovando | P28: RC-004_26; RC-006_26 | Q28: #N/A | S28: =J28-K28-(SUM(T28:BU28)) -> 1.5 | W28: =J28*0.3 -> 7657114.5 | AB28: 17866599
A29: 409-5243 INSTITUTO TECNOLOGICO | B29: EDIFICIO INGENIERÍA (EX TEC) + HABILITACIÓN | C29: 789 | D29: 732 | E29: ALHAJAMIENTO | F29: CRC Campus Doctor Luis Rivas Del Canto (vrae) | G29: CRC10 | H29: DOCENCIA | I29: MUEBLES HABILITACION LABORATORIO DE COMPUTACION EDIFICIO INGENIERIA CRC10 (JUAN IGNACIO SOLIS) | J29: 8425200 | L29: =J29-K29 -> 8425200 | N29: ESPACIO MUEBLES LIMITADA | O29: J.Solis de Ovando | P29: RC-003_26; RC-005_26 | Q29: #N/A | S29: =J29-K29-(SUM(T29:BU29)) -> 0 | W29: =J29*0.3 -> 2527560 | AC29: 5897640
A30: 409-5243 INSTITUTO TECNOLOGICO | B30: EDIFICIO INGENIERÍA (EX TEC) + HABILITACIÓN | C30: 1803 | D30: 1788 | E30: ALHAJAMIENTO | F30: CRC Campus Doctor Luis Rivas Del Canto (vrae) | G30: CRC10 | I30: MOBILITARIO INTERIOR CLOSET ESCALA CON CERRADURA PISOS 1,2,3 ED. INGENIERIA CRC10 (JUAN IGNACION SOLIS) | J30: 856800 | L30: =J30-K30 -> 856800 | N30: ESPACIO MUEBLES LIMITADA | O30: J.Solis de Ovando | P30: RC-064_26 | Q30: 46115 | R30: 0.9966088 | S30: =J30-K30-(SUM(T30:BU30)) -> 0 | AI30: 856800
A31: 409-1722 REMODELACIONES-OBRAS | B31: IMPREVISTOS | C31: 1806 | D31: 1845 | E31: AUMENTO DE OBRA | F31: CRC Campus Doctor Luis Rivas Del Canto (vrae) | G31: CRC18 | I31: AUMENTO DE OBRA OC.733 REVESTIMIENTO PERIMETRAL CRC18 GALPON 2 GRANDE (JUAN IGNACIO SOLIS) | J31: 1536340 | L31: =J31-K31 -> 1536340 | N31: CONSTRUCTORA ALPLAS SPA | O31: J.Solis de Ovando | P31: RC-068_26 | Q31: 46120 | R31: 0.41576389 | S31: =J31-K31-(SUM(T31:BU31)) -> 0 | AH31: 1536340
A32: 409-5243 INSTITUTO TECNOLOGICO | B32: EDIFICIO INGENIERÍA (EX TEC) + HABILITACIÓN | C32: 2055 | D32: 1991 | E32: ALHAJAMIENTO | F32: CRC Campus Doctor Luis Rivas Del Canto (vrae) | G32: CRC10 | I32: PIZARRAS MOVIL, HABILITACION SALA DE ESTUDIOS EDIFICIO INGENIERIA CRC10 (JUAN IGNACION SOLIS) | J32: 1266755 | L32: =J32-K32 -> 1266755 | N32: MELMAN SPA | O32: J.Solis de Ovando | Q32: #N/A | S32: =J32-K32-(SUM(T32:BU32)) -> 0 | AJ32: 1266755
A33: 409-5243 INSTITUTO TECNOLOGICO | B33: EDIFICIO INGENIERÍA (EX TEC) + HABILITACIÓN | C33: 2071 | D33: 2025 | E33: ALHAJAMIENTO | F33: CRC Campus Doctor Luis Rivas Del Canto (vrae) | G33: CRC10 | I33: EMPAVONADO DE OFICINAS Y CASINO EDIFICIO CRC10 (JUAN IGNACIOS SOLIS) | J33: 3599892 | L33: =J33-K33 -> 3599892 | O33: J.Solis de Ovando | P33: RC-013; RC-014; RC-015; RC-016; RC-019; RC-114_26 | Q33: #N/A | S33: =J33-K33-(SUM(T33:BU33)) -> 0 | AI33: 3599892
A34: 409-5243 INSTITUTO TECNOLOGICO | B34: EDIFICIO INGENIERÍA (EX TEC) + HABILITACIÓN | C34: 2809 | D34: 2692 | E34: ALHAJAMIENTO | F34: CRC Campus Doctor Luis Rivas Del Canto (vrae) | G34: CRC10 | I34: HABILITACION MOBILIARIO LABORATORIO DE PRE Y POST GRADO FACULTAD DE INGENIERIA (JUAN IGNACION SOLIS) | J34: 28468370 | L34: =J34-K34 -> 28468370 | N34: ESPACIO MUEBLES LIMITADA | O34: J.Solis de Ovando | P34: RC-156_26; RC-157_26 | Q34: #N/A | S34: =J34-K34-(SUM(T34:BU34)) -> 0 | AK34: 28468370
A35: 409-1722 REMODELACIONES-OBRAS | B35: MEJORAS ESPACIOS INTERNAS CSF10 (CREDITO) | C35: 651 | D35: 633 | E35: INSTALACIONES | F35: CSF Campus San Francisco | G35: CSF10 | H35: ADMINISTRACION | I35: INSTALACION EQUIPO DE AIRE ACONDICIONADO , MAS TRASLADO DE DOS EQUIPOS, CSF10_200 CREDITO Y RECAUDACION (LEONOR RIOS) | J35: 1997415 | L35: =J35-K35 -> 1997415 | N35: FLAVIA OYARZUN SOTO | O35: L. Rios | Q35: #N/A | S35: =J35-K35-(SUM(T35:BU35)) -> 0 | AB35: 1997415
A36: 409-1722 REMODELACIONES-OBRAS | B36: SEÑALETICA OFICINAS TERMINO EN CJP, CSF Y CRC | C36: 2790 | D36: 2598 | E36: ALHAJAMIENTO | F36: CRC Campus Doctor Luis Rivas Del Canto (vrae) | G36: CRC10 | I36: SEÑALÉTICA NOMBRE CRC10 Y NUMEROS EN CSL01 (LEONOR RIOS) | J36: 1074618 | L36: =J36-K36 -> 1074618 | N36: PUA DISEÑO | O36: L. Rios | P36: RC-115_26 | Q36: 46136 | R36: 0.44501157 | S36: =J36-K36-(SUM(T36:BU36)) -> 0 | AI36: 1074618
A37: 409-1722 REMODELACIONES-OBRAS | B37: BIBLIOTECA CSF02 ETAPA 2 Y 3, ELECTRICO | C37: 3170 | D37: 2873 | E37: REMODELACION | F37: CSF Campus San Francisco | G37: CSF02 | I37: REMODELACION PROYECTO ETAPA 2 Y 3 BIBLIOTECA CAMPUS SAN FRANCISCO (LEONOR RIOS) | J37: 12630236 | L37: =J37-K37 -> 12630236 | N37: CONSTRUCTORA Y SERVICIOS S-TEC SPA | O37: L. Rios | P37: RC-112_26 | Q37: 46135 | R37: 0.56186343 | S37: =J37-K37-(SUM(T37:BU37)) -> 0 | AJ37: 12630236
A38: 409-1722 REMODELACIONES-OBRAS | B38: OBRAS DE SEGURIDAD, PAISAJISMO CURACAUTIN | C38: 666 | D38: 663 | E38: INSTALACIONES | F38: CCC Campus Curacautin | G38: CCC | H38: ESPACIOS COMUNES | I38: INSTALACION SERVICIOS DE INTERNET SATELITAL CENTRO RECREACIONAL CURACAUTIN (ARTURO MEZA) | J38: 4699310 | L38: =J38-K38 -> 4699310 | N38: GYG SERVICIOS | O38: M.Zurita | P38: RC-164_26 | Q38: 46154 | R38: 0.656875 | S38: =J38-K38-(SUM(T38:BU38)) -> 0 | AJ38: 4699310
A39: 409-5243 INSTITUTO TECNOLOGICO | B39: EDIFICIO INGENIERÍA (EX TEC) + HABILITACIÓN | C39: 699 | D39: 703 | E39: INSTALACIONES | F39: CRC Campus Doctor Luis Rivas Del Canto (vrae) | G39: CRC10 | H39: DOCENCIA | I39: INSTALACIÓN DE ACCESS POINT EN EDIFICIO EX TEC (MAURICIO ZURITA) | J39: 2416890 | L39: =J39-K39 -> 2416890 | N39: GYG SERVICIOS | O39: M.Zurita | P39: RC-045_26 | Q39: 46107 | R39: 0.4341088 | S39: =J39-K39-(SUM(T39:BU39)) -> 0 | AF39: 2416890
A40: 409-1722 REMODELACIONES-OBRAS | B40: BIBLIOTECA CSF02 ETAPA 2 Y 3, ELECTRICO | C40: 803 | D40: 869 | E40: INSTALACIONES | F40: CSF Campus San Francisco | G40: CSF02 | H40: DOCENCIA | I40: REMODELACION PROYECTO ELECTRICO ETAPA 2 Y 3 EDIFICIO BIBLIOTECA, LABORATORIO DE COMPUTACION CSF02-311/CSF02_321 (ARTURO MEZA) | J40: 30530278 | L40: =J40-K40 -> 30530278 | N40: ELEKTRICA | O40: M.Zurita | P40: RC-288 | Q40: 46085 | R40: 0.72351852 | S40: =J40-K40-(SUM(T40:BU40)) -> 0 | AB40: 24424223 | AK40: 6106055
A41: 409-1722 REMODELACIONES-OBRAS | B41: IMPREVISTOS | I41: APS | J41: 18714740 | L41: =J41-K41 -> 18714740 | Q41: #N/A | S41: =J41-K41-(SUM(T41:BU41)) -> 0 | T41: 1905200 | X41: 2200000 | AA41: 4349400 | AF41: 4598000 | AJ41: 3293280 | AO41: 2368860
A42: 409-5506 - CASINO VRAE | B42: PERMISO + CONSTRUCCION CASINO CRC11 (VRAE) | I42: Otros | J42: =3426436+215219 -> 3641655 | L42: =J42-K42 -> 3641655 | Q42: #N/A | S42: =J42-K42-(SUM(T42:BU42)) -> 3641655
A43: 409-5243 INSTITUTO TECNOLOGICO | B43: EDIFICIO INGENIERÍA (EX TEC) + HABILITACIÓN | I43: Otros | J43: =4183240+238448 -> 4421688 | L43: =J43-K43 -> 4421688 | Q43: #N/A | S43: =J43-K43-(SUM(T43:BU43)) -> 4421688
A44: 409-1722 REMODELACIONES-OBRAS | B44: IMPREVISTOS | I44: Otros | J44: =2265645+142340+200000 -> 2607985 | L44: =J44-K44 -> 2607985 | Q44: #N/A | S44: =J44-K44-(SUM(T44:BU44)) -> 2607985
A45: 409-5243 INSTITUTO TECNOLOGICO | B45: EDIFICIO INGENIERÍA (EX TEC) + HABILITACIÓN | C45: 208 | D45: 1940 | E45: OTROS | F45: CRC Campus Doctor Luis Rivas Del Canto (vrae) | G45: CRC10 | I45: FCAEL. 4621 - ROXANA ELIANA RI | J45: 1796409 | L45: =J45-K45 -> 1796409 | Q45: #N/A | S45: =J45-K45-(SUM(T45:BU45)) -> 0 | AE45: 1796409
A46: 409-5243 INSTITUTO TECNOLOGICO | B46: IMPREVISTOS | C46: 777 | D46: 561 | I46: SP:777 - OC:561 - FCAEL. 144922807 - SODIMAC S.A | J46: 114030 | L46: =J46-K46 -> 114030 | N46: SODIMAC S.A. | Q46: #N/A | S46: =J46-K46-(SUM(T46:BU46)) -> 114030
A47: 409-1722 REMODELACIONES-OBRAS | B47: IMPREVISTOS | C47: 2865 | D47: 2773 | E47: COMPRA ELEMENTOS | F47: CSF Campus San Francisco | G47: CSF21 | H47: DOCENCIA | I47: COMPRA DE 02 SWITCH DE DATOS PARA RACK DE COMUNICACIONES LABORATORIO DE COMPUTACIÓN 230 CSF21 (ARTURO MEZA) | J47: 4538444 | L47: =J47-K47 -> 4538444 | N47: OPCIONES S.A. | O47: A. Meza | Q47: #N/A | S47: =J47-K47-(SUM(T47:BU47)) -> 4538444
A48: 409-5243 INSTITUTO TECNOLOGICO | B48: EDIFICIO INGENIERÍA (EX TEC) + HABILITACIÓN | C48: 2924 | D48: 2856 | E48: COMPRA ELEMENTOS | F48: CRC Campus Doctor Luis Rivas Del Canto (vrae) | G48: CRC10 | I48: COMPRA DE EXTINTORES PARA HABILITACION EN NUEVO EDIFICIO FAC. INGENIERIA CRC10 (JUAN IGNACIO SOLIS) | J48: 1302683 | L48: =J48-K48 -> 1302683 | N48: EXTINTORES SUPER | O48: J.Solis de Ovando | Q48: #N/A | S48: =J48-K48-(SUM(T48:BU48)) -> 1302683
A49: 409-5243 INSTITUTO TECNOLOGICO | B49: EDIFICIO INGENIERÍA (EX TEC) + HABILITACIÓN | C49: 2925 | D49: 3090 | E49: COMPRA ELEMENTOS | F49: CRC Campus Doctor Luis Rivas Del Canto (vrae) | G49: CRC10 | I49: HABILITACION GABINETE DEA CON SISTEMA DE AUDIO ALARMA Y BALIZA DE APERTURA NUEVO EDIFICIO FAC. INGENIERIA CRC10 (JUAN IGNACIO SOLIS) | J49: 2019430 | L49: =J49-K49 -> 2019430 | N49: dinamed store | O49: J.Solis de Ovando | Q49: #N/A | S49: =J49-K49-(SUM(T49:BU49)) -> 2019430
A50: 409-1722 REMODELACIONES-OBRAS | B50: REGULARIZACION EDIFICIOS | C50: 2947 | D50: 2867 | E50: REMODELACION | F50: CJP Campus San Juan Pablo II | G50: CJP07 | I50: CONSTRUCCION RAMPA ACCESO DOCTORADO (CRISTOBAL CORREA) | J50: 484030 | L50: =J50-K50 -> 484030 | N50: COMERCIAL Y FABRICA DE MUEBLES CLAUDIO GALLARDO E.I.R.L | O50: C.Correa | P50: RC-281_26 | Q50: #N/A | S50: =J50-K50-(SUM(T50:BU50)) -> 484030
A51: 409-5243 INSTITUTO TECNOLOGICO | B51: EDIFICIO INGENIERÍA (EX TEC) + HABILITACIÓN | C51: 3004 | D51: 2954 | E51: COMPRA ELEMENTOS | F51: CRC Campus Doctor Luis Rivas Del Canto (vrae) | G51: CRC10 | I51: ADHESIVOS LOCKERS EDIFICIO CRC10 (NUMERACIÓN) (USO ALUMNOS Y FUNCIONARIOS) JUAN IGNACIO SOLIS | J51: 312730 | L51: =J51-K51 -> 312730 | N51: COMERCIALIZADORA DANIELA PATRICIA ARRIAGADA CABA | O51: J.Solis de Ovando | P51: RC-117_26 | Q51: 46136 | R51: 0.66016204 | S51: =J51-K51-(SUM(T51:BU51)) -> 312730
A52: 409-1722 REMODELACIONES-OBRAS | B52: OBRAS DE SEGURIDAD, PAISAJISMO CURACAUTIN | C52: 3108 | D52: 3008 | F52: CCC Campus Curacautin | I52: AMPLIACION CASETA DE BOMBAS CON RADIER PARA RECONEXION PREDIO CURACAUTIN (DAVID SILVA) | J52: 3388430 | L52: =J52-K52 -> 3388430 | N52: LSA INGENIERIA Y CONSTRUCCIÓN E.I.R.L. | O52: D.Silva | P52: RC-210_26 | Q52: 46168 | S52: =J52-K52-(SUM(T52:BU52)) -> 0 | AN52: 3388430
A53: 409-1722 REMODELACIONES-OBRAS | B53: OBRAS DE SEGURIDAD, PAISAJISMO CURACAUTIN | C53: 3109 | D53: 3010 | I53: SEGURIDAD PERIMETRAL CAMPUS CURACAUTIN DURANTE PERIDO DE CONSTRUCCION DEL CENTRO RECREACIONAL (DAVID SILVA) | J53: 2772537 | L53: =J53-K53 -> 2772537 | N53: LSA INGENIERIA Y CONSTRUCCIÓN E.I.R.L. | O53: D.Silva | P53: RC-211_26 | Q53: 46168 | S53: =J53-K53-(SUM(T53:BU53)) -> 0 | AL53: 2772537
A54: 409-1722 REMODELACIONES-OBRAS | B54: BIBLIOTECA CSF02 ETAPA 2 Y 3, ELECTRICO | C54: 3123 | D54: 3011 | E54: AUMENTO DE OBRA | F54: CSF Campus San Francisco | I54: AUMENTO DE OBRA OC.869/2026 REMODELACION PROYECTO ELECTRICO ETAPA 2 Y 3 LABORATORIO DE COMPUTACION ED. BIBLIOTECA CAMPUS SAN FRANCISCO (ARTURO MEZA) | J54: 8315145 | L54: =J54-K54 -> 8315145 | N54: ELEKTRICA | O54: A. Meza | P54: RC-124_26 | Q54: 46139 | S54: =J54-K54-(SUM(T54:BU54)) -> 0 | AJ54: 8315145
A55: 409-1722 REMODELACIONES-OBRAS | B55: BIBLIOTECA CSF02 ETAPA 2 Y 3, ELECTRICO | C55: 3126 | D55: 3645 | E55: AUMENTO DE OBRA | F55: CSF Campus San Francisco | I55: AUMENTO DE OBRA OC.2695 REMODELACION EDIFICIO BIBLIOTECA ETAPA 2 Y 3 CAMPUS SAN FRANCISCO (LEONOR RIOS) | J55: 4960920 | L55: =J55-K55 -> 4960920 | N55: CONSTRUCTORA Y SERVICIOS S-TEC SPA | O55: L. Rios | P55: RC-185_26 | Q55: 46160 | S55: =J55-K55-(SUM(T55:BU55)) -> 0 | AL55: 4960920
A56: 409-1722 REMODELACIONES-OBRAS | B56: MANTENCIÓN ESTRUCTURA MADERA LAMINADA PILARES Y VIGAS CSF14 - CSF16 | C56: 3231 | D56: 3119 | E56: AUMENTO DE OBRA | F56: CSF Campus San Francisco | I56: AUMENTO DE OBRA OC.858/2026 MEJORAMIENTO DE ESTRUCTURAS DE MADERA DE VIGAS Y PILARES EDIFICIO 14 CAMPUS SAN FRANCISCO (DAVID SILVA) | J56: 8504097 | L56: =J56-K56 -> 8504097 | N56: AVANTI LTDA | O56: D.Silva | P56: RC-144_26 | Q56: 46146 | S56: =J56-K56-(SUM(T56:BU56)) -> 0 | AL56: 8504097
A57: 409-1722 REMODELACIONES-OBRAS | B57: BIBLIOTECA CSF02 ETAPA 2 Y 3, ELECTRICO | C57: 3234 | D57: 3082 | E57: ALHAJAMIENTO | F57: CSF Campus San Francisco | G57: csf02 | I57: REPARACIÓN DE CORTINAS METALICAS EN CSF02 EDIFICIO CSF02, JAIME ARELLANO (MAURICIO MATUS) | J57: 1000000 | L57: =J57-K57 -> 1000000 | N57: DECORENE | O57: M.Matus | P57: RC-236_26 | Q57: 46182 | S57: =J57-K57-(SUM(T57:BU57)) -> 0 | AO57: 1000000
A58: 409-5243 INSTITUTO TECNOLOGICO | B58: EDIFICIO INGENIERÍA (EX TEC) + HABILITACIÓN | C58: 2925 | D58: 3090 | E58: OTROS | F58: CRC Campus Doctor Luis Rivas Del Canto (vrae) | G58: CRC10 | I58: HABILITACION GABINETE DEA CON SISTEMA DE AUDIO ALARMA Y BALIZA DE APERTURA NUEVO EDIFICIO FAC. INGENIERIA CRC10 (JUAN IGNACIO SOLIS) | J58: 2019430 | L58: =J58-K58 -> 2019430 | N58: RyEGroupSpa | O58: J.Solis de Ovando | Q58: #N/A | S58: =J58-K58-(SUM(T58:BU58)) -> 0 | AN58: 2019430
A59: 409-5243 INSTITUTO TECNOLOGICO | B59: EDIFICIO INGENIERÍA (EX TEC) + HABILITACIÓN | C59: 3290 | E59: ALHAJAMIENTO | F59: CRC Campus Doctor Luis Rivas Del Canto (vrae) | G59: CRC10 | I59: SEÑALETICAS 3ER PISO NUEVO EDIFICIO CRC10 EDIFICIO INGENIERIA (DAVID SILVA) | J59: 3685318 | L59: =J59-K59 -> 3685318 | N59: DSIETE SPA | O59: D.Silva | Q59: #N/A | S59: =J59-K59-(SUM(T59:BU59)) -> 0 | AM59: 3685318
A60: 409-1722 REMODELACIONES-OBRAS | B60: OBRAS DE SEGURIDAD, PAISAJISMO CURACAUTIN | C60: 3388 | D60: 3147 | I60: COMPRA DE ARTICULOS DE CASA PARA HABILITACION CABAÑAS CURACAUTIN (MAURICIO MATUS) | J60: 663760 | L60: =J60-K60 -> 663760 | N60: SODIMAC S.A. | O60: M.Matus | Q60: #N/A | S60: =J60-K60-(SUM(T60:BU60)) -> 663760
A61: 409-1722 REMODELACIONES-OBRAS | B61: OBRAS DE SEGURIDAD, PAISAJISMO CURACAUTIN | C61: 3397 | D61: 3149 | I61: COMPRA DE ARTICULOS DE CASA PARA HABILITACION CABAÑAS CURACAUTIN (MAURICIO MATUS) | J61: 683812 | L61: =J61-K61 -> 683812 | N61: SODIMAC S.A. | O61: M.Matus | Q61: #N/A | S61: =J61-K61-(SUM(T61:BU61)) -> 683812
A62: 409-1722 REMODELACIONES-OBRAS | B62: PAISAJISMO ESPACIO TRAS CRC18 (ÁREA VERDE) | C62: 3527 | D62: 3332 | I62: INSTALACION ELECTRICA URBANIZACION Y ALIMENTACION DE CONTENEDORES CRC ARQUEOLOGIA (ARTURO MEZA) | J62: 14669999 | L62: =J62-K62 -> 14669999 | N62: GYG SERVICIOS | O62: A. Meza | P62: RC-302_26 | Q62: #N/A | S62: =J62-K62-(SUM(T62:BU62)) -> 0 | AN62: 14669999
A63: 409-5243 INSTITUTO TECNOLOGICO | B63: EDIFICIO INGENIERÍA (EX TEC) + HABILITACIÓN | C63: 3477 | D63: 3296 | E63: ALHAJAMIENTO | F63: CRC Campus Doctor Luis Rivas Del Canto (vrae) | G63: CRC10 | I63: INCORPORACION SEÑALETICA LOCKERS , CRC10 EDIFICIO DE INGENIERIA 1ER , 2DO NIVEL CRC10 (JUAN IGNACIO SOLIS) | J63: 78000 | L63: =J63-K63 -> 78000 | N63: COMERCIALIZADORA DANIELA PATRICIA ARRIAGADA CABA | O63: J.Solis de Ovando | P63: RC-173_26; RC-214_26 | Q63: #N/A | S63: =J63-K63-(SUM(T63:BU63)) -> 0 | AS63: 78000
A64: 409-5243 INSTITUTO TECNOLOGICO | B64: EDIFICIO INGENIERÍA (EX TEC) + HABILITACIÓN | C64: 3597 | D64: 3405 | E64: ALHAJAMIENTO | F64: CRC Campus Doctor Luis Rivas Del Canto (vrae) | G64: CRC10 | I64: HABILITACION MOBILIARIO CASETA DE SONIDO Y CONTROL CRC 10 AUDITORIO (JUAN IGNACIO SOLIS) | J64: 493850 | L64: =J64-K64 -> 493850 | N64: ESPACIO MUEBLES LIMITADA | O64: J.Solis de Ovando | P64: RC-233_26 | Q64: 46175 | S64: =J64-K64-(SUM(T64:BU64)) -> 0 | AN64: 493850
A65: 409-1722 REMODELACIONES-OBRAS | B65: IMPREVISTOS | C65: 3610 | D65: 3416 | E65: ALHAJAMIENTO | F65: CLE Nuestra Señora de Lourdes | I65: MUEBLES LABORATORIO DE SANGRE CONFECCIONES ERGONÓMICAS Y DE SEGURIDAD EN MESÓN RECEPCIÓN, AJUSTES TOMAS DE MUESTRAS Y MESONES FALTANTES EN SALA PROCESOS. (CRISTOBAL CORREA) | J65: 2648916 | L65: =J65-K65 -> 2648916 | N65: FLAVIA OYARZUN SOTO | O65: C.Correa | P65: RC-200_26 | Q65: 46162 | S65: =J65-K65-(SUM(T65:BU65)) -> 0 | AM65: 2648916
A66: 409-1722 REMODELACIONES-OBRAS | B66: IMPREVISTOS | C66: 3677 | D66: 3520 | E66: INSTALACIONES | F66: CML Campus Monseñor Alejandro Menchaca Lira | I66: INSTALACION EQUIPO DE AIRE ACONDICIONADO PARA OFICINA DE ARTESANIAS CML05_102 (ARTURO MEZA) | J66: 1011500 | L66: =J66-K66 -> 1011500 | N66: REAL CLIMA | O66: A. Meza | P66: RC-184_26 | Q66: 46160 | S66: =J66-K66-(SUM(T66:BU66)) -> 0 | AM66: 1011500
A67: 409-5243 INSTITUTO TECNOLOGICO | B67: EDIFICIO INGENIERÍA (EX TEC) + HABILITACIÓN | C67: 3796 | D67: 3647 | E67: ALHAJAMIENTO | F67: CRC Campus Doctor Luis Rivas Del Canto (vrae) | G67: CRC10 | I67: SEÑALETICA INTERIOR CON MATERIAL EXISTENTE PARA EDIFICIO CRC 10 (DAVID SILVA) | J67: 821100 | L67: =J67-K67 -> 821100 | N67: ROTULADOS DISEÑO Y PRODUCCION | O67: D.Silva | P67: RC-196_26; RC-197_26 | Q67: #N/A | S67: =J67-K67-(SUM(T67:BU67)) -> 0 | AM67: 821100
A68: 409-5243 INSTITUTO TECNOLOGICO | B68: EDIFICIO INGENIERÍA (EX TEC) + HABILITACIÓN | C68: 3854 | D68: 3661 | E68: INSTALACIONES | F68: CEC Campus Educacion Continua | G68: CRC10 | I68: CAMBIO DE ENCHUFES INDUSTRIALES PARA MAQUINAS DE LABORATORIO CRC10_160 CRC10_180 (ARTURO MEZA) | J68: 86882 | L68: =J68-K68 -> 86882 | N68: J&D Ingeniería y ejecución | O68: A. Meza | P68: RC-218_26 | Q68: 46170 | S68: =J68-K68-(SUM(T68:BU68)) -> 0 | AN68: 86882
A69: 409-5243 INSTITUTO TECNOLOGICO | B69: EDIFICIO INGENIERÍA (EX TEC) + HABILITACIÓN | C69: 3943 | D69: 3758 | E69: INSTALACIONES | F69: CEC Campus Educacion Continua | G69: CRC10 | I69: INSTALACION DE CONTROLES DE ACCESO BIOMETRICO, BRAZOS HIDRAULICOS Y BOTONERAS EDIFICIO CRC10 (OSCAR PAINEN | J69: 17497760 | L69: =J69-K69 -> 17497760 | N69: GYG SERVICIOS | O69: O. Painen | Q69: #N/A | S69: =J69-K69-(SUM(T69:BU69)) -> 0 | AW69: 17497760
A70: 409-5243 INSTITUTO TECNOLOGICO | B70: EDIFICIO INGENIERÍA (EX TEC) + HABILITACIÓN | C70: 3964 | D70: 3774 | E70: ALHAJAMIENTO | F70: CEC Campus Educacion Continua | G70: CRC10 | I70: HABILITACIÓN PODIO AUDITORIO CRC10 (JUAN IGNACIO SOLIS) | J70: 404600 | L70: =J70-K70 -> 404600 | N70: ESPACIO MUEBLES LIMITADA | O70: J.Solis de Ovando | P70: RC-231_26 | Q70: 46175 | S70: =J70-K70-(SUM(T70:BU70)) -> 404600
A71: 409-5243 INSTITUTO TECNOLOGICO | B71: EDIFICIO INGENIERÍA (EX TEC) + HABILITACIÓN | C71: 3968 | D71: 3775 | E71: ALHAJAMIENTO | F71: CEC Campus Educacion Continua | G71: CRC10 | I71: HABILITACIÓN LAVAFONDO CASINO PROVISORIO CRC10 (JUAN IGNACIO SOLIS) | J71: 739704 | L71: =J71-K71 -> 739704 | N71: ESPACIO MUEBLES LIMITADA | O71: J.Solis de Ovando | P71: RC-232_26 | Q71: 46175 | S71: =J71-K71-(SUM(T71:BU71)) -> 739704
A72: 409-1722 REMODELACIONES-OBRAS | B72: SEÑALETICA OFICINAS TERMINO EN CJP, CSF Y CRC | C72: 4026 | D72: 3808 | E72: ALHAJAMIENTO | F72: CEC Campus Educacion Continua | I72: - SEÑALETICA CRC TOTEMS CRC01 TUNEL (LEONOR RIOS) | J72: 159936 | L72: =J72-K72 -> 159936 | N72: PUA DISEÑO | O72: L. Rios | P72: RC-242_26 | Q72: 46185 | S72: =J72-K72-(SUM(T72:BU72)) -> 159936
A73: 409-1722 REMODELACIONES-OBRAS | B73: SEÑALETICA OFICINAS TERMINO EN CJP, CSF Y CRC | C73: 4027 | D73: 3810 | E73: OTROS | F73: CJP Campus San Juan Pablo II | I73: SEÑALETICA RETIRO EMPAVONADOS CJP03, 08 Y 10 TRASLADO DE FACULTAD DE INGENIERÍA Y INSTALACIÓN DE SEÑALÉTICA OFICIAL (LEONOR RIOS) | J73: 196350 | L73: =J73-K73 -> 196350 | N73: COMERCIALIZADORA DANIELA PATRICIA ARRIAGADA CABA | O73: L. Rios | P73: RC-213_26 | Q73: 46168 | S73: =J73-K73-(SUM(T73:BU73)) -> 196350
A74: 409-1722 REMODELACIONES-OBRAS | B74: SEÑALETICA OFICINAS TERMINO EN CJP, CSF Y CRC | C74: 4037 | D74: 3815 | E74: OTROS | F74: CLE Nuestra Señora de Lourdes | I74: SEÑALETICA CSL01 INSTALACIÓN NÚMEROS EXTERIOR SOBRE ACCESO ESTACIONAMIENTO (LEONOR RIOS) | J74: 85323 | L74: =J74-K74 -> 85323 | N74: DSIETE SPA | O74: L. Rios | P74: RC-237_26 | Q74: 46182 | S74: =J74-K74-(SUM(T74:BU74)) -> 85323
A75: 409-5243 INSTITUTO TECNOLOGICO | B75: EDIFICIO INGENIERÍA (EX TEC) + HABILITACIÓN | C75: 4239 | D75: 4005 | E75: OTROS | I75: PAGO DERECHOS MUNICIPALES EDIFICIO INGENIERIA (TEC) CRC10 | J75: 10851688 | L75: =J75-K75 -> 10851688 | N75: DOM | O75: J.Solis de Ovando | Q75: #N/A | S75: =J75-K75-(SUM(T75:BU75)) -> 0 | AO75: 10851688
A76: 409-1722 REMODELACIONES-OBRAS | B76: NORMALIZACIÓN SALA DE BASURA CSF Y CJP | C76: 4313 | D76: 4097 | E76: REMODELACION | F76: CJP Campus San Juan Pablo II | I76: REPARACIÓN Y PINTURA DE SALA DE BASURA POR PERMISO DE SALUBRIDA CJP104 SALA DE BASURA (LEONOR RIOS) | J76: 1333871 | L76: =J76-K76 -> 1333871 | N76: FLAVIA OYARZUN SOTO | O76: L. Rios | P76: RC-238_26 | Q76: 46182 | S76: =J76-K76-(SUM(T76:BU76)) -> 0 | AO76: 1333871
A77: 409-1722 REMODELACIONES-OBRAS | B77: SEÑALETICA OFICINAS TERMINO EN CJP, CSF Y CRC | C77: 4317 | D77: 4100 | I77: SEÑALÉTICA CAMPAÑA NO FUMAR - RECTANGULAR (LEONOR RIOS) | J77: 220150 | L77: =J77-K77 -> 220150 | N77: ROTULADOS DISEÑO Y PRODUCCION | O77: L. Rios | P77: RC-285_26 | Q77: #N/A | S77: =J77-K77-(SUM(T77:BU77)) -> 0 | AO77: 220150
A78: 409-1722 REMODELACIONES-OBRAS | B78: IMPREVISTOS | C78: 4319 | D78: 4103 | I78: CONTRUCION DE TABIQUE, DIVISION CAMARIN GUARDIAS CAMPUS SAN FRANCISCO (CRISTOBAL CORREA ) | J78: 749700 | L78: =J78-K78 -> 749700 | N78: AMARIS CONSTRUCTORA | O78: L. Rios | P78: RC-265_26 | Q78: 46195 | S78: =J78-K78-(SUM(T78:BU78)) -> 0 | AO78: 749700
A79: 409-1722 REMODELACIONES-OBRAS | B79: IMPREVISTOS | C79: 4406 | D79: 4190 | I79: REUBICACIÓN UPS CRC10 A NUEVA UBICACION (ARTURO MEZA) | J79: 797300 | L79: =J79-K79 -> 797300 | N79: GYG SERVICIOS | O79: A. Meza | P79: RC-239_26 | Q79: #N/A | S79: =J79-K79-(SUM(T79:BU79)) -> 0 | AO79: 797300
A80: 409-1722 REMODELACIONES-OBRAS | B80: IMPREVISTOS | C80: 4411 | D80: 4219 | E80: REMODELACION | F80: CSF Campus San Francisco | G80: CSF16 | I80: REMODELACION OFICINA CSF16_414, ASISTENTES CARRERAS TECNICAS (CRISTOBAL CORREA) | J80: 1401043 | L80: =J80-K80 -> 1401043 | N80: CONSTRUCTORA IGECE LIMITADA | O80: C.Correa | Q80: #N/A | S80: =J80-K80-(SUM(T80:BU80)) -> 0 | AS80: 1401043
A81: 409-1722 REMODELACIONES-OBRAS | B81: SEÑALETICA OFICINAS TERMINO EN CJP, CSF Y CRC | C81: 4634 | D81: 4475 | G81: CJP03 | I81: INSTALACIÓN EMPAVONADO OFICINA (LEONOR RÍOS) | J81: 48900 | L81: =J81-K81 -> 48900 | N81: COMERCIALIZADORA DANIELA PATRICIA ARRIAGADA CABA | O81: L. Rios | P81: RC-262_26 | Q81: 46195 | S81: =J81-K81-(SUM(T81:BU81)) -> 48900
A82: 409-1722 REMODELACIONES-OBRAS | B82: IMPREVISTOS | C82: 4641 | D82: 4534 | E82: OBRA NUEVA | F82: CRC Campus Doctor Luis Rivas Del Canto (vrae) | I82: CONFECCIÓN DE CIERRE PERIMETRAL RECINTO ARQUEOLÓGICO Y TUPAS (CRISTÓBAL CORREA) | J82: 799502 | L82: =J82-K82 -> 799502 | N82: AMARIS CONSTRUCTORA | O82: C.Correa | P82: RC-267_26 | Q82: 46196 | S82: =J82-K82-(SUM(T82:BU82)) -> 0 | AP82: =J82 -> 799502
A83: 409-1722 REMODELACIONES-OBRAS | B83: IMPREVISTOS | C83: 4719 | D83: 4569 | I83: HABILITACIÓN ELÉCTRICA Y RED PARA 2 PUESTOS DE TRABAJO OFICINAS CP03_137-134. | J83: 796575 | L83: =J83-K83 -> 796575 | N83: ELEKTRICA | O83: L. Rios | P83: RC-270_26 | Q83: 46196 | S83: =J83-K83-(SUM(T83:BU83)) -> 0 | AP83: 796575
A84: 409-1722 REMODELACIONES-OBRAS | B84: SEÑALETICA OFICINAS TERMINO EN CJP, CSF Y CRC | C84: 4720 | D84: 4596 | I84: SEÑALÉTICA, COMPRA DE PORTA HORARIOS PENDIENTES Y SOPORTE OFICINAS CSF15 (LEONOR RIOS) | J84: 1523295 | L84: =J84-K84 -> 1523295 | N84: DSIETE SPA | O84: L. Rios | Q84: #N/A | S84: =J84-K84-(SUM(T84:BU84)) -> 0 | AQ84: 1523295
A85: 409-5243 INSTITUTO TECNOLOGICO | B85: EDIFICIO INGENIERÍA (EX TEC) + HABILITACIÓN | C85: 4723 | D85: 4609 | E85: AUMENTO DE OBRA | F85: CRC Campus Doctor Luis Rivas Del Canto (vrae) | G85: CRC10 | I85: AUMENTO DE OBRA N°3 CONSTRUCCIÓN EDIFICIO INGENIERÍA CRC10 (JUAN IGNACIO SOLÍS DE OVANDO) | J85: 135040474 | L85: =J85-K85 -> 135040474 | N85: LSA INGENIERIA Y CONSTRUCCIÓN E.I.R.L. | O85: J.Solis de Ovando | P85: RC-244_26 | Q85: 46188 | S85: =J85-K85-(SUM(T85:BU85)) -> 0 | AP85: 135040474
A86: 409-1722 REMODELACIONES-OBRAS | B86: SEÑALETICA OFICINAS TERMINO EN CJP, CSF Y CRC | C86: 4797 | D86: 4634 | I86: REPOSICIÓN E INSTALACIÓN DE PORTA HORARIOS POR CAMBIOS, ASÍ COMO INSTALACIÓN DE SOPORTES ASOCIADOS A CLASES FALTANTES. (LEONOR RIOS) | J86: 6277571 | L86: =J86-K86 -> 6277571 | N86: DSIETE SPA | O86: L. Rios | Q86: #N/A | S86: =J86-K86-(SUM(T86:BU86)) -> 0 | AR86: 6277571
A87: 409-1722 REMODELACIONES-OBRAS | B87: IMPREVISTOS | C87: 4869 | D87: 4807 | I87: PAGO PARA OBTENCIÓN CERTIFICADO DE RECEPCIÓN DE PROYECTO DE DETENCIÓN VEHICULAR (CRISTOBAL CORREA) | J87: 143012 | L87: =J87-K87 -> 143012 | N87: municipalidad de temuco | O87: C.Correa | Q87: #N/A | S87: =J87-K87-(SUM(T87:BU87)) -> 143012
A88: 409-1722 REMODELACIONES-OBRAS | B88: IMPREVISTOS | C88: 4957 | D88: 4806 | E88: INSTALACIONES | I88: ACONDICIONAMIENTO ELÉCTRICO DE ESPACIOS PARA LAB. CLINICO UCT, UBICADO EN HOSPITAL DE SIMULACIÓN (ARTURO MEZA) | J88: 3888798 | L88: =J88-K88 -> 3888798 | N88: INGERTEMUCO INGENIERIA SPA | O88: A. Meza | P88: RC-254_26 | Q88: 46192 | S88: =J88-K88-(SUM(T88:BU88)) -> 0 | AQ88: 3888798
A89: 409-5506 - CASINO VRAE | B89: PERMISO + CONSTRUCCION CASINO CRC11 (VRAE) | C89: 5068 | D89: 4997 | E89: INSTALACIONES | I89: PROYECTO GAS EDIFICIO CASINO CRC11 (JUAN IGNACIO SOLID DE OVANDO) | J89: 797300 | L89: =J89-K89 -> 797300 | N89: INGENIERIA Y CONSTRUCCIONES MARCELO SEBASTIAN CARO SOTO E.I.R.L. | O89: J.Solis de Ovando | P89: RC-277_26 | Q89: 46198 | S89: =J89-K89-(SUM(T89:BU89)) -> 0 | AQ89: 797300
A90: 409-1722 REMODELACIONES-OBRAS | B90: IMPREVISTOS | C90: 5196 | D90: 5048 | I90: COMPRA MOBILIARIO CJP03 OF 137-134 (LEONOR RIOS) | J90: 1015644 | L90: =J90-K90 -> 1015644 | N90: CONSTRUCTORA IGECE LIMITADA | O90: L. Rios | Q90: #N/A | S90: =J90-K90-(SUM(T90:BU90)) -> 0 | AR90: 1015644
A91: 409-1722 REMODELACIONES-OBRAS | B91: IMPREVISTOS | I91: traspaso presupuestario N°1341 | J91: 73000000 | L91: =J91-K91 -> 73000000 | Q91: #N/A | S91: =J91-K91-(SUM(T91:BU91)) -> 73000000
A92: 409-1722 REMODELACIONES-OBRAS | B92: SEÑALETICA OFICINAS TERMINO EN CJP, CSF Y CRC | C92: 5437 | D92: 5188 | I92: SEÑALÉTICA NÚMEROS: INCORPORACIÓN DE NÚMEROS 18 Y 17 EN EXTERIOR DE EDIFICIOS CRC18 Y CRC 17 RESPECTIVAMENTE, PARA SU UBICACIÓN (LEONOR RIOS) | J92: 155771 | L92: =J92-K92 -> 155771 | N92: ROTULADOS DISEÑO Y PRODUCCION | O92: L. Rios | P92: RC-294_26 | Q92: #N/A | S92: =J92-K92-(SUM(T92:BU92)) -> 155771
A93: 409-1722 REMODELACIONES-OBRAS | B93: IMPREVISTOS | C93: 5549 | D93: 5315 | I93: TECHO Y SENDERO ARQUEOLOGIA. CC 409-1722 ---PROVEEDOR ANARIS CONSTRUCTORA SPA - COTI 81 $3.998.400 (CRISTOBAL CORREA) | J93: 3998400 | L93: =J93-K93 -> 3998400 | N93: AMARIS CONSTRUCTORA | O93: C.Correa | Q93: #N/A | S93: =J93-K93-(SUM(T93:BU93)) -> 3998400
A94: 409-1722 REMODELACIONES-OBRAS | B94: SEÑALETICA OFICINAS TERMINO EN CJP, CSF Y CRC | C94: 5664 | D94: 5439 | I94: ENUMERACIÓN EMPAVONADO DE LOCKERS DE BIBLIOTECA CSF02_321. PROVEEDOR COM DANIELA ARRIAGADA CABA EIRL. COTI 1134 $190.780 (LEONOR RIOS) | J94: 190780 | L94: =J94-K94 -> 190780 | N94: COMERCIALIZADORA DANIELA PATRICIA ARRIAGADA CABA | O94: L. Rios | S94: =J94-K94-(SUM(T94:BU94)) -> 190780
A95: 409-5243 INSTITUTO TECNOLOGICO | B95: EDIFICIO INGENIERÍA (EX TEC) + HABILITACIÓN | C95: 5791 | D95: 5541 | I95: BODEGAS RESPEL/SUSPEL CAMPUS LUIS RIVAS DEL CANTO (JUAN IGNACIO SOLIS) | J95: 13239702 | L95: =J95-K95 -> 13239702 | N95: ECOSTANDARD SPA | O95: J.Solis de Ovando | S95: =J95-K95-(SUM(T95:BU95)) -> 13239702
A96: 409-1722 REMODELACIONES-OBRAS | B96: IMPREVISTOS | C96: 5891 | D96: 5665 | I96: NORMALIZACION Y CERTIFICACION ELECTRICA PARA T1, LABORATORIO EDIFICIO CRC18_180 (ARTURO MEZA) | J96: 16397359 | L96: =J96-K96 -> 16397359 | N96: ELEKTRICA | O96: M.Zurita | S96: =J96-K96-(SUM(T96:BU96)) -> 16397359
A97: 409-1722 REMODELACIONES-OBRAS | B97: SEÑALETICA OFICINAS TERMINO EN CJP, CSF Y CRC | C97: 5955 | D97: 5639 | I97: SEÑALETICA CRC NÚMERO PARA ACREDITACIÓN DE CARRERAS TECNICAS (LEONOR RIOS) | J97: 45000 | L97: =J97-K97 -> 45000 | N97: COMERCIALIZADORA DANIELA PATRICIA ARRIAGADA CABA | O97: L. Rios | S97: =J97-K97-(SUM(T97:BU97)) -> 45000
A98: 409-1722 REMODELACIONES-OBRAS | B98: SEÑALETICA OFICINAS TERMINO EN CJP, CSF Y CRC | C98: 5956 | D98: 5640 | I98: INSTALACIÓN DE SEÑALÉTICA EN CONTENEDORES CRC13 (LEONOR RIOS) | J98: 297000 | L98: =J98-K98 -> 297000 | N98: COMERCIALIZADORA DANIELA PATRICIA ARRIAGADA CABA | O98: L. Rios | S98: =J98-K98-(SUM(T98:BU98)) -> 297000
A99: 409-5506 - CASINO VRAE | B99: CASINO CRC11 (VRAE) HABILITACIÓN | C99: 6054 | I99: HABILITACION COCINA INDUSTRIAL CASINO CRC 11 (JUAN IGNACIO SOLIS) | J99: 98069090 | L99: =J99-K99 -> 98069090 | N99: ESPACIO MUEBLES LIMITADA | O99: J.Solis de Ovando | S99: =J99-K99-(SUM(T99:BU99)) -> 98069090
A100: 409-6293 - CENTRO RECREACIONAL SAN NICOLAS | B100: OBRAS DE SEGURIDAD, PAISAJISMO CURACAUTIN | C100: 6147 | I100: CONSTRUCCION ALERO DE PROTECCIÓN CABAÑAS CURACAUTIN (DAVID SILVA) | J100: 2196742 | L100: =J100-K100 -> 2196742 | N100: CONSTRUCTORA IGECE LIMITADA | O100: D.Silva | S100: =J100-K100-(SUM(T100:BU100)) -> 2196742
...

Sheet Base de datoas ≤ 2025
Q1: =SUM(Q4:Q1002) -> 0 | R1: =SUM(R4:R1002) -> 0 | S1: =SUM(S4:S1002) -> 0 | T1: =SUM(T4:T1002) -> 18533845 | U1: =SUM(U4:U1002) -> 0 | V1: =SUM(V4:V1002) -> 0 | W1: =SUM(W4:W1002) -> 0 | X1: =SUM(X4:X1002) -> 0 | ... BR1: =SUM(BR4:BR1002) -> 0
Q2: Semana 1-Ene | R2: Semana 2-Enero | S2: Semana 3-Ene | T2: Semana 4-Ene | U2: Semana 1-Feb | V2: Semana 2-Feb | W2: Semana 3-Febr | X2: Semana 4-Feb | Y2: Semana 1-Mar | Z2: Semana 2-Marz | AA2: Semana 3-Marzo | AB2: Semana 4-Mar | AC2: Semana 1-Abri | AD2: Semana 2-Abri | AE2: Semana 3-Abril | AF2: Semana 4-Abril | AG2: Semana 5-Abri | AH2: Semana 1-May | AI2: Semana 2-Mayo | AJ2: Semana 3-Mayo | AK2: Semana 4-Mayo | AL2: Semana 1-Jun | AM2: Semana 2-Jun | AN2: Semana 3-Junio | AO2: Semana 4-Junio | AP2: Semana 1-Juli | AQ2: Semana 2-Jul | AR2: Semana 3-Julio | AS2: Semana 4-Julio | AT2: Semana 5-Juli | AU2: Semana 1-Ago | AV2: Semana 2-Agos | AW2: Semana 3-Agos | AX2: Semana 4-Agos | AY2: Semana 1-Sept | AZ2: Semana 2-Septi | BA2: Semana 3-Septi | BB2: Semana 4-Septi | BC2: Semana 5-Septi | BD2: Semana 1-Octu | BE2: Semana 2-Oct | BF2: Semana 3-Octu | BG2: Semana 4-Octu | BH2: Semana 5-Octu | BI2: Semana 1-Nov | BJ2: Semana 2-Novi | BK2: Semana 3-Novi | BL2: Semana 4-Novi | BM2: Semana 1-Dic | BN2: Semana 2-Dic | BO2: Semana 3-Dici | BP2: Semana 4-Dici | BQ2: Semana 5-Dici | BR2: Semana 1-Ene
A3: CC | B3: Proyecto | C3: Año | D3: OC | E3: Tipo Obra | F3: Campus | G3: Edificio | H3: Uso | I3: Descripción | J3: Monto | K3: Pagado | L3: Saldo | M3: % | N3: Contratista | O3: Responsable | P3: Δ | Q3: 05 al 11 | R3: 12 al 18 | S3: 19 al 25 | T3: 26 al 01 | U3: 02 al 08 | V3: 09 al 15 | W3: 16 al 22 | X3: 23 al 01 | Y3: 02 al 08 2 | Z3: 09 al 15 2 | AA3: 16 al 22 2 | AB3: 23 al 29 | AC3: 30 al 05 | AD3: 06 al 12 | AE3: 13 al 19 | AF3: 20 al 26 | AG3: 27 al 03 | AH3: 04 al 10 | AI3: 11 al 17 | AJ3: 18 al 24 | AK3: 25 al 31 | AL3: 01 al 07 | AM3: 08 al 14 | AN3: 15 al 21 | AO3: 22 al 28 | AP3: 29 al 05 | AQ3: 06 al 12 2 | AR3: 13 al 19 2 | AS3: 20 al 26 2 | AT3: 27 al 02 | AU3: 03 al 09 | AV3: 10 al 16 | AW3: 17 al 23 | AX3: 24 al 30 | AY3: 31al 06 | AZ3: 07 al 13 | BA3: 14 al 20 | BB3: 21 al 27 | BC3: 28 al 04 | BD3: 05 al 11 2 | BE3: 12 al 18 2 | BF3: 19 al 25 2 | BG3: 26 al 01 2 | BH3: 02 al 08 3 | BI3: 09 al 15 3 | BJ3: 16 al 22 3 | BK3: 23 al 29 2 | BL3: 24 al 30 2 | BM3: 30 al 06 | BN3: 07 al 13 2 | BO3: 14 al 20 2 | BP3: 21 al 27 2 | BQ3: 28 al 03 | BR3: 05 al 11 3
A4: 409-5243 INSTITUTO TECNOLOGICO | B4: EDIFICIO INGENIERÍA (EX TEC) + HABILITACIÓN | C4: 2024 | D4: 8022 | E4: AUMENTO DE OBRA | F4: CRC Campus Doctor Luis Rivas Del Canto (vrae) | G4: CRC10 | H4: DOCENCIA | I4: Edificio Ingeniería (ex TEC) | J4: 4408299870 | K4: =200000000+214576722+451540786+242312734+224174189+155623352+252294712+201102519+155455601+218152853+324983774+366374243+153086824+152511772+102298014+203742698+184685827+170139342 -> 3973055962 | L4: =J4-K4 -> 435243908 | N4: LSA INGENIERIA Y CONSTRUCCIÓN E.I.R.L. | O4: J.Solis de Ovando | P4: =J4-K4-(SUM(Q4:BR4)) -> 0 | Y4: =185222684 -> 185222684 | AH4: 250021224
A5: 409-5243 INSTITUTO TECNOLOGICO | B5: EDIFICIO INGENIERÍA (EX TEC) + HABILITACIÓN | C5: 2025 | D5: 9031 | E5: AUMENTO DE OBRA | F5: CRC Campus Doctor Luis Rivas Del Canto (vrae) | G5: CRC10 | H5: DOCENCIA | I5: AO N°1 Edificio Ingeniería (ex TEC) | J5: 456637235 | K5: =81204459+170270732+89858090+110752237 -> 452085518 | L5: =J5-K5 -> 4551717 | N5: LSA INGENIERIA Y CONSTRUCCIÓN E.I.R.L. | O5: J.Solis de Ovando | P5: =J5-K5-(SUM(Q5:BR5)) -> 0 | AI5: 4551717
A6: 409-5243 INSTITUTO TECNOLOGICO | B6: EDIFICIO INGENIERÍA (EX TEC) + HABILITACIÓN | C6: 2024 | D6: 4075 | E6: OTROS | F6: CRC Campus Doctor Luis Rivas Del Canto (vrae) | G6: CRC10 | H6: DOCENCIA | I6: Arquitectura Edificio Ingeniería (ex TEC) | J6: 86080359 | K6: =24432144+7173363+12912054+7173363 -> 51690924 | L6: =J6-K6 -> 34389435 | N6: SOCIEDAD DE PROFESIONALES BAIXAS Y DEL RIO ARQUITECTOS LIMITADA | O6: J.Solis de Ovando | P6: =J6-K6-(SUM(Q6:BR6)) -> 14304018 | AF6: 7173363 | AK6: 8608036.1 | AO6: 4304018
C7: 2023 | D7: 12187 | I7: Estudio Túnel | J7: 81691879 | K7: =12253782+12953656+8217395+4686425 -> 38111258 | L7: =J7-K7 -> 43580621 | N7: SUBTERRA INGENIERIA LIMITADA | O7: F.Anselme
C8: 2024 | D8: 8440 | I8: Revisores CES Pabelón y Hospital | J8: 4219946 | K8: 2260686 | L8: =J8-K8 -> 1959260 | N8: 88 ARQUITECTOS LIMITADA | O8: C.Correa
C9: 2023 | D9: 1754 | I9: Asesoria CES Hospital | J9: 17147240 | K9: =5621069+2953620+7426964 -> 16001653 | L9: =J9-K9 -> 1145587 | N9: 88 ARQUITECTOS LIMITADA | O9: C.Correa
C10: 2023 | D10: 1155 | I10: Asesoria CES Pabellon | J10: 9073025 | K10: =2721907+5443815 -> 8165722 | L10: =J10-K10 -> 907303 | N10: 88 ARQUITECTOS LIMITADA | O10: C.Correa
C11: 2025 | D11: 3946 | G11: CCC | I11: Cabañas Curacautín | J11: 316857372 | K11: =95057212+27725020+27725020+75253626+75253626 -> 301014504 | L11: =J11-K11 -> 15842868 | N11: CONSTRUCTORA RUKATAMI | O11: D.Silva | P11: =J11-K11-(SUM(Q11:BR11)) -> -0.6 | AF11: 15842869
C12: 2025 | D12: 7844 | I12: Regularización PE cjp07/cjp10/cjp104 | J12: 10833477 | K12: 2540943 | L12: =J12-K12 -> 8292534 | O12: C.Correa | P12: =J12-K12-(SUM(Q12:BR12)) -> 0 | AK12: 4146267 | AT12: 4146267
C13: 2025 | D13: 10964 | I13: Mobiliario Biblioteca CSF02 etapa 2 y 3 | J13: 67524777 | K13: 20257433 | L13: =J13-K13 -> 47267344 | N13: MELMAN SPA | O13: L. Rios | P13: =J13-K13-(SUM(Q13:BR13)) -> 0.1 | AE13: 47267344
C14: 2025 | D14: 11875 | I14: Remodelación Dirección General Estudiantil CSF | J14: 24367129 | K14: =7310138+7421966 -> 14732104 | L14: =J14-K14 -> 9635025 | N14: CONSTRUCTORA INGETRAPP | O14: J.Solis de Ovando | P14: =J14-K14-(SUM(Q14:BR14)) -> 0 | T14: 9635025
A15: 409-5243 INSTITUTO TECNOLOGICO | C15: 2025 | D15: 13112 | I15: Armado muebles Edificio de Ingenieria UCT (exTEC) | J15: 13917050 | K15: 5566820 | L15: =J15-K15 -> 8350230 | N15: ESPACIO MUEBLES LIMITADA | O15: J.Solis de Ovando | P15: =J15-K15-(SUM(Q15:BR15)) -> 0 | T15: =2783410+2783410 -> 5566820 | AI15: 2783410
A16: 409-5243 INSTITUTO TECNOLOGICO | C16: 2025 | D16: 13810 | I16: ccess point y switch Edificio de Ingenieria UCT (exTEC) | J16: 85398978 | L16: =J16-K16 -> 85398978 | O16: M.Zurita | Z16: 85398978
C17: 2025 | D17: 13310 | I17: Cortinas Cabañas Curacautín | J17: 4760000 | K17: =4760000*0.3 -> 1428000 | L17: =J17-K17 -> 3332000 | O17: F.Anselme | P17: =J17-K17-(SUM(Q17:BR17)) -> 0 | T17: 3332000
C18: 2025 | D18: 10880 | I18: Calculo Casino CRC | J18: 2808400 | L18: =J18-K18 -> 2808400 | O18: J.Solis de Ovando | P18: =J18-K18-(SUM(Q18:BR18)) -> 0 | Z18: 2808400
C19: 2025 | D19: 10877 | I19: Proyecto sanitario, pavimentación y topografía casino | J19: 2380000 | L19: =J19-K19 -> 2380000 | O19: J.Solis de Ovando | P19: =J19-K19-(SUM(Q19:BR19)) -> 0 | Z19: 2380000
C20: 2025 | D20: 12560 | I20: Diseño proyecto sanitario edificio Pabellón Docente | J20: 1880200 | L20: =J20-K20 -> 1880200 | O20: C.Correa | P20: =J20-K20-(SUM(Q20:BR20)) -> 0 | AG20: 1880200
C21: 2025 | D21: 5283 | I21: COMPRAS DE ACCESOS POINT, INSTALACION DISPOSITIVOS WIFI, OBRA MENORES SALA DOCTORADO HATCHERY CJP04, MENCHACA LIRA CML01 Y CONSTRUCCION POSTERIOR EDIFICIO A CSF16 | J21: 2519730 | L21: =J21-K21 -> 2519730 | O21: M.Zurita | P21: =J21-K21-(SUM(Q21:BR21)) -> 2519730
C22: 2024 | D22: 7981 | I22: SERVICIO EVALUACION CERTIFICACION EDIFICIO SUSTENTABLE, HOSPITAL SIMULACION Y PABELLON DOCENTE | J22: 4219946 | K22: 2260686 | L22: =J22-K22 -> 1959260 | N22: B-Green | O22: C.Correa | P22: =J22-K22-(SUM(Q22:BR22)) -> 0 | AK22: 1959260

Sheet Casino CRC
H1: PROGRAMACION FINANCIERA CRC11
B2: 2025 | C2: 2026 | H2: OC 1426/2026 | K2: actualizado 29/04
A3: TOTAL | B3: =B5+B14+B25+B47+B56+B63 -> 0 | C3: =C5+C14+C25+C47+C56+C63 -> 910200912 | I3: PROYECTADO | L3: REAL
H4: MES | I4: %PARCIAL | J4: %ACUMULADO | K4: EP PARCIAL | L4: EP REAL | M4: EP ACUMULADO | N4: %PARCIAL | O4: %ACUMULADO
B5: =SUM(B7:B12) -> 0 | C5: =SUM(C7:C12) -> 905200912 | G5: EP 1 | H5: MARZO | I5: 0.17 | J5: 0.18 | K5: 144479558 | L5: 144479558 | M5: =L5 -> 144479558 | N5: =L5/$K$13 -> 0.16894224 | O5: =N5 -> 0.16894224
A6: Obras | B6: 2025 | C6: 2026 | D6: 2027 | G6: EP 2 | H6: ABRIL | I6: 0.09 | J6: =J5+I6 -> 0.27 | K6: 69931126 | L6: 69931126 | M6: =L6+M5 -> 214410684 | N6: =L6/$K$13 -> 0.081771576 | O6: =N6+O5 -> 0.25071382
A7: Traslado de instalaciones | G7: EP 3 | H7: MAYO | I7: 0.21 | J7: =J6+I7 -> 0.48 | K7: 167082324 | L7: 163704571 | M7: =L7+M6 -> 378115255 | N7: =L7/$K$13 -> 0.19142235 | O7: =N7+O6 -> 0.44213617
A8: Demolición/certificados | G8: EP 4 | H8: JUNIO | I8: 0.19 | J8: =J7+I8 -> 0.67 | K8: 155127189 | L8: 105947180 | M8: =L8+M7 -> 484062435 | N8: =L8/$K$13 -> 0.12388572 | O8: =N8+O7 -> 0.56602189
A9: Construcción | C9: =K13 -> 855200912 | G9: EP 5 | H9: JULIO | I9: 0.22 | J9: =J8+I9 -> 0.89 | K9: 178457507 | L9: 108851059 | M9: =L9+M8 -> 592913494 | N9: =L9/$K$13 -> 0.12728127 | O9: =N9+O8 -> 0.69330316
A10: AO | C10: 50000000 | G10: EP 6 | H10: AGOSTO | I10: 0.12 | J10: =J9+I10 -> 1.01 | K10: 97363163 | M10: =L10+M9 -> 592913494 | N10: =L10/$K$13 -> 0 | O10: =N10+O9 -> 0.69330316
A11: Exteriores | D11: 100000000 | H11: TOTAL CON IVA | I11: =SUM(I5:I10) -> 1 | K11: =SUM(K5:K10) -> 812440867 | L11: =SUM(L5:L10) -> 592913494
A12: Otras | H12: RETENCION 5% | K12: =K13*0.05 -> 42760046 | L12: =K11-L11 -> 219527373
H13: TOTAL OBRA | K13: 855200912 | L13: =L12+L11 -> 812440867
B14: =SUM(B16:B23) -> 0 | C14: =SUM(C16:C23) -> 5000000 | M14: =M10+K12 -> 6.3567354e+08 | R14: actualizado 06/07
A15: Habilitación | B15: 2025 | C15: 2026
A16: Muebles
A17: Señalética | C17: 5000000
A18: Empavonados
A19: Pizarrones
A20: TV y/o Proyector | D20: 5000000
A21: Cortinas
A22: Access point y switch
A23: Otras
B25: =SUM(B27:B45) -> 0 | C25: =SUM(C27:C45) -> 0
A26: Especialidades | B26: 2025 | C26: 2026
A27: Arquitectura
A28: Estructura
A29: Mec. Suelos
A30: Topografía
A31: Eléctrico
A32: Incendio
A33: CCTV
A34: Control de acceso
A35: Fibra Óptica
A36: Sanitario
A37: Clima
A38: Pavimentación y ALL
... A45: Otras
B47: =SUM(B49:B54) -> 0 | C47: =SUM(C49:C54) -> 0
A48: Permiso | B48: 2025 | C48: 2026
A49: PE
A50: Derechos Municipales
A51: Rev. Arquitectura
A52: Rev. Estructura
A53: Modificación de proyecto
A54: Otras
B56: =SUM(B58:B61) -> 0 | C56: =SUM(C58:C61) -> 0
A57: Recepción | B57: 2025 | C57: 2026
A58: Rev. Recepción
A59: Aporte al espacio público
A60: Dotación de servicios
A61: Otras
B63: =SUM(B65:B67) -> 0 | C63: =SUM(C65:C67) -> 0
A64: Varios | B64: 2025 | C64: 2026
A65: Gastos
A66: Letrero de obra
A67: Otras

Sheet Ingeniería
B2: 2022 | C2: 2023 | D2: 2024 | E2: 2025 | F2: 2026
A3: TOTAL | B3: =B5+B14+B25+B47+B56+B63 -> 1387792 | C3: =C5+C14+C25+C47+C56+C63 -> 73805375 | D3: =D5+D14+D25+D47+D56+D63 -> 1607650599 | E3: =E5+E14+E25+E47+E56+E63 -> 2991895909 | F3: =F5+F14+F25+F47+F56+F63 -> 1561941445 | H3: OC 8022/2024
H4: EP N° | I4: FECHA | J4: PROYECTADO | N4: REAL | O4: OBSERVACION
B5: =SUM(B7:B12) -> 0 | C5: =SUM(C7:C12) -> 44730910 | D5: =SUM(D7:D12) -> 1341967351 | E5: =SUM(E7:E12) -> 2922398707 | F5: =SUM(F7:F12) -> 1281182758 | J5: PARCIAL ($) | K5: ACUMULADO ($) | L5: PARCIAL (%) | M5: ACUMULADO (%)
A6: Obras | B6: 2022 | C6: 2023 | D6: 2024 | E6: 2025 | F6: 2026 | H6: 0 | I6: 45893 | J6: 200000000 | K6: =J6 -> 200000000 | L6: =J6/$J$26 -> 0.045368964 | M6: =K6/$J$26 -> 0.045368964 | N6: 200000000 | O6: Anticipo
A7: Traslado de instalaciones | H7: 1 | I7: 45893 | J7: 214576722 | K7: =J7+K6 -> 414576722 | L7: =J7/$J$26 -> 0.048675618 | M7: =K7/$J$26 -> 0.094044583 | N7: 214576722 | O7: PAGADO
A8: Demolición/certificados | C8: 41531000 | D8: =535500+8827420 -> 9362920 | H8: 2 | I8: 45924 | J8: 451540786 | K8: =J8+K7 -> 866117508 | L8: =J8/$J$26 -> 0.10242969 | M8: =K8/$J$26 -> 0.19647427 | N8: 451540786 | O8: PAGADO
A9: Construcción | D9: 1332604431 | E9: 2470313188 | F9: =J23+J24+J25 -> 574491551 | H9: 3 | I9: 45954 | J9: 242312734 | K9: =J9+K8 -> 1108430242 | L9: =J9/$J$26 -> 0.054967389 | M9: =K9/$J$26 -> 0.25144166 | N9: 242312734 | O9: PAGADO
A10: AO | E10: =J36 -> 452085519 | F10: =J46 -> 646691207 | H10: 4 | I10: 45985 | J10: 224174189 | K10: =J10+K9 -> 1332604431 | L10: =J10/$J$26 -> 0.050852754 | M10: =K10/$J$26 -> 0.30229442 | N10: 224174189 | O10: PAGADO 2024
A11: Exteriores | H11: 5 | I11: 46015 | J11: 155623352 | K11: =J11+K10 -> 1488227783 | L11: =J11/$J$26 -> 0.035302352 | M11: =K11/$J$26 -> 0.33759677 | N11: 155623352 | O11: PAGADO
A12: Otras | C12: 3199910 | F12: 60000000 | H12: 6 | I12: 45682 | J12: 252294712 | K12: =J12+K11 -> 1740522495 | L12: =J12/$J$26 -> 0.057231749 | M12: =K12/$J$26 -> 0.39482852 | N12: 252294712 | O12: PAGADO
H13: 7 | I13: 45719 | J13: 201102519 | K13: =J13+K12 -> 1941625014 | L13: =J13/$J$26 -> 0.045619065 | M13: =K13/$J$26 -> 0.44044758 | N13: 201102519 | O13: PAGADO
B14: =SUM(B16:B23) -> 0 | C14: =SUM(C16:C23) -> 0 | D14: =SUM(D16:D23) -> 98018000 | E14: =SUM(E16:E23) -> 0 | F14: =SUM(F16:F23) -> 175000000 | H14: 8 | I14: 45748 | J14: 155455601 | K14: =J14+K13 -> 2097080615 | L14: =J14/$J$26 -> 0.035264298 | M14: =K14/$J$26 -> 0.47571188 | N14: 155455601 | O14: PAGADO
A15: Habilitación | B15: 2022 | C15: 2023 | D15: 2024 | E15: 2025 | F15: 2026 | H15: 9 | I15: 45802 | J15: 218152853 | K15: =J15+K14 -> 2315233468 | L15: =J15/$J$26 -> 0.049486845 | M15: =K15/$J$26 -> 0.52519872 | N15: 218152853 | O15: PAGADO
A16: Muebles | D16: 98018000 | F16: 50000000 | H16: 10 | I16: 45833 | J16: 324983774 | K16: =J16+K15 -> 2640217242 | L16: =J16/$J$26 -> 0.073720886 | M16: =K16/$J$26 -> 0.59891961 | N16: 324983774 | O16: PAGADO
A17: Señalética | F17: 15000000 | H17: 11 | I17: 45863 | J17: 366374243 | K17: =J17+K16 -> 3006591485 | L17: =J17/$J$26 -> 0.0831101 | M17: =K17/$J$26 -> 0.68202971 | N17: 366374243 | O17: PAGADO
A18: Empavonados | F18: 5000000 | H18: 12 | I18: 45894 | J18: 153086824 | K18: =J18+K17 -> 3159678309 | L18: =J18/$J$26 -> 0.034726953 | M18: =K18/$J$26 -> 0.71675666 | N18: 153086824 | O18: PAGADO
A19: Pizarrones | H19: 13 | I19: 45925 | J19: 152511772 | K19: =J19+K18 -> 3312190081 | L19: =J19/$J$26 -> 0.034596506 | M19: =K19/$J$26 -> 0.75135317 | N19: 152511772 | O19: PAGADO
A20: TV y/o Proyector | F20: 20000000 | H20: 14 | I20: 45955 | J20: 102298015 | K20: =J20+K19 -> 3414488096 | L20: =J20/$J$26 -> 0.023205775 | M20: =K20/$J$26 -> 0.77455895 | N20: 102298014 | O20: PAGADO
A21: Cortinas | F21: 15000000 | H21: 15 | I21: 45986 | J21: 205559061 | K21: =J21+K20 -> 3620047157 | L21: =J21/$J$26 -> 0.046630009 | M21: =K21/$J$26 -> 0.82118895 | N21: 203742698 | O21: PAGADO
A22: Access point y switch | H22: 16 | I22: 46016 | J22: 213761161 | K22: =J22+K21 -> 3833808318 | L22: =J22/$J$26 -> 0.048490613 | M22: =K22/$J$26 -> 0.86967957 | N22: 184685827 | O22: PAGADO 2025
A23: Otras | F23: 70000000 | H23: 17 | I23: 45683 | J23: 217950593 | K23: =J23+K22 -> 4051758911 | L23: =J23/$J$26 -> 0.049440964 | M23: =K23/$J$26 -> 0.91912053 | N23: 170139342 | O23: PAGADO
H24: 18 | I24: 45683 | J24: 136125965 | K24: =J24+K23 -> 4187884876 | L24: =J24/$J$26 -> 0.03087947 | M24: =K24/$J$26 -> 0.95 | N24: 214827912 | O24: PAGADO
B25: =SUM(B27:B45) -> 0 | C25: =SUM(C27:C45) -> 26864475 | D25: =SUM(D27:D45) -> 136151095 | E25: =SUM(E27:E45) -> 0 | F25: =SUM(F27:F45) -> 85758687 | H25: 19 | I25: 45748 | J25: 220414993 | K25: =J25+K24 -> 4408299869 | L25: =J25/$J$26 -> 0.05 | M25: =K25/$J$26 -> 1 | N25: 220415164 | O25: Devolucion retenciones abril
A26: Especialidades | B26: 2022 | C26: 2023 | D26: 2024 | E26: 2025 | F26: 2026 | H26: TOTALES | J26: =SUM(J6:J25) -> 4408299869 | L26: =SUM(L6:L25) -> 1 | N26: =SUM(N6:N25) -> 4408299038 | O26: =N26/J26 -> 0.99999981
A27: Arquitectura | D27: =10000000+86080359 -> 96080359
A28: Estructura | C28: =20425698+2121030 -> 22546728 | D28: 2121030
A29: Mec. Suelos | C29: 3717747 | H29: OC 9031/2025
A30: Topografía | C30: 600000 | H30: EP N° | I30: FECHA | J30: PROYECTADO | N30: REAL | O30: OBSERVACION
A31: Eléctrico | D31: 9472400 | J31: PARCIAL ($) | K31: ACUMULADO ($) | L31: PARCIAL (%) | M31: ACUMULADO (%)
A32: Incendio | H32: 1 | I32: 45955 | J32: 170270733 | K32: =J32 -> 170270733 | L32: =J32/$J$36 -> 0.3766339 | M32: 0.38 | N32: 170270732 | O32: PAGADO
A33: CCTV | F33: 22000000 | H33: 2 | I33: 45986 | J33: 81204459 | K33: =J33+K32 -> 251475192 | L33: =J33/$J$36 -> 0.1796219 | M33: 0.56 | N33: 81204459 | O33: PAGADO
A34: Control de acceso | F34: 15000000 | H34: 3 | I34: 46016 | J34: 89981262 | K34: =J34+K33 -> 341456454 | L34: =J34/$J$36 -> 0.19903593 | M34: 0.76 | N34: 89858090 | O34: PAGADO
A35: Fibra Óptica | F35: 3000000 | H35: 4 | I35: 45719 | J35: 110629065 | K35: =J35+K34 -> 452085519 | L35: =J35/$J$36 -> 0.24470827 | M35: 1 | N35: 110752237 | O35: PAGADO
A36: Sanitario | D36: 4300000 | H36: TOTALES | J36: 452085519 | L36: =SUM(L32:L35) -> 1 | N36: =SUM(N32:N35) -> 452085518 | O36: =N36/J36 -> 1
A37: Clima | D37: =7761132+2442981 -> 10204113
A38: Pavimentación y ALL
A39: Gas | H39: OC 66-2026
A40: Ascensor | H40: EP N° | I40: FECHA | J40: PROYECTADO | N40: REAL | O40: OBSERVACION
A41: CES | J41: PARCIAL ($) | K41: ACUMULADO ($) | L41: PARCIAL (%) | M41: ACUMULADO (%)
A42: IMIV / obras mitigación | D42: 3758687 | F42: =D42 -> 3758687 | H42: 1 | I42: 45986 | J42: 102074177 | K42: =J42 -> 102074177 | L42: =J42/$J$46 -> 0.15784068
A43: Coordinación BIM | D43: 10214506 | H43: 2 | I43: 46016 | J43: 101461706 | K43: =J43+K42 -> 203535883 | L43: =J43/$J$46 -> 0.15689359 | N43: 209275007
A44: Paisajismo / ejecución | F44: 10000000 | H44: 3 | I44: 45683 | J44: =131640070+24803417 -> 156443487 | K44: =J44+K43 -> 359979370 | L44: =J44/$J$46 -> 0.24191374 | M44: =N44/J46 -> 0.67639114 | N44: 437416202
A45: Otras | F45: 32000000 | H45: 4 | I45: 45748 | J45: 286711837 | K45: =J45+K44 -> 646691207 | L45: =J45/$J$46 -> 0.443352 | M45: 1
H46: TOTALES | J46: =SUM(J42:J45) -> 646691207 | L46: =SUM(L42:L45) -> 1 | N46: =SUM(N42:N45) -> 646691209 | O46: =N46/J46 -> 1
B47: =SUM(B49:B54) -> 0 | C47: =SUM(C49:C54) -> 0 | D47: =SUM(D49:D54) -> 4233634 | E47: =SUM(E49:E54) -> 41859834 | F47: =SUM(F49:F54) -> 0 | N47: =J46-N46 -> -2
A48: Permiso | B48: 2022 | C48: 2023 | D48: 2024 | E48: 2025 | F48: 2026 | M48: Saldo | N48: 17999999
A49: PE | G49: 9712183
A50: Derechos Municipales
A51: Rev. Arquitectura | D51: 4233634 | E51: 4199354
A52: Rev. Estructura | E52: 2045561
A53: Modificación de proyecto
A54: Otras | E54: 35614919 | R54: EP N° | S54: Factura | T54: Fecha | U54: Parcial | V54: Saldo
L55: 450000000
B56: =SUM(B58:B61) -> 0 | C56: =SUM(C58:C61) -> 0 | D56: =SUM(D58:D61) -> 0 | E56: =SUM(E58:E61) -> 0 | F56: =SUM(F58:F61) -> 0 | L56: =L55-J25 -> 229585007 | R56: 1 | S56: 10 | T56: 45271 | U56: 10000000 | W56: ante
A57: Recepción | B57: 2022 | C57: 2023 | D57: 2024 | E57: 2025 | F57: 2026
A58: Rev. Recepción | Q58: 86080359 | R58: 2 | S58: 15 | T58: 45422 | U58: 24432144 | V58: =U58 -> 24432144 | W58: ante y proy
A59: Aporte al espacio público | J59: Arquitecto | R59: 3 | S59: 22 | T59: 45678 | U59: 7173363 | V59: =U59+V58 -> 31605507 | W59: 1/3 sup.
A60: Dotación de servicios | J60: PE | K60: 10000000 | L60: 46143 | M60: OK | R60: 4 | S60: 26 | T60: 45829 | U60: 12912054 | V60: =U60+V59 -> 44517561 | W60: 1/2 PE
A61: Otras | J61: retenciones | K61: =J25 -> 220414993 | R61: 5 | S61: 28 | T61: 45905 | U61: 7173363 | V61: =U61+V60 -> 51690924 | W61: 2/3 sup.
J62: adicional 3 | K62: 110000000 | L62: 46174 | M62: ?¡ | R62: 6 | U62: 7173363 | V62: =U62+V61 -> 58864287 | W62: 3/3 sup.
B63: =SUM(B65:B67) -> 1387792 | C63: =SUM(C65:C67) -> 2209990 | D63: =SUM(D65:D67) -> 27280519 | E63: =SUM(E65:E67) -> 27637368 | F63: =SUM(F65:F67) -> 20000000 | R63: 7
A64: Varios | B64: 2022 | C64: 2023 | D64: 2024 | E64: 2025 | F64: 2026 | J64: imiv | K64: 30000000 | L64: 1 juni
A65: Gastos | B65: =1306667+71475+9650 -> 1387792 | C65: =2209990 -> 2209990 | D65: =24644260+1232059 -> 25876319 | J65: grupo elec | K65: 15170428 | L65: 46143 | M65: Arturo
A66: Letrero de obra | D66: =749700+654500 -> 1404200 | J66: bodega respel | K66: 1200000 | L66: 1 juni | S66: Pagado | T66: saldo
A67: Otras | E67: 27637368 | F67: =20000000 -> 20000000 | J67: muebles profes | K67: 2000000 | L67: 46143 | Q67: =Q58 -> 86080359 | W67: =Q58-V62 -> 27216072
J68: solicitrud muebles | K68: 5500000
J69: Señaletica | K69: 12000000 | L69: 46143 | P69: 0.15 | Q69: Ante | R69: =$Q$67*P69 -> 12912054 | S69: =R69 -> 12912054 | T69: =R69-S69 -> 0
J70: Rev. Arquitectura | K70: 4000000 | L70: 46237 | P70: 0.25 | Q70: proy | R70: =$Q$67*P70 -> 21520090 | S70: =R70 -> 21520090 | T70: =R70-S70 -> 0
P71: 0.25 | Q71: PE | R71: =$Q$67*P71 -> 21520090 | S71: =U60 -> 12912054 | T71: =R71-S71 -> 8608035.8
P72: 0.25 | Q72: S. Obra | R72: =$Q$67*P72 -> 21520090 | S72: =U62+U61+U59 -> 21520089 | T72: =R72-S72 -> 0.75 | W72: =V62+U56 -> 68864287
P73: 0.1 | Q73: RM | R73: =P73*Q67 -> 8608035.9 | S73: 0 | T73: =R73-S73 -> 8608035.9 | U73: =T73/2 -> 4304018
K74: =SUM(K60:K67) -> 388785421 | P74: =SUM(P69:P73) -> 1 | R74: =SUM(R69:R73) -> 86080359 | S74: =SUM(S69:S73) -> 68864287 | T74: =SUM(T69:T73) -> 17216072
K75: =L55-K74 -> 61214579
C90: AFR pabellon | D90: 10000000
C91: mod sangre | D91: 5000000

Sheet Datos
B2: CAMPUS | C2: EDIFICIO | D2: USO | E2: ESTADO | F2: TIPO OBRA | G2: CC | H2: PROYECTO | I2: RESPONSABLE | J2: N° | K2: % | L2: Tipo | M2: Prioridad | N2: NOMBRE | O2: RUT | Q2: RAZON SOCIAL | R2: N° | S2: $ | T2: CORREO | U2: RECEPCION CONFORME | V2: OBSERVACIONES
A3: CML | B3: CML Campus Monseñor Alejandro Menchaca Lira | C3: CML01 | D3: DOCENCIA | E3: PROYECTO | F3: OBRA NUEVA | G3: 409-1722 REMODELACIONES-OBRAS | H3: EDIFICIO INGENIERÍA (EX TEC) + HABILITACIÓN | I3: D.Silva | L3: Normal | M3: 1 | N3: ALEJANDRO BARRIA | O3: 11662472 | P3: 9 | Q3: ALEJANDRO ALVARO BARRIA MATELUNA | T3: abarriam@gmail.com | U3: SI
A4: CDS | B4: CDS Campus Dieciocho de Septiembre | C4: CML02 | D4: INVESTIGACION | E4: COTIZACION | F4: AUMENTO DE OBRA | G4: 409-5243 INSTITUTO TECNOLOGICO | H4: PERMISO + CONSTRUCCION CASINO CRC11 (VRAE) | I4: M.Zurita | L4: Prioridad Obra | M4: 2 | N4: Abastec spa | O4: 76814443 | P4: 5 | Q4: COMERCIALIZADORA ABASTEC SPA | T4: abastecspa@gmail.com | U4: NO | V4: PRODUCTOS
A5: CPH | B5: CPH Campus Phillippi | C5: CML03 | D5: ESPACIOS COMUNES | E5: EN EJECUCION | F5: AMPLIACION | G5: 409-5503 PROYECTO TÚNEL SALIDA Y CALLE PROLONGACIÓN CJPII | H5: CASINO CRC11 (VRAE) HABILITACIÓN | I5: F.Anselme | M5: 3 | N5: Amaris Constructora SpA | O5: 77648798 | P5: 8 | Q5: AMARIS CONSTRUCTORA | T5: administracion@amaris.cl | U5: SI
A6: CSC | B6: CSC Campus Monseñor Sergio Contreras Navia | C6: CML04 | D6: ADMINISTRACION | E6: TERMINADO | F6: REMODELACION | G6: 409-5506 - CASINO VRAE | H6: OBRAS DE SEGURIDAD, PAISAJISMO CURACAUTIN | I6: C.Correa | N6: Terra riegos | O6: 77094631 | P6: k | Q6: TERRA RIEGOS SPA | T6: administracion@terrariegos.cl | U6: SI
A7: CTH | B7: CTH Campus Thiers | C7: CML05 | D7: OTROS | E7: POSTERGADO | F7: AREAS VERDES | G7: 409-6293 - CENTRO RECREACIONAL SAN NICOLAS | H7: PAISAJISMO ESPACIO TRAS CRC18 (ÁREA VERDE) | I7: M.Matus | N7: Traiguen Energy S.A | O7: 76403114 | P7: 8 | Q7: TRAIGUEN ENERGY | T7: administracion@traiguenergy.com | U7: NO | V7: PRODUCTOS
A8: CBQ | B8: CBQ Campus El Bosque | C8: CDS01 | E8: ELIMINADO | F8: ALHAJAMIENTO | H8: MEJORAMIENTO DE ALMACENAMIENTO Y SUMINISTRO DE AGUA POTABLE CRC | I8: J.Solis de Ovando | N8: INSUR INGENIERIA SPA | O8: 77667513 | P8: K | Q8: INSUR INGENIERIA SPA | T8: adquisiciones@insuringenieria.cl | U8: SI
A9: CSF | B9: CSF Campus San Francisco | C9: CDS101 | E9: AJUNSTADO | F9: REGULARIZACION | H9: ESTUDIO REPARACIÓN ESTRUCTURA DE CUBIERTA EDIFICIO CJP08 | I9: L. Rios | N9: Luis Eduardo Castro Sanhueza | O9: 9346688 | P9: 8 | Q9: LUIS EDUARDO CASTRO SANHUEZA | T9: agroriegocastro@gmail.com | U9: SI
A10: CHS | B10: CHS Campus Prieto Norte | C10: CPH01 | E10: EN CARPETA | F10: COMPRA ELEMENTOS | H10: REGULARIZACION CJP07, CJP10, CJP104 ESPECIALIDADES Y PAGOS | I10: C. Huenchual | N10: ALBAYRAK | O10: 76908161 | P10: 5 | Q10: ALBAYRAK SPA | T10: albayrak.spa@gmail.com | U10: SI
A11: CEC | B11: CEC Campus Educacion Continua | C11: CPH02 | F11: DEMOLICION | H11: REGULARIZACION CJP07, CJP10, CJP104 OBRAS | I11: O. Painen | N11: AmbiQuim | O11: 76956078 | P11: 5 | Q11: AMBIQUIM SPA | T11: ambiquim@vtr.net | U11: SI
A12: CJP | B12: CJP Campus San Juan Pablo II | C12: CPH03 | F12: INSTALACIONES | H12: CALEFACCIÓN SALA NUEVA OFICIOS CREATIVOS | I12: I. Cisternas | N12: BYM Logistics SPA | O12: 77223324 | P12: 8 | Q12: BYM LOGISTICS SPA | T12: ana.lizama@bmlog.cl | U12: NO | V12: TRANSPORTE
A13: CRC | B13: CRC Campus Doctor Luis Rivas Del Canto (vet) | C13: CPH101 | F13: OTROS | H13: RECAMBIO DE CÁMARA DE FRIO PARA CASINO CJP | I13: A. Meza | N13: Comercial flores ltda | O13: 76307697 | P13: 0 | Q13: COMERCIAL FLORES LIMITADA | T13: arnold.steelltda@gmail.com | U13: SI
A14: CRC | B14: CRC Campus Doctor Luis Rivas Del Canto (vrae) | C14: CSC01 | H14: REMODELACION LAB. SUELOS , CONSTRUCCION DE OFICINAS CPH02 (PHILLIPPI) | N14: ACA Spa | O14: 77950451 | P14: 4 | Q14: ASESORÍAS CID ARRIAGADA SPA | T14: asesoriascidarriagadaspa@gmail.com | U14: SI
A15: CPL | B15: CPL Campus Pillanlelbun | C15: CSC02 | H15: BIBICLETERO CRC (VRAE) | N15: Asistec | O15: 77192604 | P15: 5 | Q15: ASISTEC ARAUCANIA SPA | T15: asistec.estufas@gmail.com | U15: SI
A16: CCC | B16: CCC Campus Curacautin | C16: CSC03 | H16: CRC05 MEJORAS HABITABILIDAD INTERIOR | N16: SOCIEDAD DE PROFESIONALES BAIXAS Y DEL RIO ARQUITECTOS LIMITADA | O16: 77712479 | P16: k | Q16: SOCIEDAD DE PROFESIONALES BAIXAS Y DEL RIO ARQUITECTOS LIMITADA | T16: baixasdelrio@vtr.net | U16: NO | V16: ASESORIA
A17: CSD | B17: CSD Campus Santiago Departamento | C17: CTH01 | H17: BANCAS Y BASUREROS | N17: Botes temuco chile | O17: 77242835 | P17: 9 | Q17: COMERCIAL BOTES TEMUCO CHILE SPA | T17: botestemucochile@gmail.com | U17: NO | V17: PRODUCTO
A18: CLE | B18: CLE Nuestra Señora de Lourdes | C18: CBQ01 | H18: MANTENCIÓN ESTRUCTURA MADERA LAMINADA PILARES Y VIGAS CSF14 - CSF16 | N18: Edipac | O18: 88566900 | P18: K | Q18: EDIPAC | T18: cajatemuco@edipac.cmpc.cl | U18: SI
A19: TODOS | C19: CBQ02 | H19: ADECUACIONES POR TRASLADOS CSF16 y CSF12 | N19: GILDA DE LOURDES MACHMAR MARTINEZ | O19: 8202873 | P19: 0 | Q19: PAQUETERIA GILDA | T19: carlosrpalaciosm@hotmail.com | U19: SI
C20: CBQ03 | H20: BIBLIOTECA CSF02 ETAPA 2 Y 3, ELECTRICO | N20: Carolin Klahn Paisajista | O20: 77976076 | P20: 6 | Q20: AREA VERDE LTDA | T20: carolinklahn@gmail.com | U20: NO | V20: SOCIEDAD COMERCIAL AREA VERDE LIMITADA
C21: CBQ04 | H21: SEÑALETICA OFICINAS TERMINO EN CJP, CSF Y CRC | N21: CHC | O21: 79903920 | P21: 6 | Q21: CHC | T21: cbello@chc.cl; shenriquez@chc.cl | U21: NO | V21: PRODUCTOS
C22: CBQ05 | H22: NORMALIZACIÓN SALA DE BASURA CSF Y CJP | N22: CONSTRUCTORA IGECE LTDA | O22: 76878824 | P22: 3 | Q22: CONSTRUCTORA IGECE LIMITADA | T22: cecilia.ulloa04@gmail.com | U22: SI
C23: CBQ06 | H23: REGULARIZACION EDIFICIOS | N23: MUEBLES ADECOR Temuco | O23: 13115771 | P23: 1 | Q23: CLAUDIO ELIAS AROSTICA ORMENO | T23: chileadecor@gmail.com | U23: SI
C24: NSL | H24: AUTOMATIZACION | N24: CORTINAJES CLAUDIO AGUILERA | O24: 11453172 | P24: 3 | Q24: CORTINAJES CLAUDIO AGUILERA | T24: claudioeduardoaguilera@hotmail.com | U24: SI
C25: CSF01 | H25: MEJORAS ESPACIOS INTERNAS CSF10 (CREDITO) | N25: Claudio triña, telecomunicaciones y obras menores e.i.r.l | O25: 77520606 | P25: 3 | Q25: CLAUDIO TRINA GARRIDO E.I.R.L. | T25: claudiotrina08@gmail.com | U25: SI
C26: CSF02 | H26: IMPREVISTOS | N26: Avantec | O26: 78209000 | P26: 3 | Q26: AVANTEC | T26: clopez@avantec.cl | U26: SI
C27: CSF03 | N27: ARF Consultores | O27: 76969759 | P27: 4 | Q27: ARF CONSULTORES LTDA. | T27: cmascui@arfarquitectura.cl | U27: SI
C28: CSF04 | N28: Schindler | O28: 93565000 | P28: 3 | Q28: ASCENSORES SCHINDLER (CHILE) | T28: cobranza.cl@schindler.com | U28: SI
C29: CSF05 | N29: Materiales y servicios mar de cantabria spa | O29: 77305657 | P29: 9 | Q29: MATERIALES Y SERVICIOS MAR DE CANTABRIA SPA | T29: colipe.gustavo@gmail.com | U29: SI
C30: CSF06 | H30: PINTURA Y CAMBIO DE ELEMENTOS DAÑADO EDIFICIO CRC17 Y CRC18 | N30: Constructora VITRO SPA | O30: 77631876 | Q30: CONSTRUCTORA VITRO SPA | T30: constructora.vitro@gmail.com | U30: SI
C31: CSF07 | N31: Invercon jbg | O31: 77119724 | P31: 8 | Q31: INVERCON JBG SPA | T31: constructorajbg@gmail.com | U31: SI
C32: CSF08 | N32: Rukatami | O32: 76514788 | P32: 3 | Q32: CONSTRUCTORA RUKATAMI | T32: CONSTRUCTORARUKATAMI@GMAIL.COM | U32: SI
C33: CSF09 | N33: TERRASUR | O33: 77780490 | P33: 1 | Q33: CONSTRUCTORA TERRASUR LIMITADA | T33: constructoraterrasur@gmail.com | U33: SI
C34: CSF10 | N34: ESPACIO MUEBLES | O34: 77544225 | P34: 5 | Q34: ESPACIO MUEBLES LIMITADA | T34: contacto.espaciomuebles@gmail.com | U34: SI
C35: CSF11 | N35: LECAR SPA. | O35: 77393585 | P35: 8 | Q35: LECAR SPA | T35: contacto.lecar@gmail.com | U35: SI
C36: CSF12 | N36: CREASMILE | O36: 76308486 | P36: 8 | Q36: SERGIO MELO PUBLICIDAD E.I.R.L. | T36: contacto@creasmile.cl | U36: SI
C37: CSF13 | N37: Girafa lift | O37: 77648625 | P37: 6 | Q37: SOCIEDAD DE ARRENDAMIENTO DE MAQUINARIAS GIRAFA LIFT LIMITADA | T37: contacto@girafa.cl | U37: SI
C38: CSF14 | N38: GYG SPA | O38: 77215624 | P38: 3 | Q38: GYG SERVICIOS | T38: contacto@gygtecnologias.com | U38: SI
C39: CSF15 | N39: POCK | O39: 77641694 | P39: 0 | Q39: POCK SPA | T39: contacto@pock.cl | U39: SI
C40: CSF16 | N40: Steelpunk | O40: 76470291 | P40: 3 | Q40: STEELPUNK FITNESS OUTFITTERS | T40: contacto@steelpunk.cl | U40: NO | V40: PRODUCTOS
C41: CSF17 | N41: Quincalleria cowe | O41: 5720722 | P41: 1 | Q41: QUINCALLERIA COWE | T41: cowelimitada@gmail.com | U41: NO | V41: PRODUCTOS
C42: CSF18 | N42: Cristian Salamanca | O42: 13582386 | P42: 4 | Q42: CRISTIAN MARCELO SALAMANCA MEZA | T42: csalamancameza@gmail.com | U42: SI
C43: CSF21 | N43: COMERCIALIZADORA DANIELA ARRIAGADA CABA EIRL | O43: 76707485 | P43: 9 | Q43: COMERCIALIZADORA DANIELA PATRICIA ARRIAGADA CABA | T43: danielaarriagadacaba@hotmail.com | U43: SI
C44: CSF101 | N44: AGENCIA DSIETE LTDA | O44: 77964311 | P44: 5 | Q44: DSIETE SPA | T44: dsiete.design@gmail.com | U44: SI
C45: CSF102 | N45: RAMASOL | O45: 76579595 | P45: 8 | Q45: RAMASOL | T45: eoliva@ramasol.cl | U45: SI
C46: CSF103 | N46: 88 LIMITADA | O46: 76108094 | P46: 6 | Q46: 88 ARQUITECTOS LIMITADA | T46: ernestina@88limitada.cl | U46: SI
C47: CSF104 | N47: FEMA | O47: 77092438 | P47: 3 | Q47: FABRICA DE MUEBLES Y CONTRUCCIONES FEMA SPA | T47: femaproyectos@gmail.com | U47: SI
C48: CSF105 | N48: Quintana y Díaz Spa | O48: 76854883 | P48: 8 | Q48: VENTANAS H-D | T48: finanzas@ventanashd.cl | U48: SI
C49: CSF107 | N49: VIVA CONSTRUCCIONES SPA | O49: 76971865 | P49: 6 | Q49: VIVA CONSTRUCCIONES SPA | T49: finanzas@vivaconstrucciones.cl | U49: SI
C50: CSF108 | N50: Fmedios | O50: 8933359 | P50: 8 | Q50: FMEDIOS | T50: fjmc_1@hotmail.com | U50: SI
C51: CSF110 | N51: Riol moisés bascur jara | O51: 11811450 | P51: 7 | Q51: FOSAS GOGOL | T51: fosasgogol@hotmail.com | U51: SI
C52: CSF120 | N52: CONSTRUCTORA ROMO Y CADI LIMITADA | O52: 76107187 | P52: 4 | Q52: ROMO Y CADI LIMITADA | T52: fromoc@gmail.com | U52: SI
C53: CSF130 | N53: Electropower | O53: 76257832 | P53: 8 | Q53: ELECTROPOWER | T53: fsalvo@electropower.cl | U53: SI
... C58: CSF260 | N58: HOGUER | O58: 4305245 | P58: 4 | Q58: HOGUER | T58: hoguer1@gmail.com | U58: SI
C59: CHS01 | N59: Dartel | O59: 96806110 | P59: 0 | Q59: DARTEL | T59: hosses@dartel.cl | U59: NO | V59: PRODUCTOS
C60: CHS02 | N60: KÜME RUKA Spa. | O60: 77929977 | P60: 5 | Q60: KÜME RUKA SPA | T60: hzambranoleal@gmail.com | U60: SI
C61: CEC01 | N61: Comercial Canada Blinds y Cia Ltda. | O61: 76271694 | P61: 1 | Q61: CORTINAS MSTUARD | T61: ignacio@mstuard.cl; contactomstuard@gmail.com | U61: SI
C62: CEC02 | N62: Revolucion sport | O62: 77052801 | P62: 1 | Q62: REVOLUCION SPORT | T62: ignaciomaciasu@hotmail.com; revolucionsportscl@gmail.com | U62: NO | V62: PRODUCTOS
C63: CEC05 | N63: Biometrika | O63: 76102607 | P63: 0 | Q63: BCR TECNOLOGIA E INNOVAVION S.A. | T63: info@biometrika.cl | U63: SI
C64: CEC101 | N64: DUNATI SPA | O64: 76515462 | P64: 6 | Q64: DUNATI CHILE SPA | T64: info@dunati.com | U64: SI
C65: CEC120 | N65: Super limitada | O65: 77224100 | P65: 3 | Q65: EXTINTORES SUPER | T65: info@extintoressuper.cl; ventas@extintoressuper.cl | U65: SI
C66: CEC130 | N66: Pua | O66: 76962330 | P66: 2 | Q66: PUA DISEÑO | T66: info@pua.cl | U66: SI
C67: CEC140 | N67: Ingenieria MC | O67: 77761115 | P67: 1 | Q67: INGENIERIA MC SPA | T67: Ingenieriamcspa@gmail.com | U67: SI
C68: CEC150 | N68: Iprosam | O68: 76423859 | P68: 1 | Q68: IROSAM LTDA. | T68: IPROSAM.FSD@GMAIL.COM | U68: SI
C69: CJP01 | N69: Jose Llancanao | O69: 77651423 | P69: 3 | Q69: SERVICIOS INTEGRALES EN EL AREA DE CONSTRUCCION E INSTALACIONES ELECTR | T69: j.elect20@gmail.com | U69: SI
C70: CJP02 | N70: mK | O70: 77137860 | P70: 9 | Q70: MK | T70: j.nunez@mk.cl | U70: NO | V70: PRODUCTOS
C71: CJP03 | N71: Eduardo Zelaya | O71: 9947799 | P71: 2 | Q71: ERASMO EDUARDO ZELAYA LOPEZ | T71: jacqueline.rodriguez@hotmail.es | U71: SI
C72: CJP04 | N72: INDUMAC | O72: 83732700 | P72: 8 | Q72: INDUSTRIA METALURGICA ACONCAGUA LIMITADA | T72: jbecker@indumac.cl | U72: SI
C73: CJP05 | N73: FORESTAL JORGE ARTURO CATALAN SANCHEZ E.I.R.L | O73: 76343261 | P73: 0 | Q73: FORESTAL JORGE ARTURO CATALÁN SÁNCHEZ E.I.R.L. | T73: JCATALANSAN@GMAIL.COM | U73: SI
C74: CJP06 | N74: Corporativa Diseño | O74: 7739192 | P74: 4 | Q74: CORPORATIVA DISEÑO | T74: jcpradenas@gmail.com | U74: SI
C75: CJP07 | N75: SERVIGEN SERVICIOS LIMITADA | O75: 76405567 | P75: 5 | Q75: SERVIGEN | T75: jhidalgo@servigenchile.cl; rsantana@servigenchile.cl; lacuna@servigenchile.cl | U75: NO | V75: ASESORIA
C76: CJP08 | N76: OPCIONES | O76: 96523180 | P76: 3 | Q76: OPCIONES S.A. | T76: jmunoz@opciones.cl | U76: SI
C77: CJP09 | N77: CONSTRUCCIONES JOSE LIENQUE E.I.R.L | O77: 76992766 | P77: 2 | Q77: CONSTRUCCIONES JOSE LIENQUEO E.I.R.L. | T77: jose.lien.neico@gmail.com | U77: SI
C78: CJP10 | N78: ESPACIO CUBIERTO | O78: 76053604 | P78: 0 | Q78: ESPACIO CUBIERTO LIMITADA | T78: JPCSORI@ESPACIOCUBIERTO.COM | U78: SI
C79: CJP11 | N79: EASTON | O79: 76028554 | P79: 4 | Q79: EASTON SPA | T79: jvillarreal@easton.cl | U79: NO | V79: PRODUCTOS
C80: CJP12 | N80: CONSTRUCCIONES KORTANZ | O80: 76535548 | P80: 6 | Q80: CONSTRUCCIONES KORTANZ LIMITADA | T80: kortanz71@gmail.com | U80: SI
C81: CJP13 | N81: OhOffice ! | O81: 77570810 | P81: 7 | Q81: OHFFICE SPA | T81: loreto.contreras@ohffice.cl | U81: SI
C82: CJP14 | N82: Sumo Arquitectura y Diseño Limitada | O82: 77652190 | P82: 6 | Q82: SUMO | T82: lsmoro@sumo.cl | U82: NO | V82: ASESORIA
C83: CJP15 | N83: Ingenieria y construcciones Perinetti SPA | O83: 77489668 | P83: 6 | Q83: CONSTRUCTORA PERINETTI | T83: lu.periavi@gmail.com | U83: SI
C84: CJP16 | N84: CONSTRUCCIONES LUIS EXEQUIEL SOLIS CATALAN E.I.R.L. | O84: 77280635 | P84: 3 | Q84: CONSTRUCCIONES LUIS EXEQUIEL SOLIS CATALAN E.I.R.L. | T84: luis.exequielsolis@gmail.com | U84: SI
C85: CJP17 | N85: MR Electro Clima SPA | O85: 77773634 | P85: 5 | Q85: MR ELECTRO | T85: luismanriquez555@gmail.com | U85: SI
C86: CJP101 | N86: LSA | O86: 76219281 | P86: 0 | Q86: LSA INGENIERIA Y CONSTRUCCIÓN E.I.R.L. | T86: luissaez@lsaingenieria.cl | U86: SI
C87: CJP102 | N87: S2 lngenieria y Construcciones Ltda | O87: 76533924 | P87: 3 | Q87: S2 INGENIERIA Y CONSTRUCCIÓN LIMITADA | T87: luissaez@lsaingenieria.cl | U87: NO | V87: ASESORIA Y CONSULTORIA
C88: CJP103 | N88: Sg 2000 | O88: 78571480 | P88: 6 | Q88: SEMILLAS GENERACION 2000 S.A. | T88: mabello@sg-2000.com; temuco@sg-2000.com | U88: NO | V88: PRODUCTOS
C89: CJP104 | N89: Ecoumwelt | O89: 9087185 | P89: 4 | Q89: ECOUMWELT | T89: marcelojacobi@vtr.net | U89: SI
C90: CJP105 | N90: ELEKTRICA SPA | O90: 76884395 | P90: 3 | Q90: ELEKTRICA | T90: marcopaine@elektrica.cl; marcopaine@gmail.com | U90: SI
C91: CJP106 | N91: Soc, Constructora Las Raíces Ltda. | O91: 76942931 | P91: k | Q91: SOCIEDAD CONSTRUCTORA LAS RAICES LTDA. | T91: marioalejandrogm@gmail.com | U91: SI | AB91: %
C92: CJP107 | N92: Adco ltda. | O92: 76102612 | P92: 7 | Q92: COMERCIAL ADCO LIMITADA | T92: mbravo@adcoltda.cl | U92: NO | V92: PRODUCTOS | AA92: Acumulado | AB92: Acumulado
C93: CJP108 | N93: 360 GRADOS ING. | O93: 76395296 | P93: 7 | Q93: INGENIERIA Y CONSTRUCCIONES MARCELO SEBASTIAN CARO SOTO E.I.R.L. | T93: mcarolina@gmail.com | U93: SI
C94: CJP110 | N94: CONSTRUCTORA Y SERVICIOS S-TEC SPA | O94: 77781356 | P94: 0 | Q94: CONSTRUCTORA Y SERVICIOS S-TEC SPA | T94: miguelptorres@gmail.com | U94: SI
C95: CJP115 | N95: Innovaclima | O95: 76464159 | P95: 0 | Q95: INNOVACLIMA | T95: mquezaday@gmail.com | U95: SI
C96: CJP120 | N96: Nueve DiseÑO | O96: 76181133 | P96: 9 | Q96: NUEVE DISEÑO | T96: mubilla@gmail.com | U96: SI
C97: CJP130 | N97: Muebles MI CASA | O97: 3639408 | P97: 0 | Q97: MUEBLES MI CASA | T97: muebleriamicasa@gmail.com | U97: SI
C98: CJP135 | N98: MULTIMUEBLES | O98: 6189318 | P98: 0 | Q98: MULTIMUEBLES | T98: multimueblestemuco@gmail.com | U98: SI
C99: CJP140 | N99: Mundo sport | O99: 76458447 | P99: 3 | Q99: MUNDO SPORT TEMUCO | T99: mundo.gonzalez@hotmail.com | U99: SI
C100: CJP145 | N100: ZUBIMED | O100: 77103330 | P100: k | Q100: ZUBIMED | T100: mvega@zubimed.cl | U100: NO | V100: Retiro residuos Hospitalarios
C101: CJP150 | N101: ESTEC LTDA | O101: 79913160 | P101: 9 | Q101: ESTEC LTDA. | T101: nfernandez@estec.cl | U101: NO | V101: PRODUCTOS
C102: CJP152 | N102: ROTULADOS DISEÑO Y PRODUCCION | O102: 9937535 | P102: 3 | Q102: ROTULADOS DISEÑO Y PRODUCCION | T102: nicolas.rotulados@gmail.com | U102: SI
C103: CJP153 | N103: OCELEC | O103: 77102344 | P103: 4 | Q103: OCELEC. INGENIERÍA Y SERVICIOS SPA | T103: ocelec.certificacion@gmail.com | U103: NO | V103: CERTIFICADOR
C104: CJP155 | N104: Grúas Sánchez | O104: 76906671 | P104: 3 | Q104: GRUAS SANCHEZ SPA | T104: oficina@gruassanchez.cl | U104: SI
C105: CJP156 | N105: TEC FULL | O105: 76265749 | P105: k | Q105: SOCIEDAD GONZALEZ GAJARDO Y COMPAÑIA LIMITADA | T105: operaciones@tecfull.cl | U105: SI
...

Sheet Hoja 12
A1: =AD1 -> N° | B1: =IFERROR(__xludf.DUMMYFUNCTION("IMPORTRANGE(""https://docs.google.com/spreadsheets/d/1Dz9D4r98_okJYtOMWli3EWCiG9bWW1Wu2cHFRjpYMpc/edit?gid=1165819795#gid=1165819795"",""Respuestas de formulario 1!A:AC"")"),"Marca temporal") -> Marca temporal | C1: =IFERROR(__xludf.DUMMYFUNCTION("""COMPUTED_VALUE"""),"Dirección de correo electrónico") -> Dirección de correo electrónico | D1: =IFERROR(__xludf.DUMMYFUNCTION("""COMPUTED_VALUE"""),"Responsable UCT") -> Responsable UCT | E1: =IFERROR(__xludf.DUMMYFUNCTION("""COMPUTED_VALUE"""),"Numero de Pedido (OP)") -> Numero de Pedido (OP) | F1: =IFERROR(__xludf.DUMMYFUNCTION("""COMPUTED_VALUE"""),"Orden de Compra (OC)") -> Orden de Compra (OC) | G1: =IFERROR(__xludf.DUMMYFUNCTION("""COMPUTED_VALUE"""),"Precio del Trabajo") -> Precio del Trabajo | H1: =IFERROR(__xludf.DUMMYFUNCTION("""COMPUTED_VALUE"""),"Fecha Orden de Compra (OC)") -> Fecha Orden de Compra (OC) | I1: =IFERROR(__xludf.DUMMYFUNCTION("""COMPUTED_VALUE"""),"Fecha Inicio Trabajos") -> Fecha Inicio Trabajos | J1: =IFERROR(__xludf.DUMMYFUNCTION("""COMPUTED_VALUE"""),"Campus") -> Campus | K1: =IFERROR(__xludf.DUMMYFUNCTION("""COMPUTED_VALUE"""),"Edificio") -> Edificio | L1: =IFERROR(__xludf.DUMMYFUNCTION("""COMPUTED_VALUE"""),"Razón Social Proveedor") -> Razón Social Proveedor | M1: =IFERROR(__xludf.DUMMYFUNCTION("""COMPUTED_VALUE"""),"RUT Empresa") -> RUT Empresa | N1: =IFERROR(__xludf.DUMMYFUNCTION("""COMPUTED_VALUE"""),"Responsable del Servicio") -> Responsable del Servicio | O1: =IFERROR(__xludf.DUMMYFUNCTION("""COMPUTED_VALUE"""),"Tipo de Servicio") -> Tipo de Servicio | P1: =IFERROR(__xludf.DUMMYFUNCTION("""COMPUTED_VALUE"""),"Tipo de Mantención") -> Tipo de Mantención | Q1: =IFERROR(__xludf.DUMMYFUNCTION("""COMPUTED_VALUE"""),"Tipo de Operación") -> Tipo de Operación | R1: =IFERROR(__xludf.DUMMYFUNCTION("""COMPUTED_VALUE"""),"Tipo de Obra") -> Tipo de Obra | S1: =IFERROR(__xludf.DUMMYFUNCTION("""COMPUTED_VALUE"""),"Estado de Obra") -> Estado de Obra | T1: =IFERROR(__xludf.DUMMYFUNCTION("""COMPUTED_VALUE"""),"EP") -> EP | U1: =IFERROR(__xludf.DUMMYFUNCTION("""COMPUTED_VALUE"""),"Monto del EP") -> Monto del EP | V1: =IFERROR(__xludf.DUMMYFUNCTION("""COMPUTED_VALUE"""),"Descripción del Trabajo Realizado") -> Descripción del Trabajo Realizado | W1: =IFERROR(__xludf.DUMMYFUNCTION("""COMPUTED_VALUE"""),"Observaciones o Recomendaciones Técnicas") -> Observaciones o Recomendaciones Técnicas | X1: =IFERROR(__xludf.DUMMYFUNCTION("""COMPUTED_VALUE"""),"Evidencia Fotográfica") -> Evidencia Fotográfica | Y1: =IFERROR(__xludf.DUMMYFUNCTION("""COMPUTED_VALUE"""),"Correo de Contacto") -> Correo de Contacto | Z1: =IFERROR(__xludf.DUMMYFUNCTION("""COMPUTED_VALUE"""),"Monto OC") -> Monto OC | AA1: =IFERROR(__xludf.DUMMYFUNCTION("""COMPUTED_VALUE"""),"Monto Orden de Compra Ingrese el Precio IVA incluido. (*) Con puntos, sin signo $. Ejemplo: 100.000.000") -> Monto Orden de Compra Ingrese el Precio IVA incluido. (*) Con puntos, sin signo $. Ejemplo: 100.000.000 | AB1: =IFERROR(__xludf.DUMMYFUNCTION("""COMPUTED_VALUE"""),"Columna 24") -> Columna 24 | AC1: =IFERROR(__xludf.DUMMYFUNCTION("""COMPUTED_VALUE"""),"Fecha de Orden de Compra (OC)") -> Fecha de Orden de Compra (OC) | AD1: =IFERROR(__xludf.DUMMYFUNCTION("""COMPUTED_VALUE"""),"N°") -> N°
A2: =AD2 -> RC-360_26 | B2: =IFERROR(__xludf.DUMMYFUNCTION("""COMPUTED_VALUE"""),46240.37720456018) -> 46240.377 | C2: =IFERROR(__xludf.DUMMYFUNCTION("""COMPUTED_VALUE"""),"") | D2: =IFERROR(__xludf.DUMMYFUNCTION("""COMPUTED_VALUE"""),"Mauricio Zurita Aldea") -> Mauricio Zurita Aldea | F2: =IFERROR(__xludf.DUMMYFUNCTION("""COMPUTED_VALUE"""),"13100 - 2025") -> 13100 - 2025 | J2: =IFERROR(__xludf.DUMMYFUNCTION("""COMPUTED_VALUE"""),"Campus San Francisco - CSF") -> Campus San Francisco - CSF | K2: =IFERROR(__xludf.DUMMYFUNCTION("""COMPUTED_VALUE"""),"01") -> 01 | L2: =IFERROR(__xludf.DUMMYFUNCTION("""COMPUTED_VALUE"""),"Gyg servicios spa") -> Gyg servicios spa | M2: =IFERROR(__xludf.DUMMYFUNCTION("""COMPUTED_VALUE"""),"77.215.624-3") -> 77.215.624-3 | N2: =IFERROR(__xludf.DUMMYFUNCTION("""COMPUTED_VALUE"""),"Gustavo Fuentes - Supervisor Técnico") -> Gustavo Fuentes - Supervisor Técnico | O2: =IFERROR(__xludf.DUMMYFUNCTION("""COMPUTED_VALUE"""),"Mantenciones") -> Mantenciones | P2: =IFERROR(__xludf.DUMMYFUNCTION("""COMPUTED_VALUE"""),"Instalaciones Eléctricas") -> Instalaciones Eléctricas | V2: =IFERROR(__xludf.DUMMYFUNCTION("""COMPUTED_VALUE"""),"Instalación de 9 controles de Acceso") -> Instalación de 9 controles de Acceso | X2: =IFERROR(__xludf.DUMMYFUNCTION("""COMPUTED_VALUE"""),"https://drive.google.com/open?id=1ZcrrKWrriGPbmxVX4BLNTstgQuPOfrWe, https://drive.google.com/open?id=1-z-R4_IeGODgG0vV_MAl-DOhW1MS61pL, https://drive.google.com/open?id=1jyWPbtJZNrkzOV2N5GktzNS_hqDyjeE6") -> https://drive.google.com/open?id=1ZcrrKWrriGPbmxVX4BLNTstgQuPOfrWe, https://drive.google.com/open?id=1-z-R4_IeGODgG0vV_MAl-DOhW1MS61pL, https://drive.google.com/open?id=1jyWPbtJZNrkzOV2N5GktzNS_hqDyjeE6 | Y2: =IFERROR(__xludf.DUMMYFUNCTION("""COMPUTED_VALUE"""),"contacto@gygtecnologias.com") -> contacto@gygtecnologias.com | Z2: =IFERROR(__xludf.DUMMYFUNCTION("""COMPUTED_VALUE"""),1.257354E7) -> 12573540 | AD2: =IFERROR(__xludf.DUMMYFUNCTION("""COMPUTED_VALUE"""),"RC-360_26") -> RC-360_26
A3: =AD3 -> RC-013 | B3: =IFERROR(__xludf.DUMMYFUNCTION("""COMPUTED_VALUE"""),45898.43310476852) -> 45898.433 | C3: =IFERROR(__xludf.DUMMYFUNCTION("""COMPUTED_VALUE"""),"") | D3: =IFERROR(__xludf.DUMMYFUNCTION("""COMPUTED_VALUE"""),"Cristóbal Correa del Río") -> Cristóbal Correa del Río | F3: =IFERROR(__xludf.DUMMYFUNCTION("""COMPUTED_VALUE"""),"2025 - 7555 ") -> 2025 - 7555 | J3: =IFERROR(__xludf.DUMMYFUNCTION("""COMPUTED_VALUE"""),"Campus Prieto Norte - CHS") -> Campus Prieto Norte - CHS | K3: =IFERROR(__xludf.DUMMYFUNCTION("""COMPUTED_VALUE"""),"01") -> 01 | L3: =IFERROR(__xludf.DUMMYFUNCTION("""COMPUTED_VALUE"""),"Flavia Oyarzun Soto") -> Flavia Oyarzun Soto | M3: =IFERROR(__xludf.DUMMYFUNCTION("""COMPUTED_VALUE"""),"5.503.590-3") -> 5.503.590-3 | N3: =IFERROR(__xludf.DUMMYFUNCTION("""COMPUTED_VALUE"""),"Roberto Lassalle (supervisor)") -> Roberto Lassalle (supervisor) | O3: =IFERROR(__xludf.DUMMYFUNCTION("""COMPUTED_VALUE"""),"Obras") -> Obras | R3: =IFERROR(__xludf.DUMMYFUNCTION("""COMPUTED_VALUE"""),"Nuevo Edificio") -> Nuevo Edificio | S3: =IFERROR(__xludf.DUMMYFUNCTION("""COMPUTED_VALUE"""),"Recepción de Obra - RC") -> Recepción de Obra - RC | V3: =IFERROR(__xludf.DUMMYFUNCTION("""COMPUTED_VALUE"""),"Instalar 30 espejos redondos en nuevo edificio Hospital de Simulación Prieto Norte.") -> Instalar 30 espejos redondos en nuevo edificio Hospital de Simulación Prieto Norte. | W3: =IFERROR(__xludf.DUMMYFUNCTION("""COMPUTED_VALUE"""),"No requiere") -> No requiere | X3: =IFERROR(__xludf.DUMMYFUNCTION("""COMPUTED_VALUE"""),"https://drive.google.com/open?id=1tFT63Z5vt7R80Rmx0QtHf0eyewQKJNJf, https://drive.google.com/open?id=1pi-scmmjGUbLAXmFKkE2lu5uY2FGipCv") -> https://drive.google.com/open?id=1tFT63Z5vt7R80Rmx0QtHf0eyewQKJNJf, https://drive.google.com/open?id=1pi-scmmjGUbLAXmFKkE2lu5uY2FGipCv | Y3: =IFERROR(__xludf.DUMMYFUNCTION("""COMPUTED_VALUE"""),"roberto.lassalle@gmail.com") -> roberto.lassalle@gmail.com | AD3: =IFERROR(__xludf.DUMMYFUNCTION("""COMPUTED_VALUE"""),"RC-013") -> RC-013
A4: =AD4 -> RC-359_26 | B4: =IFERROR(__xludf.DUMMYFUNCTION("""COMPUTED_VALUE"""),46239.74387005787) -> 46239.744 | C4: =IFERROR(__xludf.DUMMYFUNCTION("""COMPUTED_VALUE"""),"") | D4: =IFERROR(__xludf.DUMMYFUNCTION("""COMPUTED_VALUE"""),"Mauricio Matus Belmar") -> Mauricio Matus Belmar | F4: =IFERROR(__xludf.DUMMYFUNCTION("""COMPUTED_VALUE"""),"6248-2026") -> 6248-2026 | J4: =IFERROR(__xludf.DUMMYFUNCTION("""COMPUTED_VALUE"""),"Campus San Francisco - CSF") -> Campus San Francisco - CSF | K4: =IFERROR(__xludf.DUMMYFUNCTION("""COMPUTED_VALUE"""),"07") -> 07 | L4: =IFERROR(__xludf.DUMMYFUNCTION("""COMPUTED_VALUE"""),"Kume Ruka SpA") -> Kume Ruka SpA | M4: =IFERROR(__xludf.DUMMYFUNCTION("""COMPUTED_VALUE"""),"77.929.977-5") -> 77.929.977-5 | N4: =IFERROR(__xludf.DUMMYFUNCTION("""COMPUTED_VALUE"""),"Hector Zambrano") -> Hector Zambrano | O4: =IFERROR(__xludf.DUMMYFUNCTION("""COMPUTED_VALUE"""),"Mantenciones") -> Mantenciones | P4: =IFERROR(__xludf.DUMMYFUNCTION("""COMPUTED_VALUE"""),"Cubiertas") -> Cubiertas | V4: =IFERROR(__xludf.DUMMYFUNCTION("""COMPUTED_VALUE"""),"Reparación de cubierta de teja asfáltica en sus cuatro aguas, junto a una limpieza de canaletas.") -> Reparación de cubierta de teja asfáltica en sus cuatro aguas, junto a una limpieza de canaletas. | X4: =IFERROR(__xludf.DUMMYFUNCTION("""COMPUTED_VALUE"""),"https://drive.google.com/open?id=1cXvDJ7N2IhzZHogjIvg142W4z5I1YLys, https://drive.google.com/open?id=1aYKnKhXqw7iQwiwWitUwE1qO3Mb_1JRE, https://drive.google.com/open?id=1RZwZNyN7BIj71mA_XgkLx4u7xEO1rBda, https://drive.google.com/open?id=1OjcSN0zDthQfPXi9v"&"9WRzxBnfze6clPW") -> https://drive.google.com/open?id=1cXvDJ7N2IhzZHogjIvg142W4z5I1YLys, https://drive.google.com/open?id=1aYKnKhXqw7iQwiwWitUwE1qO3Mb_1JRE, https://drive.google.com/open?id=1RZwZNyN7BIj71mA_XgkLx4u7xEO1rBda, https://drive.google.com/open?id=1OjcSN0zDthQfPXi9v9WRzxBnfze6clPW | Y4: =IFERROR(__xludf.DUMMYFUNCTION("""COMPUTED_VALUE"""),"hzambranoleal@gmail.com") -> hzambranoleal@gmail.com | Z4: =IFERROR(__xludf.DUMMYFUNCTION("""COMPUTED_VALUE"""),373851.0) -> 373851 | AD4: =IFERROR(__xludf.DUMMYFUNCTION("""COMPUTED_VALUE"""),"RC-359_26") -> RC-359_26
A5: =AD5 -> RC-357_26 | B5: =IFERROR(__xludf.DUMMYFUNCTION("""COMPUTED_VALUE"""),46238.457962465276) -> 46238.458 | C5: =IFERROR(__xludf.DUMMYFUNCTION("""COMPUTED_VALUE"""),"") | D5: =IFERROR(__xludf.DUMMYFUNCTION("""COMPUTED_VALUE"""),"Mauricio Matus Belmar") -> Mauricio Matus Belmar | F5: =IFERROR(__xludf.DUMMYFUNCTION("""COMPUTED_VALUE"""),"5284-2026") -> 5284-2026 | J5: =IFERROR(__xludf.DUMMYFUNCTION("""COMPUTED_VALUE"""),"Campus Dr. Luis Rivas del Canto - CRC") -> Campus Dr. Luis Rivas del Canto - CRC | K5: =IFERROR(__xludf.DUMMYFUNCTION("""COMPUTED_VALUE"""),17.0) -> 17 | L5: =IFERROR(__xludf.DUMMYFUNCTION("""COMPUTED_VALUE"""),"Inversiones y Constructora JBG SpA ") -> Inversiones y Constructora JBG SpA | M5: =IFERROR(__xludf.DUMMYFUNCTION("""COMPUTED_VALUE"""),"77.119.724-8") -> 77.119.724-8 | N5: =IFERROR(__xludf.DUMMYFUNCTION("""COMPUTED_VALUE"""),"Jorge barra G gerente operaciones") -> Jorge barra G gerente operaciones | O5: =IFERROR(__xludf.DUMMYFUNCTION("""COMPUTED_VALUE"""),"Mantenciones") -> Mantenciones | P5: =IFERROR(__xludf.DUMMYFUNCTION("""COMPUTED_VALUE"""),"Cubiertas") -> Cubiertas | V5: =IFERROR(__xludf.DUMMYFUNCTION("""COMPUTED_VALUE"""),"Sellos y colocación de fijaciones en cubierta a intervenir") -> Sellos y colocación de fijaciones en cubierta a intervenir | W5: =IFERROR(__xludf.DUMMYFUNCTION("""COMPUTED_VALUE"""),"El.swctor esta con clavos y sin sellos la mayoría de la.cubierta y además.los policarbonatos están quemados por clima y se aco será el cambio.de estas planchas y recambio de fijaciones y sellos de clavos a tornillos de madera .") -> El.swctor esta con clavos y sin sellos la mayoría de la.cubierta y además.los policarbonatos están quemados por clima y se aco será el cambio.de estas planchas y recambio de fijaciones y sellos de clavos a tornillos de madera . | X5: =IFERROR(__xludf.DUMMYFUNCTION("""COMPUTED_VALUE"""),"https://drive.google.com/open?id=1Ulh_7RPC9fk_MoIrBlF0bLa7huCYzYbx") -> https://drive.google.com/open?id=1Ulh_7RPC9fk_MoIrBlF0bLa7huCYzYbx | Y5: =IFERROR(__xludf.DUMMYFUNCTION("""COMPUTED_VALUE"""),"constructorajbg@gmail.com") -> constructorajbg@gmail.com | Z5: =IFERROR(__xludf.DUMMYFUNCTION("""COMPUTED_VALUE"""),202200.0) -> 202200 | AD5: =IFERROR(__xludf.DUMMYFUNCTION("""COMPUTED_VALUE"""),"RC-357_26") -> RC-357_26
A6: =AD6 -> RC-356_26 | B6: =IFERROR(__xludf.DUMMYFUNCTION("""COMPUTED_VALUE"""),46237.611955636574) -> 46237.612 | C6: =IFERROR(__xludf.DUMMYFUNCTION("""COMPUTED_VALUE"""),"") | D6: =IFERROR(__xludf.DUMMYFUNCTION("""COMPUTED_VALUE"""),"Cristóbal Correa del Río") -> Cristóbal Correa del Río | F6: =IFERROR(__xludf.DUMMYFUNCTION("""COMPUTED_VALUE"""),5675.0) -> 5675 | J6: =IFERROR(__xludf.DUMMYFUNCTION("""COMPUTED_VALUE"""),"Campus San Francisco - CSF") -> Campus San Francisco - CSF | K6: =IFERROR(__xludf.DUMMYFUNCTION("""COMPUTED_VALUE"""),"05") -> 05 | L6: =IFERROR(__xludf.DUMMYFUNCTION("""COMPUTED_VALUE"""),"Construcciones: luisexequielsoliscatalan, e.i.r.l") -> Construcciones: luisexequielsoliscatalan, e.i.r.l | M6: =IFERROR(__xludf.DUMMYFUNCTION("""COMPUTED_VALUE"""),"77.280.635-3") -> 77.280.635-3 | N6: =IFERROR(__xludf.DUMMYFUNCTION("""COMPUTED_VALUE"""),"Luis solis , contratista") -> Luis solis , contratista | O6: =IFERROR(__xludf.DUMMYFUNCTION("""COMPUTED_VALUE"""),"Mantenciones") -> Mantenciones | P6: =IFERROR(__xludf.DUMMYFUNCTION("""COMPUTED_VALUE"""),"Terminaciones Interiores") -> Terminaciones Interiores | V6: =IFERROR(__xludf.DUMMYFUNCTION("""COMPUTED_VALUE"""),"Encerar piso escenario aula magna , en dos manos ") -> Encerar piso escenario aula magna , en dos manos | W6: =IFERROR(__xludf.DUMMYFUNCTION("""COMPUTED_VALUE"""),"Se debe encerar el piso del escenario de manera esporadica. ") -> Se debe encerar el piso del escenario de manera esporadica. | X6: =IFERROR(__xludf.DUMMYFUNCTION("""COMPUTED_VALUE"""),"https://drive.google.com/open?id=1xbW61loVe-eiAkJklrN0Qdc1LNmSlyCR, https://drive.google.com/open?id=1I18hWgqLslzv4smsflo24huQHFs9_nc6, https://drive.google.com/open?id=1r_y8P2YtjHB2pyaKw1WwS6x42abNxKRi, https://drive.google.com/open?id=1n2adLbfRfSCBBusDP"&"MIZ5HWASbbX580n, https://drive.google.com/open?id=1eA_cMYy4rwD8tc53gKDVLPAMOFK9mmRA") -> https://drive.google.com/open?id=1xbW61loVe-eiAkJklrN0Qdc1LNmSlyCR, https://drive.google.com/open?id=1I18hWgqLslzv4smsflo24huQHFs9_nc6, https://drive.google.com/open?id=1r_y8P2YtjHB2pyaKw1WwS6x42abNxKRi, https://drive.google.com/open?id=1n2adLbfRfSCBBusDPMIZ5HWASbbX580n, https://drive.google.com/open?id=1eA_cMYy4rwD8tc53gKDVLPAMOFK9mmRA | Y6: =IFERROR(__xludf.DUMMYFUNCTION("""COMPUTED_VALUE"""),"luis.exequielsolis@gmail.com") -> luis.exequielsolis@gmail.com | Z6: =IFERROR(__xludf.DUMMYFUNCTION("""COMPUTED_VALUE"""),366282.0) -> 366282 | AD6: =IFERROR(__xludf.DUMMYFUNCTION("""COMPUTED_VALUE"""),"RC-356_26") -> RC-356_26
A7: =AD7 -> RC-355_26 | B7: =IFERROR(__xludf.DUMMYFUNCTION("""COMPUTED_VALUE"""),46237.59575050926) -> 46237.596 | C7: =IFERROR(__xludf.DUMMYFUNCTION("""COMPUTED_VALUE"""),"") | D7: =IFERROR(__xludf.DUMMYFUNCTION("""COMPUTED_VALUE"""),"Mauricio Matus Belmar") -> Mauricio Matus Belmar | F7: =IFERROR(__xludf.DUMMYFUNCTION("""COMPUTED_VALUE"""),"4144-2026") -> 4144-2026 | J7: =IFERROR(__xludf.DUMMYFUNCTION("""COMPUTED_VALUE"""),"Campus Educación Continua - CEC") -> Campus Educación Continua - CEC | K7: =IFERROR(__xludf.DUMMYFUNCTION("""COMPUTED_VALUE"""),"Sin número") -> Sin número | L7: =IFERROR(__xludf.DUMMYFUNCTION("""COMPUTED_VALUE"""),"Innovaclima MQ SPA") -> Innovaclima MQ SPA | M7: =IFERROR(__xludf.DUMMYFUNCTION("""COMPUTED_VALUE"""),"76.464.159-0") -> 76.464.159-0 | N7: =IFERROR(__xludf.DUMMYFUNCTION("""COMPUTED_VALUE"""),"Miguel Quezada Yáñez") -> Miguel Quezada Yáñez | O7: =IFERROR(__xludf.DUMMYFUNCTION("""COMPUTED_VALUE"""),"Mantenciones") -> Mantenciones | P7: =IFERROR(__xludf.DUMMYFUNCTION("""COMPUTED_VALUE"""),"Requerimientos Emergentes e Imprevistos") -> Requerimientos Emergentes e Imprevistos | V7: =IFERROR(__xludf.DUMMYFUNCTION("""COMPUTED_VALUE"""),"Cambio pistón regulación de presión combustión, quemador de Caldera ") -> Cambio pistón regulación de presión combustión, quemador de Caldera | X7: =IFERROR(__xludf.DUMMYFUNCTION("""COMPUTED_VALUE"""),"https://drive.google.com/open?id=1j8Zhb213Rmf_3f3J6zybBjHBRg0Zex3h") -> https://drive.google.com/open?id=1j8Zhb213Rmf_3f3J6zybBjHBRg0Zex3h | Y7: =IFERROR(__xludf.DUMMYFUNCTION("""COMPUTED_VALUE"""),"mquezaday@gmail.com") -> mquezaday@gmail.com | Z7: =IFERROR(__xludf.DUMMYFUNCTION("""COMPUTED_VALUE"""),231336.0) -> 231336 | AD7: =IFERROR(__xludf.DUMMYFUNCTION("""COMPUTED_VALUE"""),"RC-355_26") -> RC-355_26
A8: =AD8 -> RC-353_26 | B8: =IFERROR(__xludf.DUMMYFUNCTION("""COMPUTED_VALUE"""),46237.53648609953) -> 46237.536 | C8: =IFERROR(__xludf.DUMMYFUNCTION("""COMPUTED_VALUE"""),"") | D8: =IFERROR(__xludf.DUMMYFUNCTION("""COMPUTED_VALUE"""),"Felipe Anselme Grandón") -> Felipe Anselme Grandón | F8: =IFERROR(__xludf.DUMMYFUNCTION("""COMPUTED_VALUE"""),"6244 - 2026") -> 6244 - 2026 | J8: =IFERROR(__xludf.DUMMYFUNCTION("""COMPUTED_VALUE"""),"Campus San Juan Pablo II - CJP") -> Campus San Juan Pablo II - CJP | K8: =IFERROR(__xludf.DUMMYFUNCTION("""COMPUTED_VALUE"""),"08") -> 08 | L8: =IFERROR(__xludf.DUMMYFUNCTION("""COMPUTED_VALUE"""),"Constructora IGECE Ltda.") -> Constructora IGECE Ltda. | M8: =IFERROR(__xludf.DUMMYFUNCTION("""COMPUTED_VALUE"""),"76.878.824-3") -> 76.878.824-3 | N8: =IFERROR(__xludf.DUMMYFUNCTION("""COMPUTED_VALUE"""),"Carlos Troncoso - Gerente General ") -> Carlos Troncoso - Gerente General | O8: =IFERROR(__xludf.DUMMYFUNCTION("""COMPUTED_VALUE"""),"Mantenciones") -> Mantenciones | P8: =IFERROR(__xludf.DUMMYFUNCTION("""COMPUTED_VALUE"""),"Terminaciones Interiores") -> Terminaciones Interiores | V8: =IFERROR(__xludf.DUMMYFUNCTION("""COMPUTED_VALUE"""),"Retiro y Reinstalación Gabinete CJP08 Sala 135: DESARME GABINETE DE ALUMINIO , RETIRO JUANQUILLOS Y VIDRIOS INSTALACION GABINETE DE ALUMINIO , INSTALACION DE JUNQUILLOS SELLADOS CAMBIO DE 2 VIDRIOS NUEVOS UNO CON PERFORACION PARA LA CAMPANA ASEO Y RETIRO"&" DE ESCOMBROS") -> Retiro y Reinstalación Gabinete CJP08 Sala 135: DESARME GABINETE DE ALUMINIO , RETIRO JUANQUILLOS Y VIDRIOS INSTALACION GABINETE DE ALUMINIO , INSTALACION DE JUNQUILLOS SELLADOS CAMBIO DE 2 VIDRIOS NUEVOS UNO CON PERFORACION PARA LA CAMPANA ASEO Y RETIRO DE ESCOMBROS | X8: =IFERROR(__xludf.DUMMYFUNCTION("""COMPUTED_VALUE"""),"https://drive.google.com/open?id=1Mxjkmdr7EOcEXVBGglX_JIkI2EiM-u20, https://drive.google.com/open?id=1F4HiZi2uh25ULMlT8P15gyEWwB_btnk-, https://drive.google.com/open?id=1z1p8rMj9cb1IalnHySayB3MdDlF5lae-, https://drive.google.com/open?id=1QjDjL_kI3vIErVi6T"&"HMSwFJlq38G7sR7") -> https://drive.google.com/open?id=1Mxjkmdr7EOcEXVBGglX_JIkI2EiM-u20, https://drive.google.com/open?id=1F4HiZi2uh25ULMlT8P15gyEWwB_btnk-, https://drive.google.com/open?id=1z1p8rMj9cb1IalnHySayB3MdDlF5lae-, https://drive.google.com/open?id=1QjDjL_kI3vIErVi6THMSwFJlq38G7sR7 | Y8: =IFERROR(__xludf.DUMMYFUNCTION("""COMPUTED_VALUE"""),"fabian.i.burgos.s@gmail.com") -> fabian.i.burgos.s@gmail.com | Z8: =IFERROR(__xludf.DUMMYFUNCTION("""COMPUTED_VALUE"""),296310.0) -> 296310 | AD8: =IFERROR(__xludf.DUMMYFUNCTION("""COMPUTED_VALUE"""),"RC-353_26") -> RC-353_26
A9: =AD9 -> RC-352_26 | B9: =IFERROR(__xludf.DUMMYFUNCTION("""COMPUTED_VALUE"""),46237.47947388889) -> 46237.479 | C9: =IFERROR(__xludf.DUMMYFUNCTION("""COMPUTED_VALUE"""),"") | D9: =IFERROR(__xludf.DUMMYFUNCTION("""COMPUTED_VALUE"""),"Juan Ignacio Solís de Ovando") -> Juan Ignacio Solís de Ovando | F9: =IFERROR(__xludf.DUMMYFUNCTION("""COMPUTED_VALUE"""),"5650 - 2026") -> 5650 - 2026 | J9: =IFERROR(__xludf.DUMMYFUNCTION("""COMPUTED_VALUE"""),"Campus Dr. Luis Rivas del Canto - CRC") -> Campus Dr. Luis Rivas del Canto - CRC | K9: =IFERROR(__xludf.DUMMYFUNCTION("""COMPUTED_VALUE"""),"Exterior") -> Exterior | L9: =IFERROR(__xludf.DUMMYFUNCTION("""COMPUTED_VALUE"""),"Constructora IGECE Ltda.") -> Constructora IGECE Ltda. | M9: =IFERROR(__xludf.DUMMYFUNCTION("""COMPUTED_VALUE"""),"76.878.824-3") -> 76.878.824-3 | N9: =IFERROR(__xludf.DUMMYFUNCTION("""COMPUTED_VALUE"""),"Carlos Troncoso - Gerente General ") -> Carlos Troncoso - Gerente General | O9: =IFERROR(__xludf.DUMMYFUNCTION("""COMPUTED_VALUE"""),"Mantenciones") -> Mantenciones | P9: =IFERROR(__xludf.DUMMYFUNCTION("""COMPUTED_VALUE"""),"Suelos") -> Suelos | V9: =IFERROR(__xludf.DUMMYFUNCTION("""COMPUTED_VALUE"""),"Fabricación Estructura Radier: Escarpe, relleno, compactado, hormigonado, incorporación de fibra de refuerzo para hormigón.") -> Fabricación Estructura Radier: Escarpe, relleno, compactado, hormigonado, incorporación de fibra de refuerzo para hormigón. | X9: =IFERROR(__xludf.DUMMYFUNCTION("""COMPUTED_VALUE"""),"https://drive.google.com/open?id=1x-CSt9_jBwpg5WGrbqHlO1ySU4qD9LsY, https://drive.google.com/open?id=1pZ7fHMthId7MUgTBlb-j4WqGI8myLjea, https://drive.google.com/open?id=1AIOL2t3zd1G2EhjBc8EoUs1FBvQ-GgKV, https://drive.google.com/open?id=1SqLlCwmVk71SqF7p-"&"pjWzte5Qu-SKrAW, https://drive.google.com/open?id=13XHaHo3mHtcuBAWLXqaMLar577ld_UlV, https://drive.google.com/open?id=1xEp2Rvg3ervvQJnbFKSlX8WCEstIrYQh") -> https://drive.google.com/open?id=1x-CSt9_jBwpg5WGrbqHlO1ySU4qD9LsY, https://drive.google.com/open?id=1pZ7fHMthId7MUgTBlb-j4WqGI8myLjea, https://drive.google.com/open?id=1AIOL2t3zd1G2EhjBc8EoUs1FBvQ-GgKV, https://drive.google.com/open?id=1SqLlCwmVk71SqF7p-pjWzte5Qu-SKrAW, https://drive.google.com/open?id=13XHaHo3mHtcuBAWLXqaMLar577ld_UlV, https://drive.google.com/open?id=1xEp2Rvg3ervvQJnbFKSlX8WCEstIrYQh | Y9: =IFERROR(__xludf.DUMMYFUNCTION("""COMPUTED_VALUE"""),"fabian.i.burgos.s@gmail.com") -> fabian.i.burgos.s@gmail.com | Z9: =IFERROR(__xludf.DUMMYFUNCTION("""COMPUTED_VALUE"""),791648.0) -> 791648 | AD9: =IFERROR(__xludf.DUMMYFUNCTION("""COMPUTED_VALUE"""),"RC-352_26") -> RC-352_26
A10: =AD10 -> RC-351_26 | B10: =IFERROR(__xludf.DUMMYFUNCTION("""COMPUTED_VALUE"""),46237.477459594906) -> 46237.477 | C10: =IFERROR(__xludf.DUMMYFUNCTION("""COMPUTED_VALUE"""),"") | D10: =IFERROR(__xludf.DUMMYFUNCTION("""COMPUTED_VALUE"""),"Cristóbal Correa del Río") -> Cristóbal Correa del Río | F10: =IFERROR(__xludf.DUMMYFUNCTION("""COMPUTED_VALUE"""),"5251 - 2026") -> 5251 - 2026 | J10: =IFERROR(__xludf.DUMMYFUNCTION("""COMPUTED_VALUE"""),"Campus San Francisco - CSF") -> Campus San Francisco - CSF | K10: =IFERROR(__xludf.DUMMYFUNCTION("""COMPUTED_VALUE"""),12.0) -> 12 | L10: =IFERROR(__xludf.DUMMYFUNCTION("""COMPUTED_VALUE"""),"Constructora IGECE Ltda.") -> Constructora IGECE Ltda. | M10: =IFERROR(__xludf.DUMMYFUNCTION("""COMPUTED_VALUE"""),"76.878.824-3") -> 76.878.824-3 | N10: =IFERROR(__xludf.DUMMYFUNCTION("""COMPUTED_VALUE"""),"Carlos Troncoso - Gerente General ") -> Carlos Troncoso - Gerente General | O10: =IFERROR(__xludf.DUMMYFUNCTION("""COMPUTED_VALUE"""),"Mantenciones") -> Mantenciones | P10: =IFERROR(__xludf.DUMMYFUNCTION("""COMPUTED_VALUE"""),"Suelos") -> Suelos | V10: =IFERROR(__xludf.DUMMYFUNCTION("""COMPUTED_VALUE"""),"Fabricación Rampa Hormigón 0,15x1,4x2,35: Retiro Estructura piso, instalación polietileno, instalación malla Acma, instalación moldajes, hormigonado, afinado y pintado.") -> Fabricación Rampa Hormigón 0,15x1,4x2,35: Retiro Estructura piso, instalación polietileno, instalación malla Acma, instalación moldajes, hormigonado, afinado y pintado. | X10: =IFERROR(__xludf.DUMMYFUNCTION("""COMPUTED_VALUE"""),"https://drive.google.com/open?id=1MZCCO-0EUxPyeH1EEetjvaq6maNVSe8d, https://drive.google.com/open?id=1DbLkxULSKuPHjCnIY2pl5vYkX27Q5hk0, https://drive.google.com/open?id=1CQ2koqm3VFKu78EdjWyF2QlbaYCv2sVL, https://drive.google.com/open?id=1EzgeOtiSQEVPl0jMu"&"OjHl6V5yymtRhol") -> https://drive.google.com/open?id=1MZCCO-0EUxPyeH1EEetjvaq6maNVSe8d, https://drive.google.com/open?id=1DbLkxULSKuPHjCnIY2pl5vYkX27Q5hk0, https://drive.google.com/open?id=1CQ2koqm3VFKu78EdjWyF2QlbaYCv2sVL, https://drive.google.com/open?id=1EzgeOtiSQEVPl0jMuOjHl6V5yymtRhol | Y10: =IFERROR(__xludf.DUMMYFUNCTION("""COMPUTED_VALUE"""),"fabian.i.burgos.s@gmail.com") -> fabian.i.burgos.s@gmail.com | Z10: =IFERROR(__xludf.DUMMYFUNCTION("""COMPUTED_VALUE"""),365996.0) -> 365996 | AD10: =IFERROR(__xludf.DUMMYFUNCTION("""COMPUTED_VALUE"""),"RC-351_26") -> RC-351_26
A11: =AD11 -> RC-350_26 | B11: =IFERROR(__xludf.DUMMYFUNCTION("""COMPUTED_VALUE"""),46237.47530471065) -> 46237.475 | C11: =IFERROR(__xludf.DUMMYFUNCTION("""COMPUTED_VALUE"""),"") | D11: =IFERROR(__xludf.DUMMYFUNCTION("""COMPUTED_VALUE"""),"Mauricio Matus Belmar") -> Mauricio Matus Belmar | F11: =IFERROR(__xludf.DUMMYFUNCTION("""COMPUTED_VALUE"""),"4874 - 2026") -> 4874 - 2026 | J11: =IFERROR(__xludf.DUMMYFUNCTION("""COMPUTED_VALUE"""),"Campus San Juan Pablo II - CJP") -> Campus San Juan Pablo II - CJP | K11: =IFERROR(__xludf.DUMMYFUNCTION("""COMPUTED_VALUE"""),"02") -> 02 | L11: =IFERROR(__xludf.DUMMYFUNCTION("""COMPUTED_VALUE"""),"Constructora IGECE Ltda.") -> Constructora IGECE Ltda. | M11: =IFERROR(__xludf.DUMMYFUNCTION("""COMPUTED_VALUE"""),"76.878.824-3") -> 76.878.824-3 | N11: =IFERROR(__xludf.DUMMYFUNCTION("""COMPUTED_VALUE"""),"Carlos Troncoso - Gerente General ") -> Carlos Troncoso - Gerente General | O11: =IFERROR(__xludf.DUMMYFUNCTION("""COMPUTED_VALUE"""),"Mantenciones") -> Mantenciones | P11: =IFERROR(__xludf.DUMMYFUNCTION("""COMPUTED_VALUE"""),"Terminaciones Interiores") -> Terminaciones Interiores | V11: =IFERROR(__xludf.DUMMYFUNCTION("""COMPUTED_VALUE"""),"Cambio Plancha + Pintura CJP02 Of 5: Retiro plancha con humedad, instalación nueva plancha, huinchas, empaste, yeso, lijado, aplicación 2 manos de pintura látex.") -> Cambio Plancha + Pintura CJP02 Of 5: Retiro plancha con humedad, instalación nueva plancha, huinchas, empaste, yeso, lijado, aplicación 2 manos de pintura látex. | X11: =IFERROR(__xludf.DUMMYFUNCTION("""COMPUTED_VALUE"""),"https://drive.google.com/open?id=1TecFEMyOMNTqA0fPN2Ns5nfC8LQ4M4eq, https://drive.google.com/open?id=1rJkR8ncZRV-wX_nCZp-l9Q9RTpnU5u-4, https://drive.google.com/open?id=1qyRtw6a6_tQeIC5sXS9KsqBX7JT1Xr7F, https://drive.google.com/open?id=1q8B4wU1mjhNCrbtQI"&"6phjJnEMIoFy_L5") -> https://drive.google.com/open?id=1TecFEMyOMNTqA0fPN2Ns5nfC8LQ4M4eq, https://drive.google.com/open?id=1rJkR8ncZRV-wX_nCZp-l9Q9RTpnU5u-4, https://drive.google.com/open?id=1qyRtw6a6_tQeIC5sXS9KsqBX7JT1Xr7F, https://drive.google.com/open?id=1q8B4wU1mjhNCrbtQI6phjJnEMIoFy_L5 | Y11: =IFERROR(__xludf.DUMMYFUNCTION("""COMPUTED_VALUE"""),"fabian.i.burgos.s@gmail.com") -> fabian.i.burgos.s@gmail.com | Z11: =IFERROR(__xludf.DUMMYFUNCTION("""COMPUTED_VALUE"""),235620.0) -> 235620 | AD11: =IFERROR(__xludf.DUMMYFUNCTION("""COMPUTED_VALUE"""),"RC-350_26") -> RC-350_26
A12: =AD12 -> RC-348_26 | B12: =IFERROR(__xludf.DUMMYFUNCTION("""COMPUTED_VALUE"""),46237.468722997684) -> 46237.469 | C12: =IFERROR(__xludf.DUMMYFUNCTION("""COMPUTED_VALUE"""),"") | D12: =IFERROR(__xludf.DUMMYFUNCTION("""COMPUTED_VALUE"""),"Cristóbal Correa del Río") -> Cristóbal Correa del Río | F12: =IFERROR(__xludf.DUMMYFUNCTION("""COMPUTED_VALUE"""),"4219 - 2026") -> 4219 - 2026 | J12: =IFERROR(__xludf.DUMMYFUNCTION("""COMPUTED_VALUE"""),"Campus San Francisco - CSF") -> Campus San Francisco - CSF | K12: =IFERROR(__xludf.DUMMYFUNCTION("""COMPUTED_VALUE"""),16.0) -> 16 | L12: =IFERROR(__xludf.DUMMYFUNCTION("""COMPUTED_VALUE"""),"Constructora IGECE Ltda.") -> Constructora IGECE Ltda. | M12: =IFERROR(__xludf.DUMMYFUNCTION("""COMPUTED_VALUE"""),"76.878.824-3") -> 76.878.824-3 | N12: =IFERROR(__xludf.DUMMYFUNCTION("""COMPUTED_VALUE"""),"Carlos Troncoso - Gerente General ") -> Carlos Troncoso - Gerente General | O12: =IFERROR(__xludf.DUMMYFUNCTION("""COMPUTED_VALUE"""),"Mantenciones") -> Mantenciones | P12: =IFERROR(__xludf.DUMMYFUNCTION("""COMPUTED_VALUE"""),"Terminaciones Interiores") -> Terminaciones Interiores | V12: =IFERROR(__xludf.DUMMYFUNCTION("""COMPUTED_VALUE"""),"Fabricación 2 Escritorios 0,75x1,75x0,73 : Fabricación en marco acero 40x30x3 electro pintado, base Melamina blanca 15 mm, instalación tapacantos blanco en todo el perímetro de la cubierta instalación tapas en las 8 patas de los escritorios. Fabricación "&"2 Cajoneras con ruedas 0,4x0,4x0,68: Fabricación en melamina blanca de 15 mm espesor, instalación 8 ruedas giratorias con freno (soporta hasta 45 kg cada rueda). Retape tabique 1,64x1,1 + Pintura 2.3x2.4: Instalación plancha yeso cartón st 10 mm, refuerz"&"o con Metalcon 60, huinchas, pasta, lijado, aplicación 2 manos de pintura tipo esmalte al agua (definir color). Fabricación e instalación Mampara: Fabricación e instalación Mampara puerta abatible + paño fijo, marco aluminio color champaña, vidrios simpl"&"e. ORDEN, ASEO Y RETIRO EXEDENTES: Se Realiza aseo general y retiro de todo residuo generado por los trabajos, dejando todo en perfectas condiciones.") -> Fabricación 2 Escritorios 0,75x1,75x0,73 : Fabricación en marco acero 40x30x3 electro pintado, base Melamina blanca 15 mm, instalación tapacantos blanco en todo el perímetro de la cubierta instalación tapas en las 8 patas de los escritorios. Fabricación 2 Cajoneras con ruedas 0,4x0,4x0,68: Fabricación en melamina blanca de 15 mm espesor, instalación 8 ruedas giratorias con freno (soporta hasta 45 kg cada rueda). Retape tabique 1,64x1,1 + Pintura 2.3x2.4: Instalación plancha yeso cartón st 10 mm, refuerzo con Metalcon 60, huinchas, pasta, lijado, aplicación 2 manos de pintura tipo esmalte al agua (definir color). Fabricación e instalación Mampara: Fabricación e instalación Mampara puerta abatible + paño fijo, marco aluminio color champaña, vidrios simple. ORDEN, ASEO Y RETIRO EXEDENTES: Se Realiza aseo general y retiro de todo residuo generado por los trabajos, dejando todo en perfectas condiciones. | X12: =IFERROR(__xludf.DUMMYFUNCTION("""COMPUTED_VALUE"""),"https://drive.google.com/open?id=1eXefSUA-Pl_JOnlhc8kFHBYa8eXggMMI, https://drive.google.com/open?id=1MtqwqrcfBlVC2YbrA6mqj2zDFVtQ_3ap, https://drive.google.com/open?id=1jVSChMSXexAkQts9TKDxW4wSWUN9TNA_, https://drive.google.com/open?id=1y3mg6nsNGPInGgGmO"&"KcvlGXMyJOiGWaF") -> https://drive.google.com/open?id=1eXefSUA-Pl_JOnlhc8kFHBYa8eXggMMI, https://drive.google.com/open?id=1MtqwqrcfBlVC2YbrA6mqj2zDFVtQ_3ap, https://drive.google.com/open?id=1jVSChMSXexAkQts9TKDxW4wSWUN9TNA_, https://drive.google.com/open?id=1y3mg6nsNGPInGgGmOKcvlGXMyJOiGWaF | Y12: =IFERROR(__xludf.DUMMYFUNCTION("""COMPUTED_VALUE"""),"fabian.i.burgos.s@gmail.com") -> fabian.i.burgos.s@gmail.com | Z12: =IFERROR(__xludf.DUMMYFUNCTION("""COMPUTED_VALUE"""),1401043.0) -> 1401043 | AD12: =IFERROR(__xludf.DUMMYFUNCTION("""COMPUTED_VALUE"""),"RC-348_26") -> RC-348_26
A13: =AD13 -> RC-023 | B13: =IFERROR(__xludf.DUMMYFUNCTION("""COMPUTED_VALUE"""),45905.51824628472) -> 45905.518 | C13: =IFERROR(__xludf.DUMMYFUNCTION("""COMPUTED_VALUE"""),"") | D13: =IFERROR(__xludf.DUMMYFUNCTION("""COMPUTED_VALUE"""),"Mauricio Matus Belmar") -> Mauricio Matus Belmar | F13: =IFERROR(__xludf.DUMMYFUNCTION("""COMPUTED_VALUE"""),6077.0) -> 6077 | J13: =IFERROR(__xludf.DUMMYFUNCTION("""COMPUTED_VALUE"""),"Campus Pillanlelbun - CPL") -> Campus Pillanlelbun - CPL | K13: =IFERROR(__xludf.DUMMYFUNCTION("""COMPUTED_VALUE"""),"Exterior") -> Exterior | L13: =IFERROR(__xludf.DUMMYFUNCTION("""COMPUTED_VALUE"""),"Empresa Constructora IGECE Ltda.") -> Empresa Constructora IGECE Ltda. | M13: =IFERROR(__xludf.DUMMYFUNCTION("""COMPUTED_VALUE"""),"76.878.824-3") -> 76.878.824-3 | N13: =IFERROR(__xludf.DUMMYFUNCTION("""COMPUTED_VALUE"""),"Carlos Troncoso Gerente General ") -> Carlos Troncoso Gerente General | O13: =IFERROR(__xludf.DUMMYFUNCTION("""COMPUTED_VALUE"""),"Obras") -> Obras | R13: =IFERROR(__xludf.DUMMYFUNCTION("""COMPUTED_VALUE"""),"Remodelación") -> Remodelación | S13: =IFERROR(__xludf.DUMMYFUNCTION("""COMPUTED_VALUE"""),"Recepción de Obra - RC") -> Recepción de Obra - RC | V13: =IFERROR(__xludf.DUMMYFUNCTION("""COMPUTED_VALUE"""),"Se realizó mejoramiento sala de ordeña, sector lechería ") -> Se realizó mejoramiento sala de ordeña, sector lechería | X13: =IFERROR(__xludf.DUMMYFUNCTION("""COMPUTED_VALUE"""),"https://drive.google.com/open?id=1eWpC4neyrHAD3N8XHBpmddWthpqNwhtF, https://drive.google.com/open?id=1R5J1r0XqeyJtgDJuR7OrW3sNMISWUO8O, https://drive.google.com/open?id=1k1KZ8kDZnF945MxkjSpMOBc4zXchBrmV, https://drive.google.com/open?id=1KZC1AckmhXQ0ZhSiu"&"_QzaQEnttYXqo4S, https://drive.google.com/open?id=1tWUUYUKqIoC1DX7oUVVPGK1eHk0mhtFD") -> https://drive.google.com/open?id=1eWpC4neyrHAD3N8XHBpmddWthpqNwhtF, https://drive.google.com/open?id=1R5J1r0XqeyJtgDJuR7OrW3sNMISWUO8O, https://drive.google.com/open?id=1k1KZ8kDZnF945MxkjSpMOBc4zXchBrmV, https://drive.google.com/open?id=1KZC1AckmhXQ0ZhSiu_QzaQEnttYXqo4S, https://drive.google.com/open?id=1tWUUYUKqIoC1DX7oUVVPGK1eHk0mhtFD | Y13: =IFERROR(__xludf.DUMMYFUNCTION("""COMPUTED_VALUE"""),"carlostroncosom@hotmail.com") -> carlostroncosom@hotmail.com | AD13: =IFERROR(__xludf.DUMMYFUNCTION("""COMPUTED_VALUE"""),"RC-023") -> RC-023
A14: =AD14 -> RC-347_26 | B14: =IFERROR(__xludf.DUMMYFUNCTION("""COMPUTED_VALUE"""),46237.4660028125) -> 46237.466 | C14: =IFERROR(__xludf.DUMMYFUNCTION("""COMPUTED_VALUE"""),"") | D14: =IFERROR(__xludf.DUMMYFUNCTION("""COMPUTED_VALUE"""),"Carol Huenchual Chañilao") -> Carol Huenchual Chañilao | F14: =IFERROR(__xludf.DUMMYFUNCTION("""COMPUTED_VALUE"""),"5189 - 2026") -> 5189 - 2026 | J14: =IFERROR(__xludf.DUMMYFUNCTION("""COMPUTED_VALUE"""),"Campus San Francisco - CSF") -> Campus San Francisco - CSF | K14: =IFERROR(__xludf.DUMMYFUNCTION("""COMPUTED_VALUE"""),10.0) -> 10 | L14: =IFERROR(__xludf.DUMMYFUNCTION("""COMPUTED_VALUE"""),"Constructora IGECE Ltda.") -> Constructora IGECE Ltda. | M14: =IFERROR(__xludf.DUMMYFUNCTION("""COMPUTED_VALUE"""),"76.878.824-3") -> 76.878.824-3 | N14: =IFERROR(__xludf.DUMMYFUNCTION("""COMPUTED_VALUE"""),"Carlos Troncoso - Gerente General ") -> Carlos Troncoso - Gerente General | O14: =IFERROR(__xludf.DUMMYFUNCTION("""COMPUTED_VALUE"""),"Mantenciones") -> Mantenciones | P14: =IFERROR(__xludf.DUMMYFUNCTION("""COMPUTED_VALUE"""),"Cubiertas") -> Cubiertas | V14: =IFERROR(__xludf.DUMMYFUNCTION("""COMPUTED_VALUE"""),"Detalle Trabajos Filtración CSF10 Sala de estar: Revisión y detección filtración, secado cubierta sector reparar, repaso y mejoramientos sellos varios.") -> Detalle Trabajos Filtración CSF10 Sala de estar: Revisión y detección filtración, secado cubierta sector reparar, repaso y mejoramientos sellos varios. | X14: =IFERROR(__xludf.DUMMYFUNCTION("""COMPUTED_VALUE"""),"https://drive.google.com/open?id=13xhYLXIUr7r951KqW8GfDmyxjOneyDFF") -> https://drive.google.com/open?id=13xhYLXIUr7r951KqW8GfDmyxjOneyDFF | Y14: =IFERROR(__xludf.DUMMYFUNCTION("""COMPUTED_VALUE"""),"fabian.i.burgos.s@gmail.com") -> fabian.i.burgos.s@gmail.com | Z14: =IFERROR(__xludf.DUMMYFUNCTION("""COMPUTED_VALUE"""),338079.0) -> 338079 | AD14: =IFERROR(__xludf.DUMMYFUNCTION("""COMPUTED_VALUE"""),"RC-347_26") -> RC-347_26
A15: =AD15 -> RC-345_26 | B15: =IFERROR(__xludf.DUMMYFUNCTION("""COMPUTED_VALUE"""),46237.463149664356) -> 46237.463 | C15: =IFERROR(__xludf.DUMMYFUNCTION("""COMPUTED_VALUE"""),"") | D15: =IFERROR(__xludf.DUMMYFUNCTION("""COMPUTED_VALUE"""),"Carol Huenchual Chañilao") -> Carol Huenchual Chañilao | F15: =IFERROR(__xludf.DUMMYFUNCTION("""COMPUTED_VALUE"""),"5171 - 2026") -> 5171 - 2026 | J15: =IFERROR(__xludf.DUMMYFUNCTION("""COMPUTED_VALUE"""),"Campus San Francisco - CSF") -> Campus San Francisco - CSF | K15: =IFERROR(__xludf.DUMMYFUNCTION("""COMPUTED_VALUE"""),13.0) -> 13 | L15: =IFERROR(__xludf.DUMMYFUNCTION("""COMPUTED_VALUE"""),"Constructora IGECE Ltda.") -> Constructora IGECE Ltda. | M15: =IFERROR(__xludf.DUMMYFUNCTION("""COMPUTED_VALUE"""),"76.878.824-3") -> 76.878.824-3 | N15: =IFERROR(__xludf.DUMMYFUNCTION("""COMPUTED_VALUE"""),"Carlos Troncoso - Gerente General ") -> Carlos Troncoso - Gerente General | O15: =IFERROR(__xludf.DUMMYFUNCTION("""COMPUTED_VALUE"""),"Mantenciones") -> Mantenciones | P15: =IFERROR(__xludf.DUMMYFUNCTION("""COMPUTED_VALUE"""),"Cubiertas") -> Cubiertas | V15: =IFERROR(__xludf.DUMMYFUNCTION("""COMPUTED_VALUE"""),"Filtración CSF13 Oficina con goteras: Revisión filtración, mejoramiento sellos y revisión tornillos.") -> Filtración CSF13 Oficina con goteras: Revisión filtración, mejoramiento sellos y revisión tornillos. | X15: =IFERROR(__xludf.DUMMYFUNCTION("""COMPUTED_VALUE"""),"https://drive.google.com/open?id=1KQShVGp2Yx3dEbof2R1Zr5ehIHsOqtqG, https://drive.google.com/open?id=1bo7HMi_b4kk9Zd-6z4b9HDpm-W06Vhm3, https://drive.google.com/open?id=1UhpAFIPkHjaExbQsf6bkAwSMEUBN8sjE") -> https://drive.google.com/open?id=1KQShVGp2Yx3dEbof2R1Zr5ehIHsOqtqG, https://drive.google.com/open?id=1bo7HMi_b4kk9Zd-6z4b9HDpm-W06Vhm3, https://drive.google.com/open?id=1UhpAFIPkHjaExbQsf6bkAwSMEUBN8sjE | Y15: =IFERROR(__xludf.DUMMYFUNCTION("""COMPUTED_VALUE"""),"fabian.i.burgos.s@gmail.com") -> fabian.i.burgos.s@gmail.com | Z15: =IFERROR(__xludf.DUMMYFUNCTION("""COMPUTED_VALUE"""),57120.0) -> 57120 | AD15: =IFERROR(__xludf.DUMMYFUNCTION("""COMPUTED_VALUE"""),"RC-345_26") -> RC-345_26
A16: =AD16 -> RC-344_26 | B16: =IFERROR(__xludf.DUMMYFUNCTION("""COMPUTED_VALUE"""),46234.3973606713) -> 46234.397 | C16: =IFERROR(__xludf.DUMMYFUNCTION("""COMPUTED_VALUE"""),"") | D16: =IFERROR(__xludf.DUMMYFUNCTION("""COMPUTED_VALUE"""),"Oscar Painén Briones") -> Oscar Painén Briones | F16: =IFERROR(__xludf.DUMMYFUNCTION("""COMPUTED_VALUE"""),"6269 2026") -> 6269 2026 | J16: =IFERROR(__xludf.DUMMYFUNCTION("""COMPUTED_VALUE"""),"Campus San Francisco - CSF") -> Campus San Francisco - CSF | K16: =IFERROR(__xludf.DUMMYFUNCTION("""COMPUTED_VALUE"""),14.0) -> 14 | L16: =IFERROR(__xludf.DUMMYFUNCTION("""COMPUTED_VALUE"""),"Ingertemuco Ingeniería Spa ") -> Ingertemuco Ingeniería Spa | M16: =IFERROR(__xludf.DUMMYFUNCTION("""COMPUTED_VALUE"""),"77.369.471-0") -> 77.369.471-0 | N16: =IFERROR(__xludf.DUMMYFUNCTION("""COMPUTED_VALUE"""),"Christian Ortega") -> Christian Ortega | O16: =IFERROR(__xludf.DUMMYFUNCTION("""COMPUTED_VALUE"""),"Mantenciones") -> Mantenciones | P16: =IFERROR(__xludf.DUMMYFUNCTION("""COMPUTED_VALUE"""),"Instalaciones Eléctricas") -> Instalaciones Eléctricas | V16: =IFERROR(__xludf.DUMMYFUNCTION("""COMPUTED_VALUE"""),"Se instalan accesorios de control de acceso en CSF14, retirados previamente de CJPII") -> Se instalan accesorios de control de acceso en CSF14, retirados previamente de CJPII | X16: =IFERROR(__xludf.DUMMYFUNCTION("""COMPUTED_VALUE"""),"https://drive.google.com/open?id=1AVc9ZJSpTWkfsXuO802G3A_MtVH-MmM-, https://drive.google.com/open?id=1o2bAUe8A80fgQxTIELs4hbdGL_PUqLTg, https://drive.google.com/open?id=1U-P1x59nHbsWsQAgjneXicRP6Gj80z50, https://drive.google.com/open?id=1d7NN7joU8cIHktjHn"&"1YwPvZ0eD4by5DO, https://drive.google.com/open?id=1MT0RHyqLkOj2DJfmZ_KYg4mHsj2owddE") -> https://drive.google.com/open?id=1AVc9ZJSpTWkfsXuO802G3A_MtVH-MmM-, https://drive.google.com/open?id=1o2bAUe8A80fgQxTIELs4hbdGL_PUqLTg, https://drive.google.com/open?id=1U-P1x59nHbsWsQAgjneXicRP6Gj80z50, https://drive.google.com/open?id=1d7NN7joU8cIHktjHn1YwPvZ0eD4by5DO, https://drive.google.com/open?id=1MT0RHyqLkOj2DJfmZ_KYg4mHsj2owddE | Y16: =IFERROR(__xludf.DUMMYFUNCTION("""COMPUTED_VALUE"""),"comercialingertemuco@gmail.com") -> comercialingertemuco@gmail.com | Z16: =IFERROR(__xludf.DUMMYFUNCTION("""COMPUTED_VALUE"""),211502.0) -> 211502 | AD16: =IFERROR(__xludf.DUMMYFUNCTION("""COMPUTED_VALUE"""),"RC-344_26") -> RC-344_26
A17: =AD17 -> RC-343_26 | B17: =IFERROR(__xludf.DUMMYFUNCTION("""COMPUTED_VALUE"""),46232.43033674768) -> 46232.43 | C17: =IFERROR(__xludf.DUMMYFUNCTION("""COMPUTED_VALUE"""),"") | D17: =IFERROR(__xludf.DUMMYFUNCTION("""COMPUTED_VALUE"""),"Carol Huenchual Chañilao") -> Carol Huenchual Chañilao | F17: =IFERROR(__xludf.DUMMYFUNCTION("""COMPUTED_VALUE"""),"6260-2026") -> 6260-2026 | J17: =IFERROR(__xludf.DUMMYFUNCTION("""COMPUTED_VALUE"""),"Campus San Francisco - CSF") -> Campus San Francisco - CSF | K17: =IFERROR(__xludf.DUMMYFUNCTION("""COMPUTED_VALUE"""),"03") -> 03 | L17: =IFERROR(__xludf.DUMMYFUNCTION("""COMPUTED_VALUE"""),"Flavia Oyarzun Soto ") -> Flavia Oyarzun Soto | M17: =IFERROR(__xludf.DUMMYFUNCTION("""COMPUTED_VALUE"""),"5.503.590-3") -> 5.503.590-3 | N17: =IFERROR(__xludf.DUMMYFUNCTION("""COMPUTED_VALUE"""),"Roberto lassalle supervisor") -> Roberto lassalle supervisor | O17: =IFERROR(__xludf.DUMMYFUNCTION("""COMPUTED_VALUE"""),"Mantenciones") -> Mantenciones | P17: =IFERROR(__xludf.DUMMYFUNCTION("""COMPUTED_VALUE"""),"Cubiertas") -> Cubiertas | V17: =IFERROR(__xludf.DUMMYFUNCTION("""COMPUTED_VALUE"""),"Cambio de forro interior de cielo pasillo techado") -> Cambio de forro interior de cielo pasillo techado | W17: =IFERROR(__xludf.DUMMYFUNCTION("""COMPUTED_VALUE"""),"Se supervisó en terreno.") -> Se supervisó en terreno. | X17: =IFERROR(__xludf.DUMMYFUNCTION("""COMPUTED_VALUE"""),"https://drive.google.com/open?id=12NVDdFT4TSoSBXXdcxqr0WOxamCoEwOB, https://drive.google.com/open?id=1TUH_4r4hjXMLFJB-3ta5AuS5EuohekTV") -> https://drive.google.com/open?id=12NVDdFT4TSoSBXXdcxqr0WOxamCoEwOB, https://drive.google.com/open?id=1TUH_4r4hjXMLFJB-3ta5AuS5EuohekTV | Y17: =IFERROR(__xludf.DUMMYFUNCTION("""COMPUTED_VALUE"""),"roberto.lassalle@gmail.com") -> roberto.lassalle@gmail.com | Z17: =IFERROR(__xludf.DUMMYFUNCTION("""COMPUTED_VALUE"""),189210.0) -> 189210 | AD17: =IFERROR(__xludf.DUMMYFUNCTION("""COMPUTED_VALUE"""),"RC-343_26") -> RC-343_26
A18: =AD18 -> RC-342_26 | B18: =IFERROR(__xludf.DUMMYFUNCTION("""COMPUTED_VALUE"""),46232.42619452546) -> 46232.426 | C18: =IFERROR(__xludf.DUMMYFUNCTION("""COMPUTED_VALUE"""),"") | D18: =IFERROR(__xludf.DUMMYFUNCTION("""COMPUTED_VALUE"""),"Carol Huenchual Chañilao") -> Carol Huenchual Chañilao | F18: =IFERROR(__xludf.DUMMYFUNCTION("""COMPUTED_VALUE"""),"6310-2026") -> 6310-2026 | J18: =IFERROR(__xludf.DUMMYFUNCTION("""COMPUTED_VALUE"""),"Campus San Francisco - CSF") -> Campus San Francisco - CSF | K18: =IFERROR(__xludf.DUMMYFUNCTION("""COMPUTED_VALUE"""),11.0) -> 11 | L18: =IFERROR(__xludf.DUMMYFUNCTION("""COMPUTED_VALUE"""),"Flavia Oyarzun Soto ") -> Flavia Oyarzun Soto | M18: =IFERROR(__xludf.DUMMYFUNCTION("""COMPUTED_VALUE"""),"5.503.590-3") -> 5.503.590-3 | N18: =IFERROR(__xludf.DUMMYFUNCTION("""COMPUTED_VALUE"""),"Roberto Lassalle supervisor ") -> Roberto Lassalle supervisor | O18: =IFERROR(__xludf.DUMMYFUNCTION("""COMPUTED_VALUE"""),"Mantenciones") -> Mantenciones | P18: =IFERROR(__xludf.DUMMYFUNCTION("""COMPUTED_VALUE"""),"Terminaciones Interiores") -> Terminaciones Interiores | V18: =IFERROR(__xludf.DUMMYFUNCTION("""COMPUTED_VALUE"""),"Reparación de piso interior de porcelanato") -> Reparación de piso interior de porcelanato | W18: =IFERROR(__xludf.DUMMYFUNCTION("""COMPUTED_VALUE"""),"Se inspeccionó en terreno con solicitante. ") -> Se inspeccionó en terreno con solicitante. | X18: =IFERROR(__xludf.DUMMYFUNCTION("""COMPUTED_VALUE"""),"https://drive.google.com/open?id=164zZZvkDA41AGcrYMdXHbZQXIZXg4hqO, https://drive.google.com/open?id=1o7jEOBuNjf4pcdM7Bcp9jksQ4tSNe6Mt, https://drive.google.com/open?id=1hNkDOtRa3kPprSo6mLgDVwG1Z1bcfhP4, https://drive.google.com/open?id=1yPzC4AoTaxBxLuLW5"&"Ao3QqebmXCGrKo7") -> https://drive.google.com/open?id=164zZZvkDA41AGcrYMdXHbZQXIZXg4hqO, https://drive.google.com/open?id=1o7jEOBuNjf4pcdM7Bcp9jksQ4tSNe6Mt, https://drive.google.com/open?id=1hNkDOtRa3kPprSo6mLgDVwG1Z1bcfhP4, https://drive.google.com/open?id=1yPzC4AoTaxBxLuLW5Ao3QqebmXCGrKo7 | Y18: =IFERROR(__xludf.DUMMYFUNCTION("""COMPUTED_VALUE"""),"roberto.lassalle@gmail.com") -> roberto.lassalle@gmail.com | Z18: =IFERROR(__xludf.DUMMYFUNCTION("""COMPUTED_VALUE"""),2111774.0) -> 2111774 | AD18: =IFERROR(__xludf.DUMMYFUNCTION("""COMPUTED_VALUE"""),"RC-342_26") -> RC-342_26
A19: =AD19 -> RC-340_26 | B19: =IFERROR(__xludf.DUMMYFUNCTION("""COMPUTED_VALUE"""),46230.86683726852) -> 46230.867 | C19: =IFERROR(__xludf.DUMMYFUNCTION("""COMPUTED_VALUE"""),"") | D19: =IFERROR(__xludf.DUMMYFUNCTION("""COMPUTED_VALUE"""),"Mauricio Matus Belmar") -> Mauricio Matus Belmar | F19: =IFERROR(__xludf.DUMMYFUNCTION("""COMPUTED_VALUE"""),"5134-2026") -> 5134-2026 | J19: =IFERROR(__xludf.DUMMYFUNCTION("""COMPUTED_VALUE"""),"Campus Educación Continua - CEC") -> Campus Educación Continua - CEC | K19: =IFERROR(__xludf.DUMMYFUNCTION("""COMPUTED_VALUE"""),18.0) -> 18 | L19: =IFERROR(__xludf.DUMMYFUNCTION("""COMPUTED_VALUE"""),"InnovaclimaMQ SPA") -> InnovaclimaMQ SPA | M19: =IFERROR(__xludf.DUMMYFUNCTION("""COMPUTED_VALUE"""),"76.464.159-0") -> 76.464.159-0 | N19: =IFERROR(__xludf.DUMMYFUNCTION("""COMPUTED_VALUE"""),"Miguel Quezada Yáñez, Dueño") -> Miguel Quezada Yáñez, Dueño | O19: =IFERROR(__xludf.DUMMYFUNCTION("""COMPUTED_VALUE"""),"Mantenciones") -> Mantenciones | P19: =IFERROR(__xludf.DUMMYFUNCTION("""COMPUTED_VALUE"""),"Requerimientos Emergentes e Imprevistos") -> Requerimientos Emergentes e Imprevistos | V19: =IFERROR(__xludf.DUMMYFUNCTION("""COMPUTED_VALUE"""),"Cambio de bomba centrifuga de calefacción por una nueva. Estaba en mal estado") -> Cambio de bomba centrifuga de calefacción por una nueva. Estaba en mal estado | W19: =IFERROR(__xludf.DUMMYFUNCTION("""COMPUTED_VALUE"""),"requiere verificación de caudal") -> requiere verificación de caudal | X19: =IFERROR(__xludf.DUMMYFUNCTION("""COMPUTED_VALUE"""),"https://drive.google.com/open?id=1m1j-Jd_u9syseAViEwtc-40daYlPR9cE, https://drive.google.com/open?id=1QH97lvyotzqMXGz-Aw-Ub04OYNs-vMak") -> https://drive.google.com/open?id=1m1j-Jd_u9syseAViEwtc-40daYlPR9cE, https://drive.google.com/open?id=1QH97lvyotzqMXGz-Aw-Ub04OYNs-vMak | Y19: =IFERROR(__xludf.DUMMYFUNCTION("""COMPUTED_VALUE"""),"mquezaday@gmail.com") -> mquezaday@gmail.com | Z19: =IFERROR(__xludf.DUMMYFUNCTION("""COMPUTED_VALUE"""),1130500.0) -> 1130500 | AD19: =IFERROR(__xludf.DUMMYFUNCTION("""COMPUTED_VALUE"""),"RC-340_26") -> RC-340_26
A20: =AD20 -> RC-339_26 | B20: =IFERROR(__xludf.DUMMYFUNCTION("""COMPUTED_VALUE"""),46230.66630143518) -> 46230.666 | C20: =IFERROR(__xludf.DUMMYFUNCTION("""COMPUTED_VALUE"""),"") | D20: =IFERROR(__xludf.DUMMYFUNCTION("""COMPUTED_VALUE"""),"Arturo Meza Vega") -> Arturo Meza Vega | F20: =IFERROR(__xludf.DUMMYFUNCTION("""COMPUTED_VALUE"""),"5782 - 2026") -> 5782 - 2026 | J20: =IFERROR(__xludf.DUMMYFUNCTION("""COMPUTED_VALUE"""),"Campus Dr. Luis Rivas del Canto - CRC") -> Campus Dr. Luis Rivas del Canto - CRC | K20: =IFERROR(__xludf.DUMMYFUNCTION("""COMPUTED_VALUE"""),10.0) -> 10 | L20: =IFERROR(__xludf.DUMMYFUNCTION("""COMPUTED_VALUE"""),"J&D Ingeniería y Ejecución SPA") -> J&D Ingeniería y Ejecución SPA | M20: =IFERROR(__xludf.DUMMYFUNCTION("""COMPUTED_VALUE"""),"78.368.635-K") -> 78.368.635-K | N20: =IFERROR(__xludf.DUMMYFUNCTION("""COMPUTED_VALUE"""),"José Espinoza - Jefe de Proyectos") -> José Espinoza - Jefe de Proyectos | O20: =IFERROR(__xludf.DUMMYFUNCTION("""COMPUTED_VALUE"""),"Mantenciones") -> Mantenciones | P20: =IFERROR(__xludf.DUMMYFUNCTION("""COMPUTED_VALUE"""),"Instalaciones Eléctricas") -> Instalaciones Eléctricas | V20: =IFERROR(__xludf.DUMMYFUNCTION("""COMPUTED_VALUE"""),"Mejoras para control de iluminación y acceso a controles remotos auditorio CRC10") -> Mejoras para control de iluminación y acceso a controles remotos auditorio CRC10 | X20: =IFERROR(__xludf.DUMMYFUNCTION("""COMPUTED_VALUE"""),"https://drive.google.com/open?id=1ffk0KrfeL6AlDoXHdX20bIsC9tK7Q-S7") -> https://drive.google.com/open?id=1ffk0KrfeL6AlDoXHdX20bIsC9tK7Q-S7 | Y20: =IFERROR(__xludf.DUMMYFUNCTION("""COMPUTED_VALUE"""),"jotayde.ingenieria@gmail.com") -> jotayde.ingenieria@gmail.com | Z20: =IFERROR(__xludf.DUMMYFUNCTION("""COMPUTED_VALUE"""),446250.0) -> 446250 | AD20: =IFERROR(__xludf.DUMMYFUNCTION("""COMPUTED_VALUE"""),"RC-339_26") -> RC-339_26
A21: =AD21 -> RC-338_26 | B21: =IFERROR(__xludf.DUMMYFUNCTION("""COMPUTED_VALUE"""),46229.76060300926) -> 46229.761 | C21: =IFERROR(__xludf.DUMMYFUNCTION("""COMPUTED_VALUE"""),"") | D21: =IFERROR(__xludf.DUMMYFUNCTION("""COMPUTED_VALUE"""),"Mauricio Matus Belmar") -> Mauricio Matus Belmar | F21: =IFERROR(__xludf.DUMMYFUNCTION("""COMPUTED_VALUE"""),"6273-2026") -> 6273-2026 | J21: =IFERROR(__xludf.DUMMYFUNCTION("""COMPUTED_VALUE"""),"Campus San Francisco - CSF") -> Campus San Francisco - CSF | K21: =IFERROR(__xludf.DUMMYFUNCTION("""COMPUTED_VALUE"""),17.0) -> 17 | L21: =IFERROR(__xludf.DUMMYFUNCTION("""COMPUTED_VALUE"""),"Flavia Oyarzun Soto") -> Flavia Oyarzun Soto | M21: =IFERROR(__xludf.DUMMYFUNCTION("""COMPUTED_VALUE"""),"5.503.590-3") -> 5.503.590-3 | N21: =IFERROR(__xludf.DUMMYFUNCTION("""COMPUTED_VALUE"""),"Supervisor, Roberto Lassalle Prado") -> Supervisor, Roberto Lassalle Prado | O21: =IFERROR(__xludf.DUMMYFUNCTION("""COMPUTED_VALUE"""),"Mantenciones") -> Mantenciones | P21: =IFERROR(__xludf.DUMMYFUNCTION("""COMPUTED_VALUE"""),"Cubiertas") -> Cubiertas | V21: =IFERROR(__xludf.DUMMYFUNCTION("""COMPUTED_VALUE"""),"Reparación de techumbre y forros de coronación ") -> Reparación de techumbre y forros de coronación | X21: =IFERROR(__xludf.DUMMYFUNCTION("""COMPUTED_VALUE"""),"https://drive.google.com/open?id=1lplSFqzu2lRs3NObOla0i17yB9-k-eac, https://drive.google.com/open?id=1UJyl1ol5K-OXvSDyJsxBCORBNDG0AjDU, https://drive.google.com/open?id=12rCjgYL0eeLC47Llv2uqWaq2JDabnhtY, https://drive.google.com/open?id=1qxIAl2iLFB813MBIs"&"wkaSaSO0IJ_zBk5") -> https://drive.google.com/open?id=1lplSFqzu2lRs3NObOla0i17yB9-k-eac, https://drive.google.com/open?id=1UJyl1ol5K-OXvSDyJsxBCORBNDG0AjDU, https://drive.google.com/open?id=12rCjgYL0eeLC47Llv2uqWaq2JDabnhtY, https://drive.google.com/open?id=1qxIAl2iLFB813MBIswkaSaSO0IJ_zBk5 | Y21: =IFERROR(__xludf.DUMMYFUNCTION("""COMPUTED_VALUE"""),"roberto.lassalle@gmail.com") -> roberto.lassalle@gmail.com | Z21: =IFERROR(__xludf.DUMMYFUNCTION("""COMPUTED_VALUE"""),702100.0) -> 702100 | AD21: =IFERROR(__xludf.DUMMYFUNCTION("""COMPUTED_VALUE"""),"RC-338_26") -> RC-338_26
A22: =AD22 -> RC-337_26 | B22: =IFERROR(__xludf.DUMMYFUNCTION("""COMPUTED_VALUE"""),46229.75704627315) -> 46229.757 | C22: =IFERROR(__xludf.DUMMYFUNCTION("""COMPUTED_VALUE"""),"") | D22: =IFERROR(__xludf.DUMMYFUNCTION("""COMPUTED_VALUE"""),"Mauricio Matus Belmar") -> Mauricio Matus Belmar | F22: =IFERROR(__xludf.DUMMYFUNCTION("""COMPUTED_VALUE"""),"6272-2026") -> 6272-2026 | J22: =IFERROR(__xludf.DUMMYFUNCTION("""COMPUTED_VALUE"""),"Campus Dr. Luis Rivas del Canto - CRC") -> Campus Dr. Luis Rivas del Canto - CRC | K22: =IFERROR(__xludf.DUMMYFUNCTION("""COMPUTED_VALUE"""),"01") -> 01 | L22: =IFERROR(__xludf.DUMMYFUNCTION("""COMPUTED_VALUE"""),"Flavia Oyarzun Soto") -> Flavia Oyarzun Soto | M22: =IFERROR(__xludf.DUMMYFUNCTION("""COMPUTED_VALUE"""),"5.503.590-3") -> 5.503.590-3 | N22: =IFERROR(__xludf.DUMMYFUNCTION("""COMPUTED_VALUE"""),"Supervisor Roberto Lassalle Prado") -> Supervisor Roberto Lassalle Prado | O22: =IFERROR(__xludf.DUMMYFUNCTION("""COMPUTED_VALUE"""),"Mantenciones") -> Mantenciones | P22: =IFERROR(__xludf.DUMMYFUNCTION("""COMPUTED_VALUE"""),"Cubiertas") -> Cubiertas | V22: =IFERROR(__xludf.DUMMYFUNCTION("""COMPUTED_VALUE"""),"Reparaciones de cubiertas por temporal 2026") -> Reparaciones de cubiertas por temporal 2026 | X22: =IFERROR(__xludf.DUMMYFUNCTION("""COMPUTED_VALUE"""),"https://drive.google.com/open?id=1SqCLHLQCw5Mh9NIkArtIvVOd9NqxHOFH, https://drive.google.com/open?id=1MczrgiPJuAluv67mvK9uxPIQG9yf3WkM, https://drive.google.com/open?id=1KKrzxu-uvrTirILXcB9Fe5ej5M94R7Xb") -> https://drive.google.com/open?id=1SqCLHLQCw5Mh9NIkArtIvVOd9NqxHOFH, https://drive.google.com/open?id=1MczrgiPJuAluv67mvK9uxPIQG9yf3WkM, https://drive.google.com/open?id=1KKrzxu-uvrTirILXcB9Fe5ej5M94R7Xb | Y22: =IFERROR(__xludf.DUMMYFUNCTION("""COMPUTED_VALUE"""),"roberto.lassalle@gmail.com") -> roberto.lassalle@gmail.com | Z22: =IFERROR(__xludf.DUMMYFUNCTION("""COMPUTED_VALUE"""),642600.0) -> 642600 | AD22: =IFERROR(__xludf.DUMMYFUNCTION("""COMPUTED_VALUE"""),"RC-337_26") -> RC-337_26
A23: =AD23 -> RC-336_26 | B23: =IFERROR(__xludf.DUMMYFUNCTION("""COMPUTED_VALUE"""),46229.74959869213) -> 46229.75 | C23: =IFERROR(__xludf.DUMMYFUNCTION("""COMPUTED_VALUE"""),"") | D23: =IFERROR(__xludf.DUMMYFUNCTION("""COMPUTED_VALUE"""),"Mauricio Matus Belmar") -> Mauricio Matus Belmar | F23: =IFERROR(__xludf.DUMMYFUNCTION("""COMPUTED_VALUE"""),"6055-2026") -> 6055-2026 | J23: =IFERROR(__xludf.DUMMYFUNCTION("""COMPUTED_VALUE"""),"Campus Dr. Luis Rivas del Canto - CRC") -> Campus Dr. Luis Rivas del Canto - CRC | K23: =IFERROR(__xludf.DUMMYFUNCTION("""COMPUTED_VALUE"""),"01") -> 01 | L23: =IFERROR(__xludf.DUMMYFUNCTION("""COMPUTED_VALUE"""),"Flavia Oyarzun Soto") -> Flavia Oyarzun Soto | M23: =IFERROR(__xludf.DUMMYFUNCTION("""COMPUTED_VALUE"""),"5.503.590-3") -> 5.503.590-3 | N23: =IFERROR(__xludf.DUMMYFUNCTION("""COMPUTED_VALUE"""),"Roberto Lassalle Prado, Supervisor") -> Roberto Lassalle Prado, Supervisor | O23: =IFERROR(__xludf.DUMMYFUNCTION("""COMPUTED_VALUE"""),"Mantenciones") -> Mantenciones | P23: =IFERROR(__xludf.DUMMYFUNCTION("""COMPUTED_VALUE"""),"Cubiertas") -> Cubiertas | V23: =IFERROR(__xludf.DUMMYFUNCTION("""COMPUTED_VALUE"""),"Cambio de planchas de zinc y cambio de tornillos") -> Cambio de planchas de zinc y cambio de tornillos | X23: =IFERROR(__xludf.DUMMYFUNCTION("""COMPUTED_VALUE"""),"https://drive.google.com/open?id=148ugR2C02vxcpVKpSZdf0ExydEauty_w, https://drive.google.com/open?id=11NG257TXifxuKJ5h7ddlCKs_C-l9mrBR, https://drive.google.com/open?id=17Sd6Xxpgy4dC7d7ty6GSerq2AcI5-pDk, https://drive.google.com/open?id=1T0SYBnT3XE27GvArX"&"nqBM0h7MnayZEAh") -> https://drive.google.com/open?id=148ugR2C02vxcpVKpSZdf0ExydEauty_w, https://drive.google.com/open?id=11NG257TXifxuKJ5h7ddlCKs_C-l9mrBR, https://drive.google.com/open?id=17Sd6Xxpgy4dC7d7ty6GSerq2AcI5-pDk, https://drive.google.com/open?id=1T0SYBnT3XE27GvArXnqBM0h7MnayZEAh | Y23: =IFERROR(__xludf.DUMMYFUNCTION("""COMPUTED_VALUE"""),"roberto.lassalle@gmail.com") -> roberto.lassalle@gmail.com | Z23: =IFERROR(__xludf.DUMMYFUNCTION("""COMPUTED_VALUE"""),648550.0) -> 648550 | AD23: =IFERROR(__xludf.DUMMYFUNCTION("""COMPUTED_VALUE"""),"RC-336_26") -> RC-336_26
A24: =AD24 -> RC-335_26 | B24: =IFERROR(__xludf.DUMMYFUNCTION("""COMPUTED_VALUE"""),46229.74447416667) -> 46229.744 | C24: =IFERROR(__xludf.DUMMYFUNCTION("""COMPUTED_VALUE"""),"") | D24: =IFERROR(__xludf.DUMMYFUNCTION("""COMPUTED_VALUE"""),"Mauricio Matus Belmar") -> Mauricio Matus Belmar | F24: =IFERROR(__xludf.DUMMYFUNCTION("""COMPUTED_VALUE"""),"6020-2026") -> 6020-2026 | J24: =IFERROR(__xludf.DUMMYFUNCTION("""COMPUTED_VALUE"""),"Campus Dr. Luis Rivas del Canto - CRC") -> Campus Dr. Luis Rivas del Canto - CRC | K24: =IFERROR(__xludf.DUMMYFUNCTION("""COMPUTED_VALUE"""),"Exterior") -> Exterior | L24: =IFERROR(__xludf.DUMMYFUNCTION("""COMPUTED_VALUE"""),"Flavia Oyarzun Soto") -> Flavia Oyarzun Soto | M24: =IFERROR(__xludf.DUMMYFUNCTION("""COMPUTED_VALUE"""),"5.503.590-3") -> 5.503.590-3 | N24: =IFERROR(__xludf.DUMMYFUNCTION("""COMPUTED_VALUE"""),"Mauricio Matus") -> Mauricio Matus | O24: =IFERROR(__xludf.DUMMYFUNCTION("""COMPUTED_VALUE"""),"Mantenciones") -> Mantenciones | P24: =IFERROR(__xludf.DUMMYFUNCTION("""COMPUTED_VALUE"""),"Requerimientos Emergentes e Imprevistos") -> Requerimientos Emergentes e Imprevistos | V24: =IFERROR(__xludf.DUMMYFUNCTION("""COMPUTED_VALUE"""),"Reparación cerco perimetral") -> Reparación cerco perimetral | X24: =IFERROR(__xludf.DUMMYFUNCTION("""COMPUTED_VALUE"""),"https://drive.google.com/open?id=1pUVrqXF6lHmrjtn3-3wuiIncSksjju-z, https://drive.google.com/open?id=1-RX-YHMgDLTvhusmintB7oZkzmQTDdO0, https://drive.google.com/open?id=1cxT_r7qS68SYQqi5l4xNdGatP-jz0owl, https://drive.google.com/open?id=15oBSK-L1U-umRB3NS"&"lqaL6964mFvn_er") -> https://drive.google.com/open?id=1pUVrqXF6lHmrjtn3-3wuiIncSksjju-z, https://drive.google.com/open?id=1-RX-YHMgDLTvhusmintB7oZkzmQTDdO0, https://drive.google.com/open?id=1cxT_r7qS68SYQqi5l4xNdGatP-jz0owl, https://drive.google.com/open?id=15oBSK-L1U-umRB3NSlqaL6964mFvn_er | Y24: =IFERROR(__xludf.DUMMYFUNCTION("""COMPUTED_VALUE"""),"roberto.lassalle@gmail.com") -> roberto.lassalle@gmail.com | Z24: =IFERROR(__xludf.DUMMYFUNCTION("""COMPUTED_VALUE"""),257040.0) -> 257040 | AD24: =IFERROR(__xludf.DUMMYFUNCTION("""COMPUTED_VALUE"""),"RC-335_26") -> RC-335_26
A25: =AD25 -> RC-334_26 | B25: =IFERROR(__xludf.DUMMYFUNCTION("""COMPUTED_VALUE"""),46227.394847013886) -> 46227.395 | C25: =IFERROR(__xludf.DUMMYFUNCTION("""COMPUTED_VALUE"""),"") | D25: =IFERROR(__xludf.DUMMYFUNCTION("""COMPUTED_VALUE"""),"Mauricio Matus Belmar") -> Mauricio Matus Belmar | F25: =IFERROR(__xludf.DUMMYFUNCTION("""COMPUTED_VALUE"""),"4189-2026") -> 4189-2026 | J25: =IFERROR(__xludf.DUMMYFUNCTION("""COMPUTED_VALUE"""),"Campus Dr. Luis Rivas del Canto - CRC") -> Campus Dr. Luis Rivas del Canto - CRC | K25: =IFERROR(__xludf.DUMMYFUNCTION("""COMPUTED_VALUE"""),"09") -> 09 | L25: =IFERROR(__xludf.DUMMYFUNCTION("""COMPUTED_VALUE"""),"SOC. GONZALEZ GAJARDO Y CIA. LTDA") -> SOC. GONZALEZ GAJARDO Y CIA. LTDA | M25: =IFERROR(__xludf.DUMMYFUNCTION("""COMPUTED_VALUE"""),"76.265.749-K") -> 76.265.749-K | N25: =IFERROR(__xludf.DUMMYFUNCTION("""COMPUTED_VALUE"""),"MARCELO GONZALEZ") -> MARCELO GONZALEZ | O25: =IFERROR(__xludf.DUMMYFUNCTION("""COMPUTED_VALUE"""),"Mantenciones") -> Mantenciones | P25: =IFERROR(__xludf.DUMMYFUNCTION("""COMPUTED_VALUE"""),"Instalaciones de Agua Potable") -> Instalaciones de Agua Potable | V25: =IFERROR(__xludf.DUMMYFUNCTION("""COMPUTED_VALUE"""),"MODERNIZACION SALA DE BOMBAS CRC09") -> MODERNIZACION SALA DE BOMBAS CRC09 | W25: =IFERROR(__xludf.DUMMYFUNCTION("""COMPUTED_VALUE"""),"NO") -> NO | X25: =IFERROR(__xludf.DUMMYFUNCTION("""COMPUTED_VALUE"""),"https://drive.google.com/open?id=1VZoXIp1Ul00pN_vJHqbrqSyzNHBnF2YL, https://drive.google.com/open?id=1m0OviF7NHzWPS77IoG0pWRwhOEeGmL0D, https://drive.google.com/open?id=1yDGu6qYLUR6ykPBRvP-pVdx8HQOnzzmY") -> https://drive.google.com/open?id=1VZoXIp1Ul00pN_vJHqbrqSyzNHBnF2YL, https://drive.google.com/open?id=1m0OviF7NHzWPS77IoG0pWRwhOEeGmL0D, https://drive.google.com/open?id=1yDGu6qYLUR6ykPBRvP-pVdx8HQOnzzmY | Y25: =IFERROR(__xludf.DUMMYFUNCTION("""COMPUTED_VALUE"""),"operaciones@tecfull.cl") -> operaciones@tecfull.cl | Z25: =IFERROR(__xludf.DUMMYFUNCTION("""COMPUTED_VALUE"""),1.06624E7) -> 10662400 | AD25: =IFERROR(__xludf.DUMMYFUNCTION("""COMPUTED_VALUE"""),"RC-334_26") -> RC-334_26
A26: =AD26 -> RC-333_26 | B26: =IFERROR(__xludf.DUMMYFUNCTION("""COMPUTED_VALUE"""),46226.52963063658) -> 46226.53 | C26: =IFERROR(__xludf.DUMMYFUNCTION("""COMPUTED_VALUE"""),"") | D26: =IFERROR(__xludf.DUMMYFUNCTION("""COMPUTED_VALUE"""),"Mauricio Matus Belmar") -> Mauricio Matus Belmar | F26: =IFERROR(__xludf.DUMMYFUNCTION("""COMPUTED_VALUE"""),"6256-2026") -> 6256-2026 | J26: =IFERROR(__xludf.DUMMYFUNCTION("""COMPUTED_VALUE"""),"Campus San Francisco - CSF") -> Campus San Francisco - CSF | K26: =IFERROR(__xludf.DUMMYFUNCTION("""COMPUTED_VALUE"""),"Exterior") -> Exterior | L26: =IFERROR(__xludf.DUMMYFUNCTION("""COMPUTED_VALUE"""),"GATICAR SPA ") -> GATICAR SPA | M26: =IFERROR(__xludf.DUMMYFUNCTION("""COMPUTED_VALUE"""),"77.578.487-3") -> 77.578.487-3 | N26: =IFERROR(__xludf.DUMMYFUNCTION("""COMPUTED_VALUE"""),"HECTOR ANDRES GATICA BADILLA ") -> HECTOR ANDRES GATICA BADILLA | O26: =IFERROR(__xludf.DUMMYFUNCTION("""COMPUTED_VALUE"""),"Mantenciones") -> Mantenciones | P26: =IFERROR(__xludf.DUMMYFUNCTION("""COMPUTED_VALUE"""),"Requerimientos Emergentes e Imprevistos") -> Requerimientos Emergentes e Imprevistos | V26: =IFERROR(__xludf.DUMMYFUNCTION("""COMPUTED_VALUE"""),"TRABAJOS DE MEJORAMIENTO POST TEMPORAL ESPACIOS ABIERTOS") -> TRABAJOS DE MEJORAMIENTO POST TEMPORAL ESPACIOS ABIERTOS | X26: =IFERROR(__xludf.DUMMYFUNCTION("""COMPUTED_VALUE"""),"https://drive.google.com/open?id=1xXsMbGTYZWjEOIAiBPM0wNx4_YzufCju, https://drive.google.com/open?id=17wvwFn9HCaCEUl3cssmCcMM2r1Kz3bGD, https://drive.google.com/open?id=1lOrEoF3lmhK4wgHzKKW_a__Uh_zU3WXg") -> https://drive.google.com/open?id=1xXsMbGTYZWjEOIAiBPM0wNx4_YzufCju, https://drive.google.com/open?id=17wvwFn9HCaCEUl3cssmCcMM2r1Kz3bGD, https://drive.google.com/open?id=1lOrEoF3lmhK4wgHzKKW_a__Uh_zU3WXg | Y26: =IFERROR(__xludf.DUMMYFUNCTION("""COMPUTED_VALUE"""),"serviciogaticar@gmail.com") -> serviciogaticar@gmail.com | Z26: =IFERROR(__xludf.DUMMYFUNCTION("""COMPUTED_VALUE"""),535500.0) -> 535500 | AD26: =IFERROR(__xludf.DUMMYFUNCTION("""COMPUTED_VALUE"""),"RC-333_26") -> RC-333_26
A27: =AD27 -> RC-332_26 | B27: =IFERROR(__xludf.DUMMYFUNCTION("""COMPUTED_VALUE"""),46226.43909023148) -> 46226.439 | C27: =IFERROR(__xludf.DUMMYFUNCTION("""COMPUTED_VALUE"""),"") | D27: =IFERROR(__xludf.DUMMYFUNCTION("""COMPUTED_VALUE"""),"Mauricio Matus Belmar") -> Mauricio Matus Belmar | F27: =IFERROR(__xludf.DUMMYFUNCTION("""COMPUTED_VALUE"""),"6223-2026") -> 6223-2026 | J27: =IFERROR(__xludf.DUMMYFUNCTION("""COMPUTED_VALUE"""),"Campus Dr. Luis Rivas del Canto - CRC") -> Campus Dr. Luis Rivas del Canto - CRC | K27: =IFERROR(__xludf.DUMMYFUNCTION("""COMPUTED_VALUE"""),"03") -> 03 | L27: =IFERROR(__xludf.DUMMYFUNCTION("""COMPUTED_VALUE"""),"INGENIERIA Y CONSTRUCCIONES ELEKTRICA SPA") -> INGENIERIA Y CONSTRUCCIONES ELEKTRICA SPA | M27: =IFERROR(__xludf.DUMMYFUNCTION("""COMPUTED_VALUE"""),"76.884.395-3") -> 76.884.395-3 | N27: =IFERROR(__xludf.DUMMYFUNCTION("""COMPUTED_VALUE"""),"Marco Paine Salgado - Gerente") -> Marco Paine Salgado - Gerente | O27: =IFERROR(__xludf.DUMMYFUNCTION("""COMPUTED_VALUE"""),"Mantenciones") -> Mantenciones | P27: =IFERROR(__xludf.DUMMYFUNCTION("""COMPUTED_VALUE"""),"Instalaciones Eléctricas") -> Instalaciones Eléctricas | V27: =IFERROR(__xludf.DUMMYFUNCTION("""COMPUTED_VALUE"""),"REPARACIÓN ELÉCTRICA SALA 230 EDIFICIO CRC03") -> REPARACIÓN ELÉCTRICA SALA 230 EDIFICIO CRC03 | X27: =IFERROR(__xludf.DUMMYFUNCTION("""COMPUTED_VALUE"""),"https://drive.google.com/open?id=1wZurFkWnzlb5ZESFXVYGflSqe_G_Nm84, https://drive.google.com/open?id=1OXaFw1ddFDv5ejsIiNMTv1pQZmDK3k7k, https://drive.google.com/open?id=1V69eq7LYtQuK3uCwW1sFQz_aAaEX0yEY, https://drive.google.com/open?id=19EzRX1407xK5nDOQX"&"yULV7nZhC7BVTmB") -> https://drive.google.com/open?id=1wZurFkWnzlb5ZESFXVYGflSqe_G_Nm84, https://drive.google.com/open?id=1OXaFw1ddFDv5ejsIiNMTv1pQZmDK3k7k, https://drive.google.com/open?id=1V69eq7LYtQuK3uCwW1sFQz_aAaEX0yEY, https://drive.google.com/open?id=19EzRX1407xK5nDOQXyULV7nZhC7BVTmB | Y27: =IFERROR(__xludf.DUMMYFUNCTION("""COMPUTED_VALUE"""),"marcopaine@gmail.com") -> marcopaine@gmail.com | Z27: =IFERROR(__xludf.DUMMYFUNCTION("""COMPUTED_VALUE"""),890675.0) -> 890675 | AD27: =IFERROR(__xludf.DUMMYFUNCTION("""COMPUTED_VALUE"""),"RC-332_26") -> RC-332_26
A28: =AD28 -> RC-038 | B28: =IFERROR(__xludf.DUMMYFUNCTION("""COMPUTED_VALUE"""),45939.47406658565) -> 45939.474 | C28: =IFERROR(__xludf.DUMMYFUNCTION("""COMPUTED_VALUE"""),"") | D28: =IFERROR(__xludf.DUMMYFUNCTION("""COMPUTED_VALUE"""),"Leonor Ríos Morales") -> Leonor Ríos Morales | F28: =IFERROR(__xludf.DUMMYFUNCTION("""COMPUTED_VALUE"""),"8552 - 2025") -> 8552 - 2025 | J28: =IFERROR(__xludf.DUMMYFUNCTION("""COMPUTED_VALUE"""),"Campus Prieto Norte - CHS") -> Campus Prieto Norte - CHS | K28: =IFERROR(__xludf.DUMMYFUNCTION("""COMPUTED_VALUE"""),"01") -> 01 | L28: =IFERROR(__xludf.DUMMYFUNCTION("""COMPUTED_VALUE"""),"DSIETE SPA") -> DSIETE SPA | M28: =IFERROR(__xludf.DUMMYFUNCTION("""COMPUTED_VALUE"""),"77.964.311-5") -> 77.964.311-5 | N28: =IFERROR(__xludf.DUMMYFUNCTION("""COMPUTED_VALUE"""),"Daniella Vidal") -> Daniella Vidal | O28: =IFERROR(__xludf.DUMMYFUNCTION("""COMPUTED_VALUE"""),"Obras") -> Obras | R28: =IFERROR(__xludf.DUMMYFUNCTION("""COMPUTED_VALUE"""),"Exteriores") -> Exteriores | S28: =IFERROR(__xludf.DUMMYFUNCTION("""COMPUTED_VALUE"""),"Recepción de Obra - RC") -> Recepción de Obra - RC | V28: =IFERROR(__xludf.DUMMYFUNCTION("""COMPUTED_VALUE"""),"Letras volumétricas costado exterior") -> Letras volumétricas costado exterior | W28: =IFERROR(__xludf.DUMMYFUNCTION("""COMPUTED_VALUE"""),"NA") -> NA | X28: =IFERROR(__xludf.DUMMYFUNCTION("""COMPUTED_VALUE"""),"https://drive.google.com/open?id=1_h4rGzW0NLTH0vlf0RjjgDqp7D7dkD4C") -> https://drive.google.com/open?id=1_h4rGzW0NLTH0vlf0RjjgDqp7D7dkD4C | Y28: =IFERROR(__xludf.DUMMYFUNCTION("""COMPUTED_VALUE"""),"lrios@uct.cl") -> lrios@uct.cl | AD28: =IFERROR(__xludf.DUMMYFUNCTION("""COMPUTED_VALUE"""),"RC-038") -> RC-038
A29: =AD29 -> RC-331_26 | B29: =IFERROR(__xludf.DUMMYFUNCTION("""COMPUTED_VALUE"""),46225.58467123842) -> 46225.585 | C29: =IFERROR(__xludf.DUMMYFUNCTION("""COMPUTED_VALUE"""),"") | D29: =IFERROR(__xludf.DUMMYFUNCTION("""COMPUTED_VALUE"""),"Carol Huenchual Chañilao") -> Carol Huenchual Chañilao | F29: =IFERROR(__xludf.DUMMYFUNCTION("""COMPUTED_VALUE"""),"6072-2026") -> 6072-2026 | J29: =IFERROR(__xludf.DUMMYFUNCTION("""COMPUTED_VALUE"""),"Campus San Francisco - CSF") -> Campus San Francisco - CSF | K29: =IFERROR(__xludf.DUMMYFUNCTION("""COMPUTED_VALUE"""),"05") -> 05 | L29: =IFERROR(__xludf.DUMMYFUNCTION("""COMPUTED_VALUE"""),"FCM Ingenieria Spa") -> FCM Ingenieria Spa | M29: =IFERROR(__xludf.DUMMYFUNCTION("""COMPUTED_VALUE"""),"76.881.945-9") -> 76.881.945-9 | N29: =IFERROR(__xludf.DUMMYFUNCTION("""COMPUTED_VALUE"""),"Marcelo Cruces Araneda, Ingeniero Mecánico") -> Marcelo Cruces Araneda, Ingeniero Mecánico | O29: =IFERROR(__xludf.DUMMYFUNCTION("""COMPUTED_VALUE"""),"Mantenciones") -> Mantenciones | P29: =IFERROR(__xludf.DUMMYFUNCTION("""COMPUTED_VALUE"""),"Requerimientos Emergentes e Imprevistos") -> Requerimientos Emergentes e Imprevistos | V29: =IFERROR(__xludf.DUMMYFUNCTION("""COMPUTED_VALUE"""),"Limpieza de radiadores y circuito de sistema de calefacción central") -> Limpieza de radiadores y circuito de sistema de calefacción central | W29: =IFERROR(__xludf.DUMMYFUNCTION("""COMPUTED_VALUE"""),"Se pudo observar que el circuito no cuenta con purgadores automaticos, se recomienda la instalación de al menos 6 purgadores automáticos, 4 en la parte mas alta de la instalación y 2 en el colector en la zona de la caldera.") -> Se pudo observar que el circuito no cuenta con purgadores automaticos, se recomienda la instalación de al menos 6 purgadores automáticos, 4 en la parte mas alta de la instalación y 2 en el colector en la zona de la caldera. | X29: =IFERROR(__xludf.DUMMYFUNCTION("""COMPUTED_VALUE"""),"https://drive.google.com/open?id=1xrzsFx1wvmbptSS_fL9L6FSyWThUAPqC, https://drive.google.com/open?id=10ulMJfujFzsEYqNLmr_54fQe3lNgwYMR, https://drive.google.com/open?id=1_OAxXKs1Gb2_tu0GzW8YMqXrO5KsDJGO, https://drive.google.com/open?id=1Fdm2VG5nnkeMq7baA"&"UFSyluJ0NMtIqw0, https://drive.google.com/open?id=1qIoH_8MpmD0YeNgaKdkrfBnQrHVMYuwQ, https://drive.google.com/open?id=1FVBvSaIi52Y-6z_GMSuyoNxjEG5DOlLD, https://drive.google.com/open?id=14JWLA_2OveGxqysNo-mQxXMr52KC85MD, https://drive.google.com/open?id=1"&"V7hwoWy2if-SOSkGS44hpEOiHwhJ9Yx7, https://drive.google.com/open?id=1Pnm6XN0nOKFQJIPFOTo6cMvO36L8-e1_, https://drive.google.com/open?id=1_pEIsW29PlKOQUTLuXbmTvLGusbHmo41") -> https://drive.google.com/open?id=1xrzsFx1wvmbptSS_fL9L6FSyWThUAPqC, https://drive.google.com/open?id=10ulMJfujFzsEYqNLmr_54fQe3lNgwYMR, https://drive.google.com/open?id=1_OAxXKs1Gb2_tu0GzW8YMqXrO5KsDJGO, https://drive.google.com/open?id=1Fdm2VG5nnkeMq7baAUFSyluJ0NMtIqw0, https://drive.google.com/open?id=1qIoH_8MpmD0YeNgaKdkrfBnQrHVMYuwQ, https://drive.google.com/open?id=1FVBvSaIi52Y-6z_GMSuyoNxjEG5DOlLD, https://drive.google.com/open?id=14JWLA_2OveGxqysNo-mQxXMr52KC85MD, https://drive.google.com/open?id=1V7hwoWy2if-SOSkGS44hpEOiHwhJ9Yx7, https://drive.google.com/open?id=1Pnm6XN0nOKFQJIPFOTo6cMvO36L8-e1_, https://drive.google.com/open?id=1_pEIsW29PlKOQUTLuXbmTvLGusbHmo41 | Y29: =IFERROR(__xludf.DUMMYFUNCTION("""COMPUTED_VALUE"""),"marcelocruces@fcmingenieria.cl") -> marcelocruces@fcmingenieria.cl | Z29: =IFERROR(__xludf.DUMMYFUNCTION("""COMPUTED_VALUE"""),799985.0) -> 799985 | AD29: =IFERROR(__xludf.DUMMYFUNCTION("""COMPUTED_VALUE"""),"RC-331_26") -> RC-331_26
A30: =AD30 -> RC-330_26 | B30: =IFERROR(__xludf.DUMMYFUNCTION("""COMPUTED_VALUE"""),46225.57534650463) -> 46225.575 | C30: =IFERROR(__xludf.DUMMYFUNCTION("""COMPUTED_VALUE"""),"") | D30: =IFERROR(__xludf.DUMMYFUNCTION("""COMPUTED_VALUE"""),"Carol Huenchual Chañilao") -> Carol Huenchual Chañilao | F30: =IFERROR(__xludf.DUMMYFUNCTION("""COMPUTED_VALUE"""),"6070-2026") -> 6070-2026 | J30: =IFERROR(__xludf.DUMMYFUNCTION("""COMPUTED_VALUE"""),"Campus San Francisco - CSF") -> Campus San Francisco - CSF | K30: =IFERROR(__xludf.DUMMYFUNCTION("""COMPUTED_VALUE"""),"05") -> 05 | L30: =IFERROR(__xludf.DUMMYFUNCTION("""COMPUTED_VALUE"""),"FCM Ingeniería Spa") -> FCM Ingeniería Spa | M30: =IFERROR(__xludf.DUMMYFUNCTION("""COMPUTED_VALUE"""),"76.881.945-9") -> 76.881.945-9 | N30: =IFERROR(__xludf.DUMMYFUNCTION("""COMPUTED_VALUE"""),"Marcelo Cruces Araneda, Ingeniero Mecánico") -> Marcelo Cruces Araneda, Ingeniero Mecánico | O30: =IFERROR(__xludf.DUMMYFUNCTION("""COMPUTED_VALUE"""),"Mantenciones") -> Mantenciones | P30: =IFERROR(__xludf.DUMMYFUNCTION("""COMPUTED_VALUE"""),"Requerimientos Emergentes e Imprevistos") -> Requerimientos Emergentes e Imprevistos | V30: =IFERROR(__xludf.DUMMYFUNCTION("""COMPUTED_VALUE"""),"Reposición de radiador doble 500x1500") -> Reposición de radiador doble 500x1500 | W30: =IFERROR(__xludf.DUMMYFUNCTION("""COMPUTED_VALUE"""),"Se recomienda realizar una limpieza de los radiadores periódica.") -> Se recomienda realizar una limpieza de los radiadores periódica. | X30: =IFERROR(__xludf.DUMMYFUNCTION("""COMPUTED_VALUE"""),"https://drive.google.com/open?id=1NyyMwrk7ygIItgSqL4kXVkYv6ZfXkeMF") -> https://drive.google.com/open?id=1NyyMwrk7ygIItgSqL4kXVkYv6ZfXkeMF | Y30: =IFERROR(__xludf.DUMMYFUNCTION("""COMPUTED_VALUE"""),"marcelocruces@fcmingenieria.cl") -> marcelocruces@fcmingenieria.cl | Z30: =IFERROR(__xludf.DUMMYFUNCTION("""COMPUTED_VALUE"""),368900.0) -> 368900 | AD30: =IFERROR(__xludf.DUMMYFUNCTION("""COMPUTED_VALUE"""),"RC-330_26") -> RC-330_26
